Workbook

Sheet 01 ДОСЬЕ
B1: NCPD ▚ NIGHT CITY POLICE DEPARTMENT ▚ УПРАВЛЕНИЕ BORDER SECURITY ▚ 2070
B2: ФОРМА NCPD-77/Б · ДЕЛО ОБЪЕКТА · ДОСТУП: ОГРАНИЧЕННЫЙ · КОПИРОВАНИЕ БЕЗ ШТАМПА НЕДОПУСТИМО
B3: Д О С Ь Е | F3: СТАТУС: | G3: АКТИВЕН
B4: ▍▎▍▎▎▍▍▎▍▎▎▍▍▎▎▍▎▍▍▎▎▍▎▍▌▎▍▎▌▍▎▎▍▎▍▌▎▍▎▎▍▎▍▎▎▍▎▍▎▎▍▎▎▌▎▍▍ | F4: ДЕЛО № | G4: NC-2070-
B6: ПОЗЫВНОЙ (HANDLE) | D6: ИМЯ / ФАМИЛИЯ | F6: ФОТО ОБЪЕКТА (вставить изображение)
B7: РОЛЬ / АРХЕТИП | C7: Законник (Lawman) — NCPD, в отставке | D7: РАНГ РОЛИ | E7: Ранг 4 (Backup: вызов 1d10 ≤ 4)
B8: ИГРОК | D8: ВОЗРАСТ / ДАТА РОЖДЕНИЯ
B9: РОДНОЙ ЯЗЫК (4 БЕСПЛ.) | C9: Английский (родной, 4 беспл.) + Streetslang | D9: КУЛЬТУРНЫЕ КОРНИ | E9: Северная Америка, Найт-Сити
B10: РАЙОН (LOCAL EXPERT) | C10: Хейвуд — боевые зоны | D10: СТИЛЬ ОДЕЖДЫ | E10: Кожаная куртка поверх брони, зеркальные очки (Nomad Leathers)
B11: РОСТ / ВЕС / СЛОЖЕНИЕ | D11: ХРОМ НА ВИДУ | E11: Видимого функционального хрома нет: на предплечье светится выцветшая татуировка-значок, остальное внутри
B12: ОСОБЫЕ ПРИМЕТЫ | C12: Сухая правая кисть — старая работа с холодом | D12: ГОЛОС / МАНЕРА | E12: Низкий, ровный, «голос протокола» — короткие фразы
B13: СВЯЗЬ / HOLOPHONE | C13: Agent (Standard): личный номер, отвечает всегда | D13: ЖИЛЬЁ / LIFESTYLE | E13: Грузовой контейнер в боевых зонах Хейвуда (аренда) · Kibble Lifestyle
B14: СТАТУС ОБЪЕКТА: АКТИВЕН · КОНТАКТ ЧЕРЕЗ ФИКСЕРА · ДЕЛО ВЕДЁТ GM
B16: Ⅰ · ЛИЧНОСТЬ И МОТИВАЦИЯ · БЛОК ПСИХОПРОФИЛЯ
B17: ЛИЧНОСТЬ (PERSONALITY) | C17: Старый коп с протоколом вместо сердца. Говорит тихо, смотрит в глаза и почти никогда не повышает голос.
B18: ЧТО ЦЕНИТ БОЛЬШЕ ВСЕГО | C18: Порядок. Не закон — порядок: чтобы человек мог спокойно дойти до дома по своей улице.
B19: КАК ОТНОСИТСЯ К ЛЮДЯМ | C19: Считает, что большинство людей не злые, а испуганные. Ошибается реже, чем боится.
B20: МОРАЛЬНЫЙ КОМПАС (ПО ЛАЙФПАТУ) | C20: 5 — ЖЁСТКИЙ: гнёт правила и закон ради результата. Лишнего не делает, но и не мучается выбором.
B21: ЦЕЛЬ ЖИЗНИ / ЗАЧЕМ ОН В ЭТОМ | C21: Закрыть дело о корпоративном складе, из-за которого его выкинули из управления, — и вернуть себе имя.
B22: ЧЕГО НИКОГДА НЕ СДЕЛАЕТ | C22: Не тронет ребёнка. Не сдаст того, кто ему доверился, — даже если это стоило ему значка.
B23: СЛАБОСТЬ / НА ЧЁМ ЕГО ВЗЯТЬ | C23: Старые связи: звонок «Джек, надо» — и он едет, даже если понимает, что это подстава.
B25: Ⅱ · СЛУЖБА · ROLE LIFEPATH (LAWMAN / NCPD — В ОТСТАВКЕ)
B26: ДОЛЖНОСТЬ В ПОДРАЗДЕЛЕНИИ | C26: Уголовный следователь
B27: ЮРИСДИКЦИЯ ПОДРАЗДЕЛЕНИЯ | C27: Боевые зоны
B28: КОРРУМПИРОВАННОСТЬ ПОДРАЗДЕЛЕНИЯ | C28: Честная, но суровая
B29: КТО ОХОТИТСЯ НА ПОДРАЗДЕЛЕНИЕ | C29: Организованная преступность
B30: ГЛАВНАЯ ЦЕЛЬ ПОДРАЗДЕЛЕНИЯ | C30: Организованная преступность
B31: ЗА ЧТО УШЁЛ СО СЛУЖБЫ / ЧТО СЛУЧИЛОСЬ (ЕГО ВЕРСИЯ) | C31: Вёл дело о поставках оружия в боевые зоны и докопался до корпоративного склада. Сверху приказали дело закрыть — он отказался и продолжил копать. Через месяц его попросили на выход: «по собственному желанию», с пенсией и без значка. Официальная версия — «выгорание».
B32: ЧТО ОН НА САМОМ ДЕЛЕ СКРЫВАЕТ О ТОМ ДЕЛЕ | C32: Что знает, чем именно торговал склад, и что в деле есть фамилия человека, который сейчас сидит в управлении. Доказательств нет — поэтому он молчит и до сих пор жив.
B33: КАКИЕ СВЯЗИ В УПРАВЛЕНИИ ОСТАЛИСЬ (ЗВОНИТЬ МОЖНО КОМУ) | C33: Сержант из архива — достаёт копии закрытых дел за бутылку. Медэксперт со старых времён — осмотрит тихо и не оставит следов в системе.
B34: ПОДПИСКИ И РЕГУЛЯРНЫЕ ТРАТЫ (TRAUMA TEAM, ЖИЛЬЁ, ДОЛГИ) | C34: Наличных на старте нет — вышел из управления с нулём, всё до последнего евродоллара ушло в снаряжение. Жильё — контейнер в боевых зонах: жильё 1 000 €$ + Kibble 100 €$/мес = 1 100 €$ к 1-му числу каждого месяца (первый месяц покрыт). Подписок нет: Trauma Team Silver (500 €$/мес) не по карману — копит на разовый вызов с первых дел. Долгов нет, кредитная история убита вместе с карьерой.
B35: КТО НА НЕГО ОХОТИТСЯ (WHO'S GUNNING FOR YOU) | C35: Корпоративная служба безопасности того склада — и она умеет ждать. Второй в очереди — бустерганг «Ржавые Псы», которого он тогда не закрыл.
B36: РЕПУТАЦИЯ НА УЛИЦАХ / ЧЕМ ИЗВЕСТЕН | C36: В боевых зонах его знают как копа, который не брал процент и не сдавал своих.
B37: ТЕКУЩИЙ РАБОТОДАТЕЛЬ / ФИКСЕР | C37: Работает через фиксера средней руки (имя впиши сам — он ещё не назвался). Берёт и «левые» дела, если цель понятна.
B38: ПРАВИЛА РАБОТЫ (КАК БЕРЁТ КОНТРАКТЫ) | C38: Три вопроса перед делом: кто пострадает, кто платит, что будет, если он откажется.
B40: Ⅲ · ПРОШЛОЕ · GENERAL LIFEPATH
B41: СЕМЬЯ / ДЕТСТВО | C41: Вырос в боевых зонах Хейвуда: мать работала медсестрой в бесплатной клинике, отец ушёл в банду и не вернулся.
B42: СЕМЕЙНЫЙ КРИЗИС | C42: Мать погибла от шальной пули в перекрёстном огне — в тот год он и подал документы в академию NCPD.
B43: ДРУЗЬЯ | C43: Двое: сержант из архива, который всё ещё берёт трубку, и брат бывшего напарника, который его ненавидит.
B44: РОМАНТИЧЕСКИЕ СВЯЗИ | C44: Разведён. Жена не выдержала графика, ночных звонков и того, что он приносил работу домой.
B45: ВРАГИ | C45: Корпоративная безопасность (дело о складе) и бустерганг «Ржавые Псы», который он не смог закрыть по закону.
B46: ПЕРЕЛОМНЫЙ МОМЕНТ | C46: Тот день, когда он вышел из кабинета начальника после отказа закрыть дело, — и понял, что обратно дороги нет.
B48: Ⅳ · СВЯЗИ · КТО МОЖЕТ ПОМОЧЬ ИЛИ ПОДСТАВИТЬ
B49: КТО | C49: РОЛЬ В ЖИЗНИ | D49: КАК НАЙТИ / КОНТАКТ | F49: ЧЕМ ПОЛЕЗЕН | G49: ЧЕМ ОПАСЕН
B50: Сержант в архиве NCPD | C50: Старый сослуживец | D50: Бар «У Дока», Хейвуд · по вторникам | F50: Копии закрытых дел, старые адреса, кто из копов ещё на связи
B51: Медэксперт со старых дел | C51: Должник | D51: Клиника в Хейвуде, без записи | F51: Осмотрит, зашьёт и не оставит следа в системе
B52: Фиксер средней руки | C52: Работодатель | D52: Через Агента: номер знают только свои | F52: Контракты, наводки, выход на нужных людей
B53: Информатор «Птица» | C53: Осведомитель из боевых зон | D53: Уотсон, у рынка — спросить у детей | F53: Кто где стоит, кто кого заказал, что говорят на улице
B57: Ⅴ · СЛУЖЕБНАЯ СВОДКА · СЧИТАЕТСЯ АВТОМАТИЧЕСКИ
B58: HP (ТЕКУЩИЕ / МАКСИМУМ) | D58: ='02 ОСНОВА'!$D$25&" / "&'02 ОСНОВА'!$D$24
B59: ПОРОГ «СЕРЬЁЗНО РАНЕН» | D59: ='02 ОСНОВА'!$D$26
B60: СПАСБРОСОК СМЕРТИ (BODY) | D60: ='02 ОСНОВА'!$D$27&" − "&'02 ОСНОВА'!$D$28&" штраф"
B61: HUMANITY (ТЕКУЩАЯ / МАКСИМУМ) | D61: ='02 ОСНОВА'!$D$36&" / "&'02 ОСНОВА'!$D$33
B62: EMP ТЕКУЩАЯ | D62: ='02 ОСНОВА'!$D$37
B63: СОСТОЯНИЕ РАН | D63: ='02 ОСНОВА'!$G$3
B64: БРОНЯ: SP ГОЛОВЫ / ТЕЛА | D64: ='05 СНАРЯЖЕНИЕ'!$D$27&" / "&'05 СНАРЯЖЕНИЕ'!$D$28
B65: ЩИТ (HP) | D65: ='05 СНАРЯЖЕНИЕ'!$D$29
B66: ОСНОВНОЕ ОРУЖИЕ (СЛОТ 1) | D66: =IFERROR(INDEX('05 СНАРЯЖЕНИЕ'!$C$9:$C$16,MATCH(1,'05 СНАРЯЖЕНИЕ'!$K$9:$K$16,0)),"—")
B67: БАЗА АТАКИ ОСНОВНОГО (+1D10) | D67: =IFERROR(INDEX('05 СНАРЯЖЕНИЕ'!$L$9:$L$16,MATCH(1,'05 СНАРЯЖЕНИЕ'!$K$9:$K$16,0)),"—")
B68: АКТИВНЫХ КРИТ-ТРАВМ | D68: =COUNTIF('06 СОСТОЯНИЕ'!$I$8:$I$17,"Активна")
B69: НАЛИЧНЫЕ €$ (СТАРТ + ИГРА) | D69: ='05 СНАРЯЖЕНИЕ'!$D$5
B70: IP: ЗАРАБОТАНО / СВОБОДНО | D70: ='06 СОСТОЯНИЕ'!$D$61&" / "&'06 СОСТОЯНИЕ'!$D$63
B71: BACKUP: РАНГ · ТИР ПОДКРЕПЛЕНИЯ | D71: ='02 ОСНОВА'!$G$2&" → вызов 1d10 ≤ "&'02 ОСНОВА'!$G$2&"; тир: "&IF('02 ОСНОВА'!$G$2<=2,"1–2 · корпоративная охрана",IF('02 ОСНОВА'!$G$2<=4,"3–4 · патрульные",IF('02 ОСНОВА'!$G$2<=7,"5–7 · департамент шерифа",IF('02 ОСНОВА'!$G$2=8,"8 · маршал зоны восстановления",IF('02 ОСНОВА'!$G$2=9,"9 · C-SWAT","10 · национальные силы")))))
B73: Ⅵ · ЗАМЕТКИ ОТДЕЛА · СВОБОДНАЯ ЗАПИСЬ GM И ИГРОКА
B80: Ⅶ · ГРАНИЦЫ БЕЗОПАСНОСТИ (LINES / VEILS / X-CARD)
B81: СТОП-ТЕМЫ (LINES)
B82: УВОДИМ БЕЗ ДЕТАЛЕЙ (VEILS)
B84: ЗАПИСЬ ВЁЛ: ________________ ПЕЧАТЬ: NC//NET · 2070 ПОДПИСЬ GM: ________________
B85: ФАЙЛ: 01 ДОСЬЕ · ИСТОЧНИКИ: Cyberpunk RED Corebook, CEMK (2070-е), гайд «Spes Desperata»

Sheet 02 ОСНОВА
B1: ЛИСТ ПЕРСОНАЖА ▚ ОСНОВА ▚ CYBERPUNK RED / CEMK · НАЙТ-СИТИ, 2070-е
B2: ПОЗЫВНОЙ / РОЛЬ | E2: ='01 ДОСЬЕ'!C6&" · "&'01 ДОСЬЕ'!C7 | F2: РАНГ РОЛИ | G2: 4
B3: ИГРОК / СТАТУС ДЕЛА | E3: ='01 ДОСЬЕ'!C8&" · "&'01 ДОСЬЕ'!G3 | F3: СОСТОЯНИЕ РАН | G3: =IF(D25="","—",IF(D25<1,"СМЕРТЕЛЬНО РАНЕН",IF(D25<=D26,"СЕРЬЁЗНО РАНЕН",IF(D25<D24,"ЛЁГКОЕ РАНЕНИЕ","В НОРМЕ"))))
B4: КОНТАКТ / HOLOPHONE | E4: ='01 ДОСЬЕ'!C13 | F4: КИБЕРПСИХОЗ | G4: =IF(D36<0,"⚠ ПОРОГ ПРОЙДЕН",IF(D36<10,"⚠ НА ГРАНИ","—"))
B5: ЖЁЛТЫЕ ПОЛЯ — ВВОД · СЕРО-СИНИЕ — СЧИТАЕТСЯ АВТОМАТИЧЕСКИ · СТАТЫ ДАЮТ ИТОГ С УЧЁТОМ ШТРАФА БРОНИ (ЛИСТ 05)
B6: Ⅰ · ХАРАКТЕРИСТИКИ · 62 ОЧКА НА 10 СТАТ · КАЖДАЯ ОТ 2 ДО 8
B7: КОД | C7: СТАТА | D7: ЗНАЧ. | E7: БРОНЯ | F7: ИТОГ | G7: НА ЧТО ВЛИЯЕТ
B8: INT | C8: Интеллект | D8: 8 | E8: 0 | F8: =IF(D8="",0,MAX(0,D8-E8)) | G8: Ум, восприятие, обучение. База для Perception, Education, Local Expert
B9: WILL | C9: Воля | D9: 7 | E9: 0 | F9: =IF(D9="",0,MAX(0,D9-E9)) | G9: Решимость и стрессоустойчивость. Входит в расчёт HP. База для Concentr
B10: COOL | C10: Хладнокровие | D10: 7 | E10: 0 | F10: =IF(D10="",0,MAX(0,D10-E10)) | G10: Характер и харизма. База для Persuasion, Streetwise, Acting, Interroga
B11: EMP | C11: Эмпатия | D11: 5 | E11: 0 | F11: =IF(D11="",0,MIN(MAX(0,D11-E11),$D$37)) | G11: Сопереживание. База Humanity (EMP × 10) и EMP-навыков. Падает вместе с
B12: TECH | C12: Техника | D12: 3 | E12: 0 | F12: =IF(D12="",0,MAX(0,D12-E12)) | G12: Работа с инструментами и электроникой: Basic Tech, Cybertech, Weaponst
B13: REF | C13: Реакция | D13: 8 | E13: ='05 СНАРЯЖЕНИЕ'!$D$30 | F13: =IF(D13="",0,MAX(0,D13-E13)) | G13: Координация и прицеливание. Инициатива, все дальние атаки. Штраф брони
B14: LUCK | C14: Удача | D14: 2 | E14: 0 | F14: =IF(D14="",0,MAX(0,D14-E14)) | G14: Пул на любой бросок (до броска). Восстанавливается в начале следующей
B15: BODY | C15: Телосложение | D15: 8 | E15: 0 | F15: =IF(D15="",0,MAX(0,D15-E15)) | G15: Сила и живучесть. Входит в HP, задаёт спасбросок смерти. Штраф брони н
B16: DEX | C16: Ловкость | D16: 8 | E16: ='05 СНАРЯЖЕНИЕ'!$E$30 | F16: =IF(D16="",0,MAX(0,D16-E16)) | G16: Баланс, прыжки, ближний бой, уклонение. Штраф брони бьёт сюда.
B17: MOVE | C17: Скорость | D17: 6 | E17: ='05 СНАРЯЖЕНИЕ'!$F$30 | F17: =IF(D17="",0,MAX(0,D17-E17)) | G17: Перемещение: MOVE × 2 м за Move Action. Штраф брони бьёт сюда (может у
B18: РАСКИДАНО / НОРМА 62 | D18: =SUM(D8:D17) | E18: ОСТАТОК | F18: =62-SUM(D8:D17) | G18: =IF(F18=0,"✔ ровно 62 очка","свободно: "&F18&" (нужно раздать все 62)")
B19: ПРОВЕРКА | D19: =IF(AND(SUM(D8:D17)=62,MIN(D8:D17)>=2,MAX(D8:D17)<=8),"✔ 62 очка, диапазон 2–8 соблюдён","✖ ПРОВЕРЬ: сумма должна быть 62, каждая стата 2–8")
B20: Штраф брони вычитается из REF, DEX и MOVE — он берётся один раз, самый строгий из надетого (лист 05). Броня режет и навыки на этих статах автоматически (лист 03).
B22: Ⅱ · ПРОИЗВОДНЫЕ · HP, ЧЕЛОВЕЧНОСТЬ, ИНИЦИАТИВА
B23: ПОКАЗАТЕЛЬ | D23: ЗНАЧЕНИЕ | E23: ФОРМУЛА / ПРАВИЛО
B24: HP МАКСИМУМ | D24: =10+5*ROUNDUP((F15+F9)/2,0) | E24: HP = 10 + 5 × ⌈(BODY+WILL)/2⌉. Считается по ИТОГОВЫМ статам, но броня на них не влияет.
B25: HP ТЕКУЩИЕ (ВВОД) | D25: 50 | E25: Просто вписывай текущие HP. Ноль и ниже — смертельное состояние.
B26: ПОРОГ «СЕРЬЁЗНО РАНЕН» | D26: =ROUNDUP(D24/2,0) | E26: Половина максимума, округление вверх → −2 ко всем действиям.
B27: СПАСБРОСОК СМЕРТИ (BODY) | D27: =F15 | E27: 1d10 ≤ BODY − штраф. Выпало 10 — провал. Провал = смерть.
B28: ШТРАФ К СПАСБРОСКАМ (ВВОД) | D28: 0 | E28: Складывается с крит-травм (+1 за каждую такую травму) и урона.
B29: ИНИЦИАТИВА (REF + 1D10) | D29: =F13 | E29: Бросок 1d10 + это число. Combat Awareness: +1 за каждое вложенное очко в Initiative Reaction.
B30: MOVE ACTION (МЕТРЫ) | D30: =F17*2 | E30: За Move Action персонаж двигается на MOVE × 2 м. Ход = Move Action + одно действие.
B31: HUMANITY: БАЗА (EMP × 10) | D31: =D11*10 | E31: Считается от исходной EMP (колонка «ЗНАЧ.»), не от текущей.
B32: СРЕЗ МАКСИМУМА ЗА ХРОМ | D32: ='04 ХРОМ'!$I$25 | E32: −2 за каждый обычный имплант, −4 за боргвар, Fashionware не режет максимум (лист 04).
B33: HUMANITY МАКСИМУМ | D33: =D31-D32 | E33: Максимум Humanity = база − срез. Полностью вернуть можно только сняв хром.
B34: HL ВСЕГО (СРЕДНЕЕ) | D34: ='04 ХРОМ'!$H$25 | E34: Среднее значение HL каждого установленного импланта (дом-правило кампании: «7 (2d6)» = −7).
B35: ВОССТАНОВЛЕНО (ТЕРАПИЯ/ОПЫТ) | E35: Сколько Humanity вернули терапией, опытом или событиями кампании (CEMK: Humanity Gain).
B36: HUMANITY ТЕКУЩАЯ | D36: =MIN(D33,D31-D34+D35) | E36: Не может превышать максимум. Ниже 0 — киберпсихоз, лист уходит GM.
B37: EMP ТЕКУЩАЯ | D37: =MAX(0,ROUNDDOWN(D36/10,0)) | E37: Каждый раз, когда десяток Humanity падает, падает и EMP.
B38: СТАТУС HUMANITY | D38: =IF(D36<0,"⚠ КИБЕРПСИХОЗ",IF(D36<10,"⚠ НА ГРАНИ",IF(D36<20,"ПОНИЖЕННАЯ","В НОРМЕ"))) | E38: Порог киберпсихоза: 0 Humanity. EMP 0 = отстранённость, диссоциация, «люди — детали».
B40: Ⅲ · РОЛЕВАЯ СПОСОБНОСТЬ · A: SOLO — COMBAT AWARENESS · B: LAWMAN — BACKUP
B41: СПОСОБНОСТЬ | C41: ЦЕНА ЗА ЭФФЕКТ | D41: ВЛОЖЕНО ОЧКОВ | E41: ЧТО ЭТО ДАЁТ
B42: Damage Deflection | C42: 2 очка за −1 урона | D42: 0 | E42: Уменьшает первый урон раунда: 2/4/6/8/10 очков = −1…−5.
B43: Fumble Recovery | C43: 4 очка | D43: 0 | E43: Игнорируешь критический провал (1) на атаках — но 1 всё равно 1.
B44: Initiative Reaction | C44: 1 очко = +1 | D44: 0 | E44: Каждое очко даёт +1 к инициативе.
B45: Precision Attack | C45: 3 очка за +1 | D45: 0 | E45: 3/6/9 очков = +1/+2/+3 ко всем атакам.
B46: Spot Weakness | C46: 1 очко = +1 урона | D46: 0 | E46: +1 к урону первого успешного попадания в раунде (до брони).
B47: Threat Detection | C47: 1 очко = +1 | D47: 0 | E47: +1 ко всем проверкам Perception.
B48: ВЛОЖЕНО / РАНГ РОЛИ (SOLO) | D48: =SUM(D42:D47) | E48: =IF(OR(ISNUMBER(SEARCH("awman",$E$2)),ISNUMBER(SEARCH("законник",$E$2))),"Lawman: Combat Awareness не используется — твоя способность Backup (блок Ⅳ)",IF(SUM(D42:D47)=$G$2,"✔ распределено ровно по рангу",IF(SUM(D42:D47)<$G$2,"осталось очков: "&($G$2-SUM(D42:D47)),"✖ вложено больше ранга на "&(SUM(D42:D47)-$G$2)))) | F48: Расклад можно менять до боя, вне боя и в бою — но в бою это Действие. Если не меняешь — держится прежний.
B50: Ⅳ · LAWMAN · BACKUP · ВЫЗОВ ПОДКРЕПЛЕНИЯ (РАНГ = РАНГ РОЛИ)
B51: РАНГ BACKUP | D51: БОЕВОЙ № · SP · HP | E51: КТО ПРИЕДЕТ И НА ЧЁМ
B52: 1–2 | D52: 8 · 7 · 20 | E52: Корпоративная охрана: 4 местных прокат-копа, приходят пешком. Heavy Pistols, Kevlar.
B53: 3–4 | D53: 10 · 7 · 25 | E53: Патрульные: 4 копа с района на двух Compact Groundcar. Heavy Pistols, Kevlar.
B54: 5–7 | D54: 14 · 13 · 35 | E54: Департамент шерифа: 2 «маунти» на High Performance Groundcar. Heavy Pistols + Assault Rifles, Heavy Armorjack.
B55: 8 | D55: 16 · 15 · 50 | E55: Маршал зоны восстановления: один, на Superbike. Very Heavy Pistol, Assault Rifle, Grenade Launcher, Flak.
B56: 9 | D56: 15 · 18 · 35 | E56: C-SWAT: 2 бойца Psycho Squad с воздуха, на AV-4. Assault Rifles + Rocket Launchers, Metalgear.
B57: 10 | D57: 14 · 11 · 35 | E57: Национальные силы / Интерпол / Netwatch: 2 агента с AV-4. Very Heavy Pistols + Assault Rifles, Light Armorjack. Остаются до закрытия дела и считают по боевому номеру навыки Criminology, Deduction, Interrogation, Paramedic, Perception, Stealth, Tracking и др.
B58: ▪ ВЫЗОВ: Действие → бросок 1d10, успех при результате ≤ ранга Backup. Приезд — через 1d6 раундов; выпало 6 — приезжает тир на уровень выше (на 10-м ранге — две группы). Не ответили — зови в следующем ходу. Злоупотребление вызовом = разжалование или штраф от начальства.
B59: ▪ Backup атакует и защищается боевым номером (стат + навык), но НЕ уклоняется от пуль. Отставной коп (вне службы) может звать только тех, с кем сохранил отношения, — решает GM.
B61: Ⅴ · ОРУЖИЕ В РУКАХ · АВТО ИЗ ЛИСТА 05 (СЛОТ 1–4)
B62: ОРУЖИЕ | C62: УРОН | D62: ROF | E62: МАГ. | F62: НАВЫК | G62: БАЗА АТАКИ (+1D10)
B63: =IFERROR(INDEX('05 СНАРЯЖЕНИЕ'!$C$9:$C$16,MATCH(1,'05 СНАРЯЖЕНИЕ'!$K$9:$K$16,0)),"—") | C63: =IFERROR(INDEX('05 СНАРЯЖЕНИЕ'!$F$9:$F$16,MATCH(1,'05 СНАРЯЖЕНИЕ'!$K$9:$K$16,0)),"—") | D63: =IFERROR(INDEX('05 СНАРЯЖЕНИЕ'!$G$9:$G$16,MATCH(1,'05 СНАРЯЖЕНИЕ'!$K$9:$K$16,0)),"—") | E63: =IFERROR(INDEX('05 СНАРЯЖЕНИЕ'!$H$9:$H$16,MATCH(1,'05 СНАРЯЖЕНИЕ'!$K$9:$K$16,0)),"—") | F63: =IFERROR(INDEX('05 СНАРЯЖЕНИЕ'!$E$9:$E$16,MATCH(1,'05 СНАРЯЖЕНИЕ'!$K$9:$K$16,0)),"—") | G63: =IFERROR(INDEX('05 СНАРЯЖЕНИЕ'!$L$9:$L$16,MATCH(1,'05 СНАРЯЖЕНИЕ'!$K$9:$K$16,0)),"—")
B64: =IFERROR(INDEX('05 СНАРЯЖЕНИЕ'!$C$9:$C$16,MATCH(2,'05 СНАРЯЖЕНИЕ'!$K$9:$K$16,0)),"—") | C64: =IFERROR(INDEX('05 СНАРЯЖЕНИЕ'!$F$9:$F$16,MATCH(2,'05 СНАРЯЖЕНИЕ'!$K$9:$K$16,0)),"—") | D64: =IFERROR(INDEX('05 СНАРЯЖЕНИЕ'!$G$9:$G$16,MATCH(2,'05 СНАРЯЖЕНИЕ'!$K$9:$K$16,0)),"—") | E64: =IFERROR(INDEX('05 СНАРЯЖЕНИЕ'!$H$9:$H$16,MATCH(2,'05 СНАРЯЖЕНИЕ'!$K$9:$K$16,0)),"—") | F64: =IFERROR(INDEX('05 СНАРЯЖЕНИЕ'!$E$9:$E$16,MATCH(2,'05 СНАРЯЖЕНИЕ'!$K$9:$K$16,0)),"—") | G64: =IFERROR(INDEX('05 СНАРЯЖЕНИЕ'!$L$9:$L$16,MATCH(2,'05 СНАРЯЖЕНИЕ'!$K$9:$K$16,0)),"—")
B65: =IFERROR(INDEX('05 СНАРЯЖЕНИЕ'!$C$9:$C$16,MATCH(3,'05 СНАРЯЖЕНИЕ'!$K$9:$K$16,0)),"—") | C65: =IFERROR(INDEX('05 СНАРЯЖЕНИЕ'!$F$9:$F$16,MATCH(3,'05 СНАРЯЖЕНИЕ'!$K$9:$K$16,0)),"—") | D65: =IFERROR(INDEX('05 СНАРЯЖЕНИЕ'!$G$9:$G$16,MATCH(3,'05 СНАРЯЖЕНИЕ'!$K$9:$K$16,0)),"—") | E65: =IFERROR(INDEX('05 СНАРЯЖЕНИЕ'!$H$9:$H$16,MATCH(3,'05 СНАРЯЖЕНИЕ'!$K$9:$K$16,0)),"—") | F65: =IFERROR(INDEX('05 СНАРЯЖЕНИЕ'!$E$9:$E$16,MATCH(3,'05 СНАРЯЖЕНИЕ'!$K$9:$K$16,0)),"—") | G65: =IFERROR(INDEX('05 СНАРЯЖЕНИЕ'!$L$9:$L$16,MATCH(3,'05 СНАРЯЖЕНИЕ'!$K$9:$K$16,0)),"—")
B66: =IFERROR(INDEX('05 СНАРЯЖЕНИЕ'!$C$9:$C$16,MATCH(4,'05 СНАРЯЖЕНИЕ'!$K$9:$K$16,0)),"—") | C66: =IFERROR(INDEX('05 СНАРЯЖЕНИЕ'!$F$9:$F$16,MATCH(4,'05 СНАРЯЖЕНИЕ'!$K$9:$K$16,0)),"—") | D66: =IFERROR(INDEX('05 СНАРЯЖЕНИЕ'!$G$9:$G$16,MATCH(4,'05 СНАРЯЖЕНИЕ'!$K$9:$K$16,0)),"—") | E66: =IFERROR(INDEX('05 СНАРЯЖЕНИЕ'!$H$9:$H$16,MATCH(4,'05 СНАРЯЖЕНИЕ'!$K$9:$K$16,0)),"—") | F66: =IFERROR(INDEX('05 СНАРЯЖЕНИЕ'!$E$9:$E$16,MATCH(4,'05 СНАРЯЖЕНИЕ'!$K$9:$K$16,0)),"—") | G66: =IFERROR(INDEX('05 СНАРЯЖЕНИЕ'!$L$9:$L$16,MATCH(4,'05 СНАРЯЖЕНИЕ'!$K$9:$K$16,0)),"—")
B68: Ⅵ · БРОНЯ И ЗАЩИТА · АВТО ИЗ ЛИСТА 05
B69: SP ГОЛОВЫ (НАДЕТОЕ) | D69: ='05 СНАРЯЖЕНИЕ'!$C$27 | E69: В локации работает только лучший SP — он не складывается.
B70: SP ТЕЛА (НАДЕТОЕ) | D70: ='05 СНАРЯЖЕНИЕ'!$C$28 | E70: При попадании вся надетая броня в локации аблейтится одновременно.
B71: ЩИТ (HP) | D71: ='05 СНАРЯЖЕНИЕ'!$C$29 | E71: Щит держится на HP: 10 HP у обычного, 15 у усиленного.
B72: ШТРАФ БРОНИ REF / DEX / MOVE | D72: ='05 СНАРЯЖЕНИЕ'!$D$30 | E72: ='05 СНАРЯЖЕНИЕ'!$E$30 | F72: ='05 СНАРЯЖЕНИЕ'!$F$30 | G72: применяется один раз, самый строгий
B73: УКЛОНЕНИЕ ОТ ВЫСТРЕЛОВ (REF ≥ 8) | D73: =IF($F$13<8,"✖ нельзя: REF "&$F$13&" < 8 после штрафа брони","✔ можно: Evasion "&IFERROR(INDEX('03 НАВЫКИ'!$I$5:$I$76,MATCH("Evasion",'03 НАВЫКИ'!$C$5:$C$76,0)),$F$16)&" + 1d10") | E73: Уклонение от дальних атак доступно только при REF 8+ ПОСЛЕ штрафа брони: бросок DEX + Evasion + 1d10 против атаки. Тяжёлая броня (−4) лишает этой возможности — сравни цену SP и цену уклонения.
B74: Ⅶ · ПАМЯТКА БОЙЦА · 2070
B75: ▪ Ход: 1 Move Action (MOVE × 2 м) + 1 действие. Инициатива = REF + 1d10.
B76: ▪ Серьёзно ранен (HP ≤ ½): −2 ко всем действиям. Смертельно ранен (HP < 1): −4 ко всем действиям, −6 MOVE, спасбросок смерти в начале хода.
B77: ▪ Крит-травма: два и более «6» на кубах урона. Даёт +5 урона НАПРЯМУЮ в HP (SP не гасит) и эффект с листа 06.
B78: ▪ Смертельно раненый получает крит-травму от каждой атаки ближнего/дальнего боя и +1 к штрафу спасброска.
B79: ▪ REF 8+ — можно уклоняться (Evasion) от дальних атак. REF ниже — только от ближних.
B80: ▪ Прицельный выстрел в голову: −8 к атаке, урон ×2; при треснувшем черепе ×3. Прицельный в оружие/ногу: −4 (см. СПРАВКА).
B81: ▪ Укрытие бинарно: либо ты полностью за тем, что держит пулю и по тебе не попасть (урон уходит в укрытие), либо тебя видно — и тогда ты не в укрытии. Щит — подвижное укрытие: принимает весь урон в свои HP, но уклоняться с ним нельзя.
B82: ▪ Hardened / SP: урон меньше SP = 0 урона, но броня аблейтится на 1 (при пробитии — тоже на 1).
B83: ▪ LAWMAN: ранг Backup = ранг роли. Вызов подкрепления — Действие, 1d10 ≤ ранг. Отставной коп зовёт только «своих».

Sheet 03 НАВЫКИ
B1: НАВЫКИ ▚ 86 ОЧКОВ ▚ МАКСИМУМ 6 ПРИ СОЗДАНИИ ▚ МИН. 2 В 13 ОБЯЗАТЕЛЬНЫХ
B2: РАБОЧАЯ ТАБЛИЦА НАВЫКОВ · ЗАПОЛНЯЙ ТОЛЬКО СТОЛБЕЦ «УР.» | F2: РАСКИДАНО | G2: =SUM($J$5:$J$76) | H2: ОСТАТОК | I2: =86-$G$2 | J2: =IF($I$2=0,"✔ 86 очков распределены полностью",IF($I$2>0,"свободно: "&$I$2&" очков","✖ перебор на "&-$I$2&" очков"))
B3: ★ — обязательный пакет роли LAWMAN (мин. 2 каждому): Autofire (×2), Criminology, Deduction, Handgun, Interrogation, Shoulder Arms, Tracking. ☆ — пакет Solo на случай смены роли. 13 обязательных для всех: Athletics, Brawling, Concentration, Conversation, Education, Evasion, First Aid, Human Perception, Language (Streetslang), Local Expert (твой район), Perception, Persuasion, Stealth. Навыки с ×2 стоят 2 очка за уровень.
B4: ГРУППА | C4: НАВЫК | D4: СТАТА | E4: ×2 | F4: РОЛЬ | G4: УР. | H4: СТАТА | I4: БАЗА | J4: ОЧКИ | K4: СПЕЦИАЛИЗАЦИЯ | L4: ЧТО ЭТО / ЗАМЕТКА
B5: Осознание | C5: Concentration | D5: WILL | F5: ☆ | G5: 2 | H5: =IFERROR(INDEX('02 ОСНОВА'!$F$8:$F$17,MATCH($D5,'02 ОСНОВА'!$B$8:$B$17,0)),"") | I5: =IF($G5="","",$G5+IFERROR($H5,0)) | J5: =IF($G5="",0,IF($E5="×2",$G5*2,$G5)) | L5: ОБЯЗАТЕЛЬНЫЙ: минимум 2. Фокусировка и ментальный контроль, память, игнорирование отвлекающих факторов.
B6: Осознание | C6: Conceal/Reveal Object | D6: INT | H6: =IFERROR(INDEX('02 ОСНОВА'!$F$8:$F$17,MATCH($D6,'02 ОСНОВА'!$B$8:$B$17,0)),"") | I6: =IF($G6="","",$G6+IFERROR($H6,0)) | J6: =IF($G6="",0,IF($E6="×2",$G6*2,$G6)) | L6: Скрытие и поиск спрятанных объектов. Прятать оружие под одеждой и выявлять его.
B7: Осознание | C7: Lip Reading | D7: INT | H7: =IFERROR(INDEX('02 ОСНОВА'!$F$8:$F$17,MATCH($D7,'02 ОСНОВА'!$B$8:$B$17,0)),"") | I7: =IF($G7="","",$G7+IFERROR($H7,0)) | J7: =IF($G7="",0,IF($E7="×2",$G7*2,$G7)) | L7: Чтение по губам.
B8: Осознание | C8: Perception | D8: INT | F8: ☆ | G8: 6 | H8: =IFERROR(INDEX('02 ОСНОВА'!$F$8:$F$17,MATCH($D8,'02 ОСНОВА'!$B$8:$B$17,0)),"") | I8: =IF($G8="","",$G8+IFERROR($H8,0)) | J8: =IF($G8="",0,IF($E8="×2",$G8*2,$G8)) | L8: ОБЯЗАТЕЛЬНЫЙ: минимум 2. Обнаружение скрытого: улики, ловушки, крадущиеся (но не спрятанное Conceal/Reveal Object).
B9: Осознание | C9: Tracking | D9: INT | F9: ★ | G9: 4 | H9: =IFERROR(INDEX('02 ОСНОВА'!$F$8:$F$17,MATCH($D9,'02 ОСНОВА'!$B$8:$B$17,0)),"") | I9: =IF($G9="","",$G9+IFERROR($H9,0)) | J9: =IF($G9="",0,IF($E9="×2",$G9*2,$G9)) | L9: Отслеживание по следам и уликам.
B10: Тело | C10: Athletics | D10: DEX | F10: ☆ | G10: 2 | H10: =IFERROR(INDEX('02 ОСНОВА'!$F$8:$F$17,MATCH($D10,'02 ОСНОВА'!$B$8:$B$17,0)),"") | I10: =IF($G10="","",$G10+IFERROR($H10,0)) | J10: =IF($G10="",0,IF($E10="×2",$G10*2,$G10)) | L10: ОБЯЗАТЕЛЬНЫЙ: минимум 2. Прыжки, карабкание, броски, лазание, плавание, подъём вещей.
B11: Тело | C11: Contortionist | D11: DEX | H11: =IFERROR(INDEX('02 ОСНОВА'!$F$8:$F$17,MATCH($D11,'02 ОСНОВА'!$B$8:$B$17,0)),"") | I11: =IF($G11="","",$G11+IFERROR($H11,0)) | J11: =IF($G11="",0,IF($E11="×2",$G11*2,$G11)) | L11: Выбраться из наручников, протискиваться в труднодоступные места.
B12: Тело | C12: Dance | D12: DEX | H12: =IFERROR(INDEX('02 ОСНОВА'!$F$8:$F$17,MATCH($D12,'02 ОСНОВА'!$B$8:$B$17,0)),"") | I12: =IF($G12="","",$G12+IFERROR($H12,0)) | J12: =IF($G12="",0,IF($E12="×2",$G12*2,$G12)) | L12: Профессиональные танцы.
B13: Тело | C13: Endurance | D13: WILL | H13: =IFERROR(INDEX('02 ОСНОВА'!$F$8:$F$17,MATCH($D13,'02 ОСНОВА'!$B$8:$B$17,0)),"") | I13: =IF($G13="","",$G13+IFERROR($H13,0)) | J13: =IF($G13="",0,IF($E13="×2",$G13*2,$G13)) | L13: Преодоление тяжёлых условий и тягот.
B14: Тело | C14: Resist Torture/Drugs | D14: WILL | F14: ☆ | H14: =IFERROR(INDEX('02 ОСНОВА'!$F$8:$F$17,MATCH($D14,'02 ОСНОВА'!$B$8:$B$17,0)),"") | I14: =IF($G14="","",$G14+IFERROR($H14,0)) | J14: =IF($G14="",0,IF($E14="×2",$G14*2,$G14)) | L14: Сопротивление допросу, пыткам и наркотикам.
B15: Тело | C15: Stealth | D15: DEX | F15: ☆ | G15: 2 | H15: =IFERROR(INDEX('02 ОСНОВА'!$F$8:$F$17,MATCH($D15,'02 ОСНОВА'!$B$8:$B$17,0)),"") | I15: =IF($G15="","",$G15+IFERROR($H15,0)) | J15: =IF($G15="",0,IF($E15="×2",$G15*2,$G15)) | L15: ОБЯЗАТЕЛЬНЫЙ: минимум 2. Тихое перемещение и скрытность. Против — Perception.
B16: Управление | C16: Drive Land Vehicle | D16: REF | H16: =IFERROR(INDEX('02 ОСНОВА'!$F$8:$F$17,MATCH($D16,'02 ОСНОВА'!$B$8:$B$17,0)),"") | I16: =IF($G16="","",$G16+IFERROR($H16,0)) | J16: =IF($G16="",0,IF($E16="×2",$G16*2,$G16)) | L16: Вождение наземного транспорта.
B17: Управление | C17: Pilot Air Vehicle | D17: REF | E17: ×2 | H17: =IFERROR(INDEX('02 ОСНОВА'!$F$8:$F$17,MATCH($D17,'02 ОСНОВА'!$B$8:$B$17,0)),"") | I17: =IF($G17="","",$G17+IFERROR($H17,0)) | J17: =IF($G17="",0,IF($E17="×2",$G17*2,$G17))
B18: Управление | C18: Pilot Sea Vehicle | D18: REF | H18: =IFERROR(INDEX('02 ОСНОВА'!$F$8:$F$17,MATCH($D18,'02 ОСНОВА'!$B$8:$B$17,0)),"") | I18: =IF($G18="","",$G18+IFERROR($H18,0)) | J18: =IF($G18="",0,IF($E18="×2",$G18*2,$G18)) | L18: Управление водным транспортом.
B19: Управление | C19: Riding | D19: REF | H19: =IFERROR(INDEX('02 ОСНОВА'!$F$8:$F$17,MATCH($D19,'02 ОСНОВА'!$B$8:$B$17,0)),"") | I19: =IF($G19="","",$G19+IFERROR($H19,0)) | J19: =IF($G19="",0,IF($E19="×2",$G19*2,$G19)) | L19: Верховая езда на обученном животном.
B20: Образование | C20: Accounting | D20: INT | H20: =IFERROR(INDEX('02 ОСНОВА'!$F$8:$F$17,MATCH($D20,'02 ОСНОВА'!$B$8:$B$17,0)),"") | I20: =IF($G20="","",$G20+IFERROR($H20,0)) | J20: =IF($G20="",0,IF($E20="×2",$G20*2,$G20)) | L20: Бухгалтерия: липовые отчёты и их выявление, бюджет, бизнес-операции.
B21: Образование | C21: Animal Handling | D21: INT | H21: =IFERROR(INDEX('02 ОСНОВА'!$F$8:$F$17,MATCH($D21,'02 ОСНОВА'!$B$8:$B$17,0)),"") | I21: =IF($G21="","",$G21+IFERROR($H21,0)) | J21: =IF($G21="",0,IF($E21="×2",$G21*2,$G21)) | L21: Обращение, дрессировка и уход за животными.
B22: Образование | C22: Bureaucracy | D22: INT | H22: =IFERROR(INDEX('02 ОСНОВА'!$F$8:$F$17,MATCH($D22,'02 ОСНОВА'!$B$8:$B$17,0)),"") | I22: =IF($G22="","",$G22+IFERROR($H22,0)) | J22: =IF($G22="",0,IF($E22="×2",$G22*2,$G22)) | L22: Работа с бюрократией: с кем говорить и как выбивать информацию.
B23: Образование | C23: Business | D23: INT | H23: =IFERROR(INDEX('02 ОСНОВА'!$F$8:$F$17,MATCH($D23,'02 ОСНОВА'!$B$8:$B$17,0)),"") | I23: =IF($G23="","",$G23+IFERROR($H23,0)) | J23: =IF($G23="",0,IF($E23="×2",$G23*2,$G23)) | L23: Бизнес-практики, спрос и предложение, закупки, продажи, маркетинг.
B24: Образование | C24: Composition | D24: INT | H24: =IFERROR(INDEX('02 ОСНОВА'!$F$8:$F$17,MATCH($D24,'02 ОСНОВА'!$B$8:$B$17,0)),"") | I24: =IF($G24="","",$G24+IFERROR($H24,0)) | J24: =IF($G24="",0,IF($E24="×2",$G24*2,$G24)) | L24: Профессиональное написание песен, статей, историй.
B25: Образование | C25: Criminology | D25: INT | F25: ★ | G25: 5 | H25: =IFERROR(INDEX('02 ОСНОВА'!$F$8:$F$17,MATCH($D25,'02 ОСНОВА'!$B$8:$B$17,0)),"") | I25: =IF($G25="","",$G25+IFERROR($H25,0)) | J25: =IF($G25="",0,IF($E25="×2",$G25*2,$G25)) | L25: Поиск улик: отпечатки, баллистика, полицейские базы.
B26: Образование | C26: Cryptography | D26: INT | H26: =IFERROR(INDEX('02 ОСНОВА'!$F$8:$F$17,MATCH($D26,'02 ОСНОВА'!$B$8:$B$17,0)),"") | I26: =IF($G26="","",$G26+IFERROR($H26,0)) | J26: =IF($G26="",0,IF($E26="×2",$G26*2,$G26)) | L26: Шифрование и расшифровка сообщений.
B27: Образование | C27: Deduction | D27: INT | F27: ★ | G27: 5 | H27: =IFERROR(INDEX('02 ОСНОВА'!$F$8:$F$17,MATCH($D27,'02 ОСНОВА'!$B$8:$B$17,0)),"") | I27: =IF($G27="","",$G27+IFERROR($H27,0)) | J27: =IF($G27="",0,IF($E27="×2",$G27*2,$G27)) | L27: Приходить к неочевидным выводам из улик (и мед. диагнозам).
B28: Образование | C28: Education | D28: INT | F28: ☆ | G28: 2 | H28: =IFERROR(INDEX('02 ОСНОВА'!$F$8:$F$17,MATCH($D28,'02 ОСНОВА'!$B$8:$B$17,0)),"") | I28: =IF($G28="","",$G28+IFERROR($H28,0)) | J28: =IF($G28="",0,IF($E28="×2",$G28*2,$G28)) | L28: ОБЯЗАТЕЛЬНЫЙ: минимум 2. Общая эрудиция: чтение, письмо, базовые вычисления, история.
B29: Образование | C29: Gamble | D29: INT | H29: =IFERROR(INDEX('02 ОСНОВА'!$F$8:$F$17,MATCH($D29,'02 ОСНОВА'!$B$8:$B$17,0)),"") | I29: =IF($G29="","",$G29+IFERROR($H29,0)) | J29: =IF($G29="",0,IF($E29="×2",$G29*2,$G29)) | L29: Вероятности и стратегия в азартных играх.
B30: Образование | C30: Language | D30: INT | F30: ☆ | G30: 2 | H30: =IFERROR(INDEX('02 ОСНОВА'!$F$8:$F$17,MATCH($D30,'02 ОСНОВА'!$B$8:$B$17,0)),"") | I30: =IF($G30="","",$G30+IFERROR($H30,0)) | J30: =IF($G30="",0,IF($E30="×2",$G30*2,$G30)) | K30: Streetslang | L30: ОБЯЗАТЕЛЬНЫЙ: минимум 2. Конкретный язык (выбирается при прокачке).
B31: Образование | C31: Library Search | D31: INT | H31: =IFERROR(INDEX('02 ОСНОВА'!$F$8:$F$17,MATCH($D31,'02 ОСНОВА'!$B$8:$B$17,0)),"") | I31: =IF($G31="","",$G31+IFERROR($H31,0)) | J31: =IF($G31="",0,IF($E31="×2",$G31*2,$G31)) | L31: Поиск по базам данных, Data Pool, библиотекам.
B32: Образование | C32: Local Expert | D32: INT | F32: ☆ | G32: 2 | H32: =IFERROR(INDEX('02 ОСНОВА'!$F$8:$F$17,MATCH($D32,'02 ОСНОВА'!$B$8:$B$17,0)),"") | I32: =IF($G32="","",$G32+IFERROR($H32,0)) | J32: =IF($G32="",0,IF($E32="×2",$G32*2,$G32)) | K32: Хейвуд | L32: ОБЯЗАТЕЛЬНЫЙ: минимум 2. Знание местности и целей группировок. Выберите район.
B33: Образование | C33: Science | D33: INT | H33: =IFERROR(INDEX('02 ОСНОВА'!$F$8:$F$17,MATCH($D33,'02 ОСНОВА'!$B$8:$B$17,0)),"") | I33: =IF($G33="","",$G33+IFERROR($H33,0)) | J33: =IF($G33="",0,IF($E33="×2",$G33*2,$G33)) | L33: Эксперименты, научные работы. Выберите область: геология, химия, биология…
B34: Образование | C34: Tactics | D34: INT | F34: ☆ | H34: =IFERROR(INDEX('02 ОСНОВА'!$F$8:$F$17,MATCH($D34,'02 ОСНОВА'!$B$8:$B$17,0)),"") | I34: =IF($G34="","",$G34+IFERROR($H34,0)) | J34: =IF($G34="",0,IF($E34="×2",$G34*2,$G34)) | L34: Руководство большими битвами: как поведут себя силы противника.
B35: Образование | C35: Wilderness Survival | D35: INT | H35: =IFERROR(INDEX('02 ОСНОВА'!$F$8:$F$17,MATCH($D35,'02 ОСНОВА'!$B$8:$B$17,0)),"") | I35: =IF($G35="","",$G35+IFERROR($H35,0)) | J35: =IF($G35="",0,IF($E35="×2",$G35*2,$G35)) | L35: Выживание в дикой природе.
B36: Бой | C36: Brawling | D36: DEX | F36: ☆ | G36: 5 | H36: =IFERROR(INDEX('02 ОСНОВА'!$F$8:$F$17,MATCH($D36,'02 ОСНОВА'!$B$8:$B$17,0)),"") | I36: =IF($G36="","",$G36+IFERROR($H36,0)) | J36: =IF($G36="",0,IF($E36="×2",$G36*2,$G36)) | L36: ОБЯЗАТЕЛЬНЫЙ: минимум 2. Уличные драки и захваты грубой силой.
B37: Бой | C37: Evasion | D37: DEX | F37: ☆ | G37: 6 | H37: =IFERROR(INDEX('02 ОСНОВА'!$F$8:$F$17,MATCH($D37,'02 ОСНОВА'!$B$8:$B$17,0)),"") | I37: =IF($G37="","",$G37+IFERROR($H37,0)) | J37: =IF($G37="",0,IF($E37="×2",$G37*2,$G37)) | L37: ОБЯЗАТЕЛЬНЫЙ: минимум 2. Уход с линии атаки. С REF 8+ — уклонение и от дальнего боя.
B38: Бой | C38: Martial Arts | D38: DEX | E38: ×2 | G38: 5 | H38: =IFERROR(INDEX('02 ОСНОВА'!$F$8:$F$17,MATCH($D38,'02 ОСНОВА'!$B$8:$B$17,0)),"") | I38: =IF($G38="","",$G38+IFERROR($H38,0)) | J38: =IF($G38="",0,IF($E38="×2",$G38*2,$G38)) | K38: Thamoc | L38: выбери вариант
B39: Бой | C39: Melee Weapon | D39: DEX | F39: ☆ | H39: =IFERROR(INDEX('02 ОСНОВА'!$F$8:$F$17,MATCH($D39,'02 ОСНОВА'!$B$8:$B$17,0)),"") | I39: =IF($G39="","",$G39+IFERROR($H39,0)) | J39: =IF($G39="",0,IF($E39="×2",$G39*2,$G39)) | L39: Орудование оружием ближнего боя.
B40: Выступление | C40: Acting | D40: COOL | H40: =IFERROR(INDEX('02 ОСНОВА'!$F$8:$F$17,MATCH($D40,'02 ОСНОВА'!$B$8:$B$17,0)),"") | I40: =IF($G40="","",$G40+IFERROR($H40,0)) | J40: =IF($G40="",0,IF($E40="×2",$G40*2,$G40)) | L40: Отыгрыш роли, маскировка под другого, изображение эмоций.
B41: Выступление | C41: Play Instrument | D41: TECH | H41: =IFERROR(INDEX('02 ОСНОВА'!$F$8:$F$17,MATCH($D41,'02 ОСНОВА'!$B$8:$B$17,0)),"") | I41: =IF($G41="","",$G41+IFERROR($H41,0)) | J41: =IF($G41="",0,IF($E41="×2",$G41*2,$G41)) | L41: Профессиональная игра: пение, гитара, барабаны, скрипка, пианино…
B42: Стрелковое | C42: Archery | D42: REF | H42: =IFERROR(INDEX('02 ОСНОВА'!$F$8:$F$17,MATCH($D42,'02 ОСНОВА'!$B$8:$B$17,0)),"") | I42: =IF($G42="","",$G42+IFERROR($H42,0)) | J42: =IF($G42="",0,IF($E42="×2",$G42*2,$G42)) | L42: Стрельба из оружия на стрелах и болтах.
B43: Стрелковое | C43: Autofire | D43: REF | E43: ×2 | F43: ★ | G43: 2 | H43: =IFERROR(INDEX('02 ОСНОВА'!$F$8:$F$17,MATCH($D43,'02 ОСНОВА'!$B$8:$B$17,0)),"") | I43: =IF($G43="","",$G43+IFERROR($H43,0)) | J43: =IF($G43="",0,IF($E43="×2",$G43*2,$G43))
B44: Стрелковое | C44: Handgun | D44: REF | F44: ★ | G44: 6 | H44: =IFERROR(INDEX('02 ОСНОВА'!$F$8:$F$17,MATCH($D44,'02 ОСНОВА'!$B$8:$B$17,0)),"") | I44: =IF($G44="","",$G44+IFERROR($H44,0)) | J44: =IF($G44="",0,IF($E44="×2",$G44*2,$G44)) | L44: Одноручное оружие пистолетного типа.
B45: Стрелковое | C45: Heavy Weapons | D45: REF | E45: ×2 | H45: =IFERROR(INDEX('02 ОСНОВА'!$F$8:$F$17,MATCH($D45,'02 ОСНОВА'!$B$8:$B$17,0)),"") | I45: =IF($G45="","",$G45+IFERROR($H45,0)) | J45: =IF($G45="",0,IF($E45="×2",$G45*2,$G45))
B46: Стрелковое | C46: Shoulder Arms | D46: REF | F46: ★ | G46: 5 | H46: =IFERROR(INDEX('02 ОСНОВА'!$F$8:$F$17,MATCH($D46,'02 ОСНОВА'!$B$8:$B$17,0)),"") | I46: =IF($G46="","",$G46+IFERROR($H46,0)) | J46: =IF($G46="",0,IF($E46="×2",$G46*2,$G46)) | L46: Двуручное оружие с плечевым упором: винтовки, дробовики.
B47: Социальные | C47: Bribery | D47: COOL | H47: =IFERROR(INDEX('02 ОСНОВА'!$F$8:$F$17,MATCH($D47,'02 ОСНОВА'!$B$8:$B$17,0)),"") | I47: =IF($G47="","",$G47+IFERROR($H47,0)) | J47: =IF($G47="",0,IF($E47="×2",$G47*2,$G47)) | L47: Когда, как и сколько давать на лапу.
B48: Социальные | C48: Conversation | D48: EMP | F48: ☆ | G48: 2 | H48: =IFERROR(INDEX('02 ОСНОВА'!$F$8:$F$17,MATCH($D48,'02 ОСНОВА'!$B$8:$B$17,0)),"") | I48: =IF($G48="","",$G48+IFERROR($H48,0)) | J48: =IF($G48="",0,IF($E48="×2",$G48*2,$G48)) | L48: ОБЯЗАТЕЛЬНЫЙ: минимум 2. Выуживание информации из людей без их ведома.
B49: Социальные | C49: Human Perception | D49: EMP | F49: ☆ | G49: 2 | H49: =IFERROR(INDEX('02 ОСНОВА'!$F$8:$F$17,MATCH($D49,'02 ОСНОВА'!$B$8:$B$17,0)),"") | I49: =IF($G49="","",$G49+IFERROR($H49,0)) | J49: =IF($G49="",0,IF($E49="×2",$G49*2,$G49)) | L49: ОБЯЗАТЕЛЬНЫЙ: минимум 2. Чтение лиц и невербальных сигналов, выявление лжи.
B50: Социальные | C50: Interrogation | D50: COOL | F50: ★ | G50: 5 | H50: =IFERROR(INDEX('02 ОСНОВА'!$F$8:$F$17,MATCH($D50,'02 ОСНОВА'!$B$8:$B$17,0)),"") | I50: =IF($G50="","",$G50+IFERROR($H50,0)) | J50: =IF($G50="",0,IF($E50="×2",$G50*2,$G50)) | L50: Выбивание информации силой.
B51: Социальные | C51: Persuasion | D51: COOL | F51: ☆ | G51: 5 | H51: =IFERROR(INDEX('02 ОСНОВА'!$F$8:$F$17,MATCH($D51,'02 ОСНОВА'!$B$8:$B$17,0)),"") | I51: =IF($G51="","",$G51+IFERROR($H51,0)) | J51: =IF($G51="",0,IF($E51="×2",$G51*2,$G51)) | L51: ОБЯЗАТЕЛЬНЫЙ: минимум 2. Убеждение и влияние на людей.
B52: Социальные | C52: Personal Grooming | D52: COOL | H52: =IFERROR(INDEX('02 ОСНОВА'!$F$8:$F$17,MATCH($D52,'02 ОСНОВА'!$B$8:$B$17,0)),"") | I52: =IF($G52="","",$G52+IFERROR($H52,0)) | J52: =IF($G52="",0,IF($E52="×2",$G52*2,$G52)) | L52: Уход за собой для подчёркивания привлекательности.
B53: Социальные | C53: Streetwise | D53: COOL | G53: 2 | H53: =IFERROR(INDEX('02 ОСНОВА'!$F$8:$F$17,MATCH($D53,'02 ОСНОВА'!$B$8:$B$17,0)),"") | I53: =IF($G53="","",$G53+IFERROR($H53,0)) | J53: =IF($G53="",0,IF($E53="×2",$G53*2,$G53)) | L53: Связи для нелегальных товаров, общение с криминалом, выживание в плохом районе.
B54: Социальные | C54: Trading | D54: COOL | H54: =IFERROR(INDEX('02 ОСНОВА'!$F$8:$F$17,MATCH($D54,'02 ОСНОВА'!$B$8:$B$17,0)),"") | I54: =IF($G54="","",$G54+IFERROR($H54,0)) | J54: =IF($G54="",0,IF($E54="×2",$G54*2,$G54)) | L54: Выгодные сделки с продавцами и покупателями.
B55: Социальные | C55: Wardrobe & Style | D55: COOL | H55: =IFERROR(INDEX('02 ОСНОВА'!$F$8:$F$17,MATCH($D55,'02 ОСНОВА'!$B$8:$B$17,0)),"") | I55: =IF($G55="","",$G55+IFERROR($H55,0)) | J55: =IF($G55="",0,IF($E55="×2",$G55*2,$G55)) | L55: Выбор одежды и умение её носить.
B56: Технические | C56: Air Vehicle Tech | D56: TECH | H56: =IFERROR(INDEX('02 ОСНОВА'!$F$8:$F$17,MATCH($D56,'02 ОСНОВА'!$B$8:$B$17,0)),"") | I56: =IF($G56="","",$G56+IFERROR($H56,0)) | J56: =IF($G56="",0,IF($E56="×2",$G56*2,$G56)) | L56: Ремонт и обслуживание воздушного транспорта.
B57: Технические | C57: Basic Tech | D57: TECH | H57: =IFERROR(INDEX('02 ОСНОВА'!$F$8:$F$17,MATCH($D57,'02 ОСНОВА'!$B$8:$B$17,0)),"") | I57: =IF($G57="","",$G57+IFERROR($H57,0)) | J57: =IF($G57="",0,IF($E57="×2",$G57*2,$G57)) | L57: Ремонт простых электронных и механических устройств.
B58: Технические | C58: Cybertech | D58: TECH | H58: =IFERROR(INDEX('02 ОСНОВА'!$F$8:$F$17,MATCH($D58,'02 ОСНОВА'!$B$8:$B$17,0)),"") | I58: =IF($G58="","",$G58+IFERROR($H58,0)) | J58: =IF($G58="",0,IF($E58="×2",$G58*2,$G58)) | L58: Ремонт кибернетики и имплантов.
B59: Технические | C59: Demolitions | D59: TECH | E59: ×2 | H59: =IFERROR(INDEX('02 ОСНОВА'!$F$8:$F$17,MATCH($D59,'02 ОСНОВА'!$B$8:$B$17,0)),"") | I59: =IF($G59="","",$G59+IFERROR($H59,0)) | J59: =IF($G59="",0,IF($E59="×2",$G59*2,$G59))
B60: Технические | C60: Electronics/Security Tech | D60: TECH | E60: ×2 | H60: =IFERROR(INDEX('02 ОСНОВА'!$F$8:$F$17,MATCH($D60,'02 ОСНОВА'!$B$8:$B$17,0)),"") | I60: =IF($G60="","",$G60+IFERROR($H60,0)) | J60: =IF($G60="",0,IF($E60="×2",$G60*2,$G60))
B61: Технические | C61: First Aid | D61: TECH | F61: ☆ | G61: 2 | H61: =IFERROR(INDEX('02 ОСНОВА'!$F$8:$F$17,MATCH($D61,'02 ОСНОВА'!$B$8:$B$17,0)),"") | I61: =IF($G61="","",$G61+IFERROR($H61,0)) | J61: =IF($G61="",0,IF($E61="×2",$G61*2,$G61)) | L61: ОБЯЗАТЕЛЬНЫЙ: минимум 2. Первая помощь: купирование простых крит. травм, поддержание жизни.
B62: Технические | C62: Forgery | D62: TECH | H62: =IFERROR(INDEX('02 ОСНОВА'!$F$8:$F$17,MATCH($D62,'02 ОСНОВА'!$B$8:$B$17,0)),"") | I62: =IF($G62="","",$G62+IFERROR($H62,0)) | J62: =IF($G62="",0,IF($E62="×2",$G62*2,$G62)) | L62: Создание и выявление поддельных документов.
B63: Технические | C63: Land Vehicle Tech | D63: TECH | H63: =IFERROR(INDEX('02 ОСНОВА'!$F$8:$F$17,MATCH($D63,'02 ОСНОВА'!$B$8:$B$17,0)),"") | I63: =IF($G63="","",$G63+IFERROR($H63,0)) | J63: =IF($G63="",0,IF($E63="×2",$G63*2,$G63)) | L63: Ремонт и обслуживание наземного транспорта.
B64: Технические | C64: Paint/Draw/Sculpt | D64: TECH | H64: =IFERROR(INDEX('02 ОСНОВА'!$F$8:$F$17,MATCH($D64,'02 ОСНОВА'!$B$8:$B$17,0)),"") | I64: =IF($G64="","",$G64+IFERROR($H64,0)) | J64: =IF($G64="",0,IF($E64="×2",$G64*2,$G64)) | L64: Профессиональное рисование, живопись, скульптура.
B65: Технические | C65: Paramedic | D65: TECH | E65: ×2 | H65: =IFERROR(INDEX('02 ОСНОВА'!$F$8:$F$17,MATCH($D65,'02 ОСНОВА'!$B$8:$B$17,0)),"") | I65: =IF($G65="","",$G65+IFERROR($H65,0)) | J65: =IF($G65="",0,IF($E65="×2",$G65*2,$G65))
B66: Технические | C66: Photography/Film | D66: TECH | H66: =IFERROR(INDEX('02 ОСНОВА'!$F$8:$F$17,MATCH($D66,'02 ОСНОВА'!$B$8:$B$17,0)),"") | I66: =IF($G66="","",$G66+IFERROR($H66,0)) | J66: =IF($G66="",0,IF($E66="×2",$G66*2,$G66)) | L66: Фото, видео и брейндансы.
B67: Технические | C67: Pick Lock | D67: TECH | H67: =IFERROR(INDEX('02 ОСНОВА'!$F$8:$F$17,MATCH($D67,'02 ОСНОВА'!$B$8:$B$17,0)),"") | I67: =IF($G67="","",$G67+IFERROR($H67,0)) | J67: =IF($G67="",0,IF($E67="×2",$G67*2,$G67)) | L67: Взлом неэлектронных замков.
B68: Технические | C68: Pick Pocket | D68: TECH | H68: =IFERROR(INDEX('02 ОСНОВА'!$F$8:$F$17,MATCH($D68,'02 ОСНОВА'!$B$8:$B$17,0)),"") | I68: =IF($G68="","",$G68+IFERROR($H68,0)) | J68: =IF($G68="",0,IF($E68="×2",$G68*2,$G68)) | L68: Скрытное извлечение предметов с людей, мелкие кражи.
B69: Технические | C69: Sea Vehicle Tech | D69: TECH | H69: =IFERROR(INDEX('02 ОСНОВА'!$F$8:$F$17,MATCH($D69,'02 ОСНОВА'!$B$8:$B$17,0)),"") | I69: =IF($G69="","",$G69+IFERROR($H69,0)) | J69: =IF($G69="",0,IF($E69="×2",$G69*2,$G69)) | L69: Ремонт и обслуживание водного транспорта.
B70: Технические | C70: Weaponstech | D70: TECH | H70: =IFERROR(INDEX('02 ОСНОВА'!$F$8:$F$17,MATCH($D70,'02 ОСНОВА'!$B$8:$B$17,0)),"") | I70: =IF($G70="","",$G70+IFERROR($H70,0)) | J70: =IF($G70="",0,IF($E70="×2",$G70*2,$G70)) | L70: Ремонт и обслуживание оружия всех видов.
B71: СВОЙ | H71: =IFERROR(INDEX('02 ОСНОВА'!$F$8:$F$17,MATCH($D71,'02 ОСНОВА'!$B$8:$B$17,0)),"") | I71: =IF($G71="","",$G71+IFERROR($H71,0)) | J71: =IF($G71="",0,IF($E71="×2",$G71*2,$G71)) | L71: свободная строка: домашние навыки, арт-скиллы, хобби
B72: СВОЙ | H72: =IFERROR(INDEX('02 ОСНОВА'!$F$8:$F$17,MATCH($D72,'02 ОСНОВА'!$B$8:$B$17,0)),"") | I72: =IF($G72="","",$G72+IFERROR($H72,0)) | J72: =IF($G72="",0,IF($E72="×2",$G72*2,$G72)) | L72: свободная строка: домашние навыки, арт-скиллы, хобби
B73: СВОЙ | H73: =IFERROR(INDEX('02 ОСНОВА'!$F$8:$F$17,MATCH($D73,'02 ОСНОВА'!$B$8:$B$17,0)),"") | I73: =IF($G73="","",$G73+IFERROR($H73,0)) | J73: =IF($G73="",0,IF($E73="×2",$G73*2,$G73)) | L73: свободная строка: домашние навыки, арт-скиллы, хобби
B74: СВОЙ | H74: =IFERROR(INDEX('02 ОСНОВА'!$F$8:$F$17,MATCH($D74,'02 ОСНОВА'!$B$8:$B$17,0)),"") | I74: =IF($G74="","",$G74+IFERROR($H74,0)) | J74: =IF($G74="",0,IF($E74="×2",$G74*2,$G74)) | L74: свободная строка: домашние навыки, арт-скиллы, хобби
B75: СВОЙ | H75: =IFERROR(INDEX('02 ОСНОВА'!$F$8:$F$17,MATCH($D75,'02 ОСНОВА'!$B$8:$B$17,0)),"") | I75: =IF($G75="","",$G75+IFERROR($H75,0)) | J75: =IF($G75="",0,IF($E75="×2",$G75*2,$G75)) | L75: свободная строка: домашние навыки, арт-скиллы, хобби
B76: СВОЙ | H76: =IFERROR(INDEX('02 ОСНОВА'!$F$8:$F$17,MATCH($D76,'02 ОСНОВА'!$B$8:$B$17,0)),"") | I76: =IF($G76="","",$G76+IFERROR($H76,0)) | J76: =IF($G76="",0,IF($E76="×2",$G76*2,$G76)) | L76: свободная строка: домашние навыки, арт-скиллы, хобби
B78: Ⅰ · БАЗОВЫЕ ОБЯЗАТЕЛЬНЫЕ НАВЫКИ — 13 ШТУК, МИНИМУМ 2 КАЖДОМУ (ОБЩИЕ ДЛЯ ВСЕХ РОЛЕЙ)
B79: ОБЯЗАТЕЛЬНЫЙ НАВЫК | D79: УР. | E79: СТАТУС | F79: ЧТО ДАЁТ / НАПОМИНАНИЕ
B80: Athletics | D80: =IFERROR(INDEX($G$5:$G$76,MATCH("Athletics",$C$5:$C$76,0)),0) | E80: =IF($D80>=2,"✔","✖ мало") | F80: Прыжки, лазание, броски, плавание — Move Action вне боя и половина трюков.
B81: Brawling | D81: =IFERROR(INDEX($G$5:$G$76,MATCH("Brawling",$C$5:$C$76,0)),0) | E81: =IF($D81>=2,"✔","✖ мало") | F81: Драка руками/ногами, Grab, Choke. Нужен, даже если ты «стрелок».
B82: Concentration | D82: =IFERROR(INDEX($G$5:$G$76,MATCH("Concentration",$C$5:$C$76,0)),0) | E82: =IF($D82>=2,"✔","✖ мало") | F82: Фокус, память, сопротивление отвлечению и подавлению.
B83: Conversation | D83: =IFERROR(INDEX($G$5:$G$76,MATCH("Conversation",$C$5:$C$76,0)),0) | E83: =IF($D83>=2,"✔","✖ мало") | F83: Вытягивать информацию из людей, не выдавая себя.
B84: Education | D84: =IFERROR(INDEX($G$5:$G$76,MATCH("Education",$C$5:$C$76,0)),0) | E84: =IF($D84>=2,"✔","✖ мало") | F84: Эрудиция: чтение, письмо, история, базовые вычисления.
B85: Evasion | D85: =IFERROR(INDEX($G$5:$G$76,MATCH("Evasion",$C$5:$C$76,0)),0) | E85: =IF($D85>=2,"✔","✖ мало") | F85: Уклонение. С REF 8+ — от дальних атак тоже.
B86: First Aid | D86: =IFERROR(INDEX($G$5:$G$76,MATCH("First Aid",$C$5:$C$76,0)),0) | E86: =IF($D86>=2,"✔","✖ мало") | F86: Стабилизация ран, купирование простых крит-травм.
B87: Human Perception | D87: =IFERROR(INDEX($G$5:$G$76,MATCH("Human Perception",$C$5:$C$76,0)),0) | E87: =IF($D87>=2,"✔","✖ мало") | F87: Читать лица, ловить ложь. Ключевой социальный навык: и в допросе, и на переговорах.
B88: Language | D88: =IFERROR(INDEX($G$5:$G$76,MATCH("Language",$C$5:$C$76,0)),0) | E88: =IF($D88>=2,"✔","✖ мало") | F88: Streetslang — минимум 2. Родной язык обычно 4 (бесплатно от Lifepath).
B89: Local Expert | D89: =IFERROR(INDEX($G$5:$G$76,MATCH("Local Expert",$C$5:$C$76,0)),0) | E89: =IF($D89>=2,"✔","✖ мало") | F89: Свой район: кто держит улицу, где можно спрятаться и пересидеть.
B90: Perception | D90: =IFERROR(INDEX($G$5:$G$76,MATCH("Perception",$C$5:$C$76,0)),0) | E90: =IF($D90>=2,"✔","✖ мало") | F90: Замечать засады, скрытое, слежку. Твой главный рабочий навык.
B91: Persuasion | D91: =IFERROR(INDEX($G$5:$G$76,MATCH("Persuasion",$C$5:$C$76,0)),0) | E91: =IF($D91>=2,"✔","✖ мало") | F91: Убеждать, договариваться, выкручиваться на переговорах.
B92: Stealth | D92: =IFERROR(INDEX($G$5:$G$76,MATCH("Stealth",$C$5:$C$76,0)),0) | E92: =IF($D92>=2,"✔","✖ мало") | F92: Подход, засада, уход с места работы.
B93: ВЫПОЛНЕНО | D93: =COUNTIF($E$80:$E$92,"✔") | E93: из 13 | F93: =IF($D$93=13,"✔ все обязательные навыки закрыты","✖ не закрыто обязательных: "&(13-$D$93))
B94: Ⅱ · ОБЯЗАТЕЛЬНЫЙ ПАКЕТ РОЛИ LAWMAN — МИНИМУМ 2 КАЖДОМУ (BACKUP ДЕРЖИТСЯ НА ЭТИХ НАВЫКАХ)
B95: НАВЫК РОЛИ | D95: УР. | E95: СТАТУС | F95: ЗАЧЕМ КОПУ
B96: Autofire | D96: =IFERROR(INDEX($G$5:$G$76,MATCH("Autofire",$C$5:$C$76,0)),0) | E96: =IF($D96>=2,"✔","✖ мало")
B97: Criminology | D97: =IFERROR(INDEX($G$5:$G$76,MATCH("Criminology",$C$5:$C$76,0)),0) | E97: =IF($D97>=2,"✔","✖ мало") | F97: Читать место преступления, вязать улики с известными бандами и «почерками».
B98: Deduction | D98: =IFERROR(INDEX($G$5:$G$76,MATCH("Deduction",$C$5:$C$76,0)),0) | E98: =IF($D98>=2,"✔","✖ мало") | F98: Собирать выводы из мелочей: допросы, логи, камеры, опись изъятого.
B99: Handgun | D99: =IFERROR(INDEX($G$5:$G$76,MATCH("Handgun",$C$5:$C$76,0)),0) | E99: =IF($D99>=2,"✔","✖ мало") | F99: Табельный пистолет — то, что всегда с собой, даже вне службы.
B100: Interrogation | D100: =IFERROR(INDEX($G$5:$G$76,MATCH("Interrogation",$C$5:$C$76,0)),0) | E100: =IF($D100>=2,"✔","✖ мало") | F100: Разговорить задержанного: запугать, припереть к фактам, вытянуть имена.
B101: Shoulder Arms | D101: =IFERROR(INDEX($G$5:$G$76,MATCH("Shoulder Arms",$C$5:$C$76,0)),0) | E101: =IF($D101>=2,"✔","✖ мало") | F101: Винтовки, дробовики, пулемёты — ствол, который коп берёт из оружейки.
...

Sheet 04 ХРОМ
B1: КИБЕРНЕТИКА ▚ ЮГАС / ХРОМ ▚ 2070: ВЕСЬ НЕМЕДИЦИНСКИЙ ХРОМ ТРЕБУЕТ NEUROPORT
B2: HL СЧИТАЕТСЯ ПО СРЕДНЕМУ ЗНАЧЕНИЮ (7 (2D6) → 7) · СРЕЗ МАКСИМУМА: −2 ОБЫЧНЫЙ, −4 БОРГВАР | G2: HL: | H2: =$H$25 | I2: СРЕЗ: | J2: =$I$25 | K2: €$ В БЮДЖЕТ: | L2: =SUM($M$5:$M$24)+SUM($N$5:$N$24)
B3: Пиши название как в КАТАЛОГЕ — категория, цена, HL, срез и клиника подтянутся сами. Столбец «СЛОТ» — куда ставится: нейролинк, правый киберарм, опция 1 и т.п. В бюджет листа 05 попадают только отмеченные «Да» и только то, чего ещё нет в инвентаре: «В БЮДЖЕТ €$» — в стартовые 2550, «СТИЛЬ €$» — Fashionware в 800. Neuroport при создании: 0 €$ и 0 HL.
B4: № | C4: НАЗВАНИЕ (КАК В КАТАЛОГЕ) | D4: КАТЕГОРИЯ | E4: ПОДТИП | F4: СЛОТ / КУДА | G4: ЦЕНА €$ | H4: HL | I4: СРЕЗ | J4: УСТАНОВЛЕН | K4: КЛИНИКА | L4: ЭФФЕКТ / ЗАМЕТКА | M4: В БЮДЖЕТ €$ | N4: СТИЛЬ €$
B5: 1 | C5: Neuroport | D5: =IFERROR(INDEX('КАТАЛОГ'!$B$2:$B$1093,MATCH($C5,'КАТАЛОГ'!$A$2:$A$1093,0)),"") | E5: =IFERROR(INDEX('КАТАЛОГ'!$C$2:$C$1093,MATCH($C5,'КАТАЛОГ'!$A$2:$A$1093,0)),"") | G5: =IF($C5="",0,IF(ISNUMBER(SEARCH("Neuroport",$C5)),0,IFERROR(INDEX('КАТАЛОГ'!$R$2:$R$1093,MATCH($C5,'КАТАЛОГ'!$A$2:$A$1093,0)),0))) | H5: =IF($C5="",0,IF(ISNUMBER(SEARCH("Neuroport",$C5)),0,IFERROR(INDEX('КАТАЛОГ'!$M$2:$M$1093,MATCH($C5,'КАТАЛОГ'!$A$2:$A$1093,0)),0))) | I5: =IF($C5="",0,IF(OR(N($H5)=0,ISNUMBER(SEARCH("Fashionware",$E5))),0,IF(ISNUMBER(SEARCH("Borgware",$E5)),4,2))) | J5: Да | K5: =IFERROR(INDEX('КАТАЛОГ'!$N$2:$N$1093,MATCH($C5,'КАТАЛОГ'!$A$2:$A$1093,0)),"") | L5: Нейролинк, бесплатно в 2070-х | M5: =IF($C5="",0,IF($J5<>"Да",0,IF(ISNUMBER(SEARCH("Fashionware",$E5)),0,IF(COUNTIF('05 СНАРЯЖЕНИЕ'!$C$34:$C$53,$C5)>0,0,$G5)))) | N5: =IF($C5="",0,IF($J5<>"Да",0,IF(ISNUMBER(SEARCH("Fashionware",$E5)),$G5,0)))
B6: 2 | C6: Cyberaudio Suite | D6: =IFERROR(INDEX('КАТАЛОГ'!$B$2:$B$1093,MATCH($C6,'КАТАЛОГ'!$A$2:$A$1093,0)),"") | E6: =IFERROR(INDEX('КАТАЛОГ'!$C$2:$C$1093,MATCH($C6,'КАТАЛОГ'!$A$2:$A$1093,0)),"") | G6: =IF($C6="",0,IF(ISNUMBER(SEARCH("Neuroport",$C6)),0,IFERROR(INDEX('КАТАЛОГ'!$R$2:$R$1093,MATCH($C6,'КАТАЛОГ'!$A$2:$A$1093,0)),0))) | H6: =IF($C6="",0,IF(ISNUMBER(SEARCH("Neuroport",$C6)),0,IFERROR(INDEX('КАТАЛОГ'!$M$2:$M$1093,MATCH($C6,'КАТАЛОГ'!$A$2:$A$1093,0)),0))) | I6: =IF($C6="",0,IF(OR(N($H6)=0,ISNUMBER(SEARCH("Fashionware",$E6))),0,IF(ISNUMBER(SEARCH("Borgware",$E6)),4,2))) | J6: Да | K6: =IFERROR(INDEX('КАТАЛОГ'!$N$2:$N$1093,MATCH($C6,'КАТАЛОГ'!$A$2:$A$1093,0)),"") | L6: хост для аудио-опций, 3 слота | M6: =IF($C6="",0,IF($J6<>"Да",0,IF(ISNUMBER(SEARCH("Fashionware",$E6)),0,IF(COUNTIF('05 СНАРЯЖЕНИЕ'!$C$34:$C$53,$C6)>0,0,$G6)))) | N6: =IF($C6="",0,IF($J6<>"Да",0,IF(ISNUMBER(SEARCH("Fashionware",$E6)),$G6,0)))
B7: 3 | C7: Voice Stress Analyzer | D7: =IFERROR(INDEX('КАТАЛОГ'!$B$2:$B$1093,MATCH($C7,'КАТАЛОГ'!$A$2:$A$1093,0)),"") | E7: =IFERROR(INDEX('КАТАЛОГ'!$C$2:$C$1093,MATCH($C7,'КАТАЛОГ'!$A$2:$A$1093,0)),"") | G7: =IF($C7="",0,IF(ISNUMBER(SEARCH("Neuroport",$C7)),0,IFERROR(INDEX('КАТАЛОГ'!$R$2:$R$1093,MATCH($C7,'КАТАЛОГ'!$A$2:$A$1093,0)),0))) | H7: =IF($C7="",0,IF(ISNUMBER(SEARCH("Neuroport",$C7)),0,IFERROR(INDEX('КАТАЛОГ'!$M$2:$M$1093,MATCH($C7,'КАТАЛОГ'!$A$2:$A$1093,0)),0))) | I7: =IF($C7="",0,IF(OR(N($H7)=0,ISNUMBER(SEARCH("Fashionware",$E7))),0,IF(ISNUMBER(SEARCH("Borgware",$E7)),4,2))) | J7: Да | K7: =IFERROR(INDEX('КАТАЛОГ'!$N$2:$N$1093,MATCH($C7,'КАТАЛОГ'!$A$2:$A$1093,0)),"") | L7: +2 Human Perception и Interrogation, детектор лжи | M7: =IF($C7="",0,IF($J7<>"Да",0,IF(ISNUMBER(SEARCH("Fashionware",$E7)),0,IF(COUNTIF('05 СНАРЯЖЕНИЕ'!$C$34:$C$53,$C7)>0,0,$G7)))) | N7: =IF($C7="",0,IF($J7<>"Да",0,IF(ISNUMBER(SEARCH("Fashionware",$E7)),$G7,0)))
B8: 4 | C8: Amplified Hearing | D8: =IFERROR(INDEX('КАТАЛОГ'!$B$2:$B$1093,MATCH($C8,'КАТАЛОГ'!$A$2:$A$1093,0)),"") | E8: =IFERROR(INDEX('КАТАЛОГ'!$C$2:$C$1093,MATCH($C8,'КАТАЛОГ'!$A$2:$A$1093,0)),"") | G8: =IF($C8="",0,IF(ISNUMBER(SEARCH("Neuroport",$C8)),0,IFERROR(INDEX('КАТАЛОГ'!$R$2:$R$1093,MATCH($C8,'КАТАЛОГ'!$A$2:$A$1093,0)),0))) | H8: =IF($C8="",0,IF(ISNUMBER(SEARCH("Neuroport",$C8)),0,IFERROR(INDEX('КАТАЛОГ'!$M$2:$M$1093,MATCH($C8,'КАТАЛОГ'!$A$2:$A$1093,0)),0))) | I8: =IF($C8="",0,IF(OR(N($H8)=0,ISNUMBER(SEARCH("Fashionware",$E8))),0,IF(ISNUMBER(SEARCH("Borgware",$E8)),4,2))) | J8: Да | K8: =IFERROR(INDEX('КАТАЛОГ'!$N$2:$N$1093,MATCH($C8,'КАТАЛОГ'!$A$2:$A$1093,0)),"") | L8: +2 Perception на слух | M8: =IF($C8="",0,IF($J8<>"Да",0,IF(ISNUMBER(SEARCH("Fashionware",$E8)),0,IF(COUNTIF('05 СНАРЯЖЕНИЕ'!$C$34:$C$53,$C8)>0,0,$G8)))) | N8: =IF($C8="",0,IF($J8<>"Да",0,IF(ISNUMBER(SEARCH("Fashionware",$E8)),$G8,0)))
B9: 5 | C9: Toxin Binders | D9: =IFERROR(INDEX('КАТАЛОГ'!$B$2:$B$1093,MATCH($C9,'КАТАЛОГ'!$A$2:$A$1093,0)),"") | E9: =IFERROR(INDEX('КАТАЛОГ'!$C$2:$C$1093,MATCH($C9,'КАТАЛОГ'!$A$2:$A$1093,0)),"") | G9: =IF($C9="",0,IF(ISNUMBER(SEARCH("Neuroport",$C9)),0,IFERROR(INDEX('КАТАЛОГ'!$R$2:$R$1093,MATCH($C9,'КАТАЛОГ'!$A$2:$A$1093,0)),0))) | H9: =IF($C9="",0,IF(ISNUMBER(SEARCH("Neuroport",$C9)),0,IFERROR(INDEX('КАТАЛОГ'!$M$2:$M$1093,MATCH($C9,'КАТАЛОГ'!$A$2:$A$1093,0)),0))) | I9: =IF($C9="",0,IF(OR(N($H9)=0,ISNUMBER(SEARCH("Fashionware",$E9))),0,IF(ISNUMBER(SEARCH("Borgware",$E9)),4,2))) | J9: Да | K9: =IFERROR(INDEX('КАТАЛОГ'!$N$2:$N$1093,MATCH($C9,'КАТАЛОГ'!$A$2:$A$1093,0)),"") | L9: +2 Resist Torture/Drugs | M9: =IF($C9="",0,IF($J9<>"Да",0,IF(ISNUMBER(SEARCH("Fashionware",$E9)),0,IF(COUNTIF('05 СНАРЯЖЕНИЕ'!$C$34:$C$53,$C9)>0,0,$G9)))) | N9: =IF($C9="",0,IF($J9<>"Да",0,IF(ISNUMBER(SEARCH("Fashionware",$E9)),$G9,0)))
B10: 6 | C10: Biomonitor | D10: =IFERROR(INDEX('КАТАЛОГ'!$B$2:$B$1093,MATCH($C10,'КАТАЛОГ'!$A$2:$A$1093,0)),"") | E10: =IFERROR(INDEX('КАТАЛОГ'!$C$2:$C$1093,MATCH($C10,'КАТАЛОГ'!$A$2:$A$1093,0)),"") | G10: =IF($C10="",0,IF(ISNUMBER(SEARCH("Neuroport",$C10)),0,IFERROR(INDEX('КАТАЛОГ'!$R$2:$R$1093,MATCH($C10,'КАТАЛОГ'!$A$2:$A$1093,0)),0))) | H10: =IF($C10="",0,IF(ISNUMBER(SEARCH("Neuroport",$C10)),0,IFERROR(INDEX('КАТАЛОГ'!$M$2:$M$1093,MATCH($C10,'КАТАЛОГ'!$A$2:$A$1093,0)),0))) | I10: =IF($C10="",0,IF(OR(N($H10)=0,ISNUMBER(SEARCH("Fashionware",$E10))),0,IF(ISNUMBER(SEARCH("Borgware",$E10)),4,2))) | J10: Да | K10: =IFERROR(INDEX('КАТАЛОГ'!$N$2:$N$1093,MATCH($C10,'КАТАЛОГ'!$A$2:$A$1093,0)),"") | L10: Fashionware · пульс/температура на Агент | M10: =IF($C10="",0,IF($J10<>"Да",0,IF(ISNUMBER(SEARCH("Fashionware",$E10)),0,IF(COUNTIF('05 СНАРЯЖЕНИЕ'!$C$34:$C$53,$C10)>0,0,$G10)))) | N10: =IF($C10="",0,IF($J10<>"Да",0,IF(ISNUMBER(SEARCH("Fashionware",$E10)),$G10,0)))
B11: 7 | C11: Radio Communicator | D11: =IFERROR(INDEX('КАТАЛОГ'!$B$2:$B$1093,MATCH($C11,'КАТАЛОГ'!$A$2:$A$1093,0)),"") | E11: =IFERROR(INDEX('КАТАЛОГ'!$C$2:$C$1093,MATCH($C11,'КАТАЛОГ'!$A$2:$A$1093,0)),"") | G11: =IF($C11="",0,IF(ISNUMBER(SEARCH("Neuroport",$C11)),0,IFERROR(INDEX('КАТАЛОГ'!$R$2:$R$1093,MATCH($C11,'КАТАЛОГ'!$A$2:$A$1093,0)),0))) | H11: =IF($C11="",0,IF(ISNUMBER(SEARCH("Neuroport",$C11)),0,IFERROR(INDEX('КАТАЛОГ'!$M$2:$M$1093,MATCH($C11,'КАТАЛОГ'!$A$2:$A$1093,0)),0))) | I11: =IF($C11="",0,IF(OR(N($H11)=0,ISNUMBER(SEARCH("Fashionware",$E11))),0,IF(ISNUMBER(SEARCH("Borgware",$E11)),4,2))) | J11: Да | K11: =IFERROR(INDEX('КАТАЛОГ'!$N$2:$N$1093,MATCH($C11,'КАТАЛОГ'!$A$2:$A$1093,0)),"") | L11: Cyberaudio Option (3-й слот Suite): связь на 1 милю | M11: =IF($C11="",0,IF($J11<>"Да",0,IF(ISNUMBER(SEARCH("Fashionware",$E11)),0,IF(COUNTIF('05 СНАРЯЖЕНИЕ'!$C$34:$C$53,$C11)>0,0,$G11)))) | N11: =IF($C11="",0,IF($J11<>"Да",0,IF(ISNUMBER(SEARCH("Fashionware",$E11)),$G11,0)))
B12: 8 | C12: Light Tattoo | D12: =IFERROR(INDEX('КАТАЛОГ'!$B$2:$B$1093,MATCH($C12,'КАТАЛОГ'!$A$2:$A$1093,0)),"") | E12: =IFERROR(INDEX('КАТАЛОГ'!$C$2:$C$1093,MATCH($C12,'КАТАЛОГ'!$A$2:$A$1093,0)),"") | G12: =IF($C12="",0,IF(ISNUMBER(SEARCH("Neuroport",$C12)),0,IFERROR(INDEX('КАТАЛОГ'!$R$2:$R$1093,MATCH($C12,'КАТАЛОГ'!$A$2:$A$1093,0)),0))) | H12: =IF($C12="",0,IF(ISNUMBER(SEARCH("Neuroport",$C12)),0,IFERROR(INDEX('КАТАЛОГ'!$M$2:$M$1093,MATCH($C12,'КАТАЛОГ'!$A$2:$A$1093,0)),0))) | I12: =IF($C12="",0,IF(OR(N($H12)=0,ISNUMBER(SEARCH("Fashionware",$E12))),0,IF(ISNUMBER(SEARCH("Borgware",$E12)),4,2))) | J12: Да | K12: =IFERROR(INDEX('КАТАЛОГ'!$N$2:$N$1093,MATCH($C12,'КАТАЛОГ'!$A$2:$A$1093,0)),"") | L12: Fashionware: выцветшая татуировка-значок NCPD (0 HL, стиль-бюджет) | M12: =IF($C12="",0,IF($J12<>"Да",0,IF(ISNUMBER(SEARCH("Fashionware",$E12)),0,IF(COUNTIF('05 СНАРЯЖЕНИЕ'!$C$34:$C$53,$C12)>0,0,$G12)))) | N12: =IF($C12="",0,IF($J12<>"Да",0,IF(ISNUMBER(SEARCH("Fashionware",$E12)),$G12,0)))
B13: 9 | C13: EMP Threading | D13: =IFERROR(INDEX('КАТАЛОГ'!$B$2:$B$1093,MATCH($C13,'КАТАЛОГ'!$A$2:$A$1093,0)),"") | E13: =IFERROR(INDEX('КАТАЛОГ'!$C$2:$C$1093,MATCH($C13,'КАТАЛОГ'!$A$2:$A$1093,0)),"") | G13: =IF($C13="",0,IF(ISNUMBER(SEARCH("Neuroport",$C13)),0,IFERROR(INDEX('КАТАЛОГ'!$R$2:$R$1093,MATCH($C13,'КАТАЛОГ'!$A$2:$A$1093,0)),0))) | H13: =IF($C13="",0,IF(ISNUMBER(SEARCH("Neuroport",$C13)),0,IFERROR(INDEX('КАТАЛОГ'!$M$2:$M$1093,MATCH($C13,'КАТАЛОГ'!$A$2:$A$1093,0)),0))) | I13: =IF($C13="",0,IF(OR(N($H13)=0,ISNUMBER(SEARCH("Fashionware",$E13))),0,IF(ISNUMBER(SEARCH("Borgware",$E13)),4,2))) | J13: Да | K13: =IFERROR(INDEX('КАТАЛОГ'!$N$2:$N$1093,MATCH($C13,'КАТАЛОГ'!$A$2:$A$1093,0)),"") | L13: Fashionware: светящиеся линии на предплечье (0 HL) | M13: =IF($C13="",0,IF($J13<>"Да",0,IF(ISNUMBER(SEARCH("Fashionware",$E13)),0,IF(COUNTIF('05 СНАРЯЖЕНИЕ'!$C$34:$C$53,$C13)>0,0,$G13)))) | N13: =IF($C13="",0,IF($J13<>"Да",0,IF(ISNUMBER(SEARCH("Fashionware",$E13)),$G13,0)))
B14: 10 | D14: =IFERROR(INDEX('КАТАЛОГ'!$B$2:$B$1093,MATCH($C14,'КАТАЛОГ'!$A$2:$A$1093,0)),"") | E14: =IFERROR(INDEX('КАТАЛОГ'!$C$2:$C$1093,MATCH($C14,'КАТАЛОГ'!$A$2:$A$1093,0)),"") | G14: =IF($C14="",0,IF(ISNUMBER(SEARCH("Neuroport",$C14)),0,IFERROR(INDEX('КАТАЛОГ'!$R$2:$R$1093,MATCH($C14,'КАТАЛОГ'!$A$2:$A$1093,0)),0))) | H14: =IF($C14="",0,IF(ISNUMBER(SEARCH("Neuroport",$C14)),0,IFERROR(INDEX('КАТАЛОГ'!$M$2:$M$1093,MATCH($C14,'КАТАЛОГ'!$A$2:$A$1093,0)),0))) | I14: =IF($C14="",0,IF(OR(N($H14)=0,ISNUMBER(SEARCH("Fashionware",$E14))),0,IF(ISNUMBER(SEARCH("Borgware",$E14)),4,2))) | J14: Нет | K14: =IFERROR(INDEX('КАТАЛОГ'!$N$2:$N$1093,MATCH($C14,'КАТАЛОГ'!$A$2:$A$1093,0)),"") | L14: =IFERROR(LEFT(INDEX('КАТАЛОГ'!$T$2:$T$1093,MATCH($C14,'КАТАЛОГ'!$A$2:$A$1093,0)),70),"") | M14: =IF($C14="",0,IF($J14<>"Да",0,IF(ISNUMBER(SEARCH("Fashionware",$E14)),0,IF(COUNTIF('05 СНАРЯЖЕНИЕ'!$C$34:$C$53,$C14)>0,0,$G14)))) | N14: =IF($C14="",0,IF($J14<>"Да",0,IF(ISNUMBER(SEARCH("Fashionware",$E14)),$G14,0)))
B15: 11 | D15: =IFERROR(INDEX('КАТАЛОГ'!$B$2:$B$1093,MATCH($C15,'КАТАЛОГ'!$A$2:$A$1093,0)),"") | E15: =IFERROR(INDEX('КАТАЛОГ'!$C$2:$C$1093,MATCH($C15,'КАТАЛОГ'!$A$2:$A$1093,0)),"") | G15: =IF($C15="",0,IF(ISNUMBER(SEARCH("Neuroport",$C15)),0,IFERROR(INDEX('КАТАЛОГ'!$R$2:$R$1093,MATCH($C15,'КАТАЛОГ'!$A$2:$A$1093,0)),0))) | H15: =IF($C15="",0,IF(ISNUMBER(SEARCH("Neuroport",$C15)),0,IFERROR(INDEX('КАТАЛОГ'!$M$2:$M$1093,MATCH($C15,'КАТАЛОГ'!$A$2:$A$1093,0)),0))) | I15: =IF($C15="",0,IF(OR(N($H15)=0,ISNUMBER(SEARCH("Fashionware",$E15))),0,IF(ISNUMBER(SEARCH("Borgware",$E15)),4,2))) | J15: Нет | K15: =IFERROR(INDEX('КАТАЛОГ'!$N$2:$N$1093,MATCH($C15,'КАТАЛОГ'!$A$2:$A$1093,0)),"") | L15: =IFERROR(LEFT(INDEX('КАТАЛОГ'!$T$2:$T$1093,MATCH($C15,'КАТАЛОГ'!$A$2:$A$1093,0)),70),"") | M15: =IF($C15="",0,IF($J15<>"Да",0,IF(ISNUMBER(SEARCH("Fashionware",$E15)),0,IF(COUNTIF('05 СНАРЯЖЕНИЕ'!$C$34:$C$53,$C15)>0,0,$G15)))) | N15: =IF($C15="",0,IF($J15<>"Да",0,IF(ISNUMBER(SEARCH("Fashionware",$E15)),$G15,0)))
B16: 12 | D16: =IFERROR(INDEX('КАТАЛОГ'!$B$2:$B$1093,MATCH($C16,'КАТАЛОГ'!$A$2:$A$1093,0)),"") | E16: =IFERROR(INDEX('КАТАЛОГ'!$C$2:$C$1093,MATCH($C16,'КАТАЛОГ'!$A$2:$A$1093,0)),"") | G16: =IF($C16="",0,IF(ISNUMBER(SEARCH("Neuroport",$C16)),0,IFERROR(INDEX('КАТАЛОГ'!$R$2:$R$1093,MATCH($C16,'КАТАЛОГ'!$A$2:$A$1093,0)),0))) | H16: =IF($C16="",0,IF(ISNUMBER(SEARCH("Neuroport",$C16)),0,IFERROR(INDEX('КАТАЛОГ'!$M$2:$M$1093,MATCH($C16,'КАТАЛОГ'!$A$2:$A$1093,0)),0))) | I16: =IF($C16="",0,IF(OR(N($H16)=0,ISNUMBER(SEARCH("Fashionware",$E16))),0,IF(ISNUMBER(SEARCH("Borgware",$E16)),4,2))) | J16: Нет | K16: =IFERROR(INDEX('КАТАЛОГ'!$N$2:$N$1093,MATCH($C16,'КАТАЛОГ'!$A$2:$A$1093,0)),"") | L16: =IFERROR(LEFT(INDEX('КАТАЛОГ'!$T$2:$T$1093,MATCH($C16,'КАТАЛОГ'!$A$2:$A$1093,0)),70),"") | M16: =IF($C16="",0,IF($J16<>"Да",0,IF(ISNUMBER(SEARCH("Fashionware",$E16)),0,IF(COUNTIF('05 СНАРЯЖЕНИЕ'!$C$34:$C$53,$C16)>0,0,$G16)))) | N16: =IF($C16="",0,IF($J16<>"Да",0,IF(ISNUMBER(SEARCH("Fashionware",$E16)),$G16,0)))
B17: 13 | D17: =IFERROR(INDEX('КАТАЛОГ'!$B$2:$B$1093,MATCH($C17,'КАТАЛОГ'!$A$2:$A$1093,0)),"") | E17: =IFERROR(INDEX('КАТАЛОГ'!$C$2:$C$1093,MATCH($C17,'КАТАЛОГ'!$A$2:$A$1093,0)),"") | G17: =IF($C17="",0,IF(ISNUMBER(SEARCH("Neuroport",$C17)),0,IFERROR(INDEX('КАТАЛОГ'!$R$2:$R$1093,MATCH($C17,'КАТАЛОГ'!$A$2:$A$1093,0)),0))) | H17: =IF($C17="",0,IF(ISNUMBER(SEARCH("Neuroport",$C17)),0,IFERROR(INDEX('КАТАЛОГ'!$M$2:$M$1093,MATCH($C17,'КАТАЛОГ'!$A$2:$A$1093,0)),0))) | I17: =IF($C17="",0,IF(OR(N($H17)=0,ISNUMBER(SEARCH("Fashionware",$E17))),0,IF(ISNUMBER(SEARCH("Borgware",$E17)),4,2))) | J17: Нет | K17: =IFERROR(INDEX('КАТАЛОГ'!$N$2:$N$1093,MATCH($C17,'КАТАЛОГ'!$A$2:$A$1093,0)),"") | L17: =IFERROR(LEFT(INDEX('КАТАЛОГ'!$T$2:$T$1093,MATCH($C17,'КАТАЛОГ'!$A$2:$A$1093,0)),70),"") | M17: =IF($C17="",0,IF($J17<>"Да",0,IF(ISNUMBER(SEARCH("Fashionware",$E17)),0,IF(COUNTIF('05 СНАРЯЖЕНИЕ'!$C$34:$C$53,$C17)>0,0,$G17)))) | N17: =IF($C17="",0,IF($J17<>"Да",0,IF(ISNUMBER(SEARCH("Fashionware",$E17)),$G17,0)))
B18: 14 | D18: =IFERROR(INDEX('КАТАЛОГ'!$B$2:$B$1093,MATCH($C18,'КАТАЛОГ'!$A$2:$A$1093,0)),"") | E18: =IFERROR(INDEX('КАТАЛОГ'!$C$2:$C$1093,MATCH($C18,'КАТАЛОГ'!$A$2:$A$1093,0)),"") | G18: =IF($C18="",0,IF(ISNUMBER(SEARCH("Neuroport",$C18)),0,IFERROR(INDEX('КАТАЛОГ'!$R$2:$R$1093,MATCH($C18,'КАТАЛОГ'!$A$2:$A$1093,0)),0))) | H18: =IF($C18="",0,IF(ISNUMBER(SEARCH("Neuroport",$C18)),0,IFERROR(INDEX('КАТАЛОГ'!$M$2:$M$1093,MATCH($C18,'КАТАЛОГ'!$A$2:$A$1093,0)),0))) | I18: =IF($C18="",0,IF(OR(N($H18)=0,ISNUMBER(SEARCH("Fashionware",$E18))),0,IF(ISNUMBER(SEARCH("Borgware",$E18)),4,2))) | J18: Нет | K18: =IFERROR(INDEX('КАТАЛОГ'!$N$2:$N$1093,MATCH($C18,'КАТАЛОГ'!$A$2:$A$1093,0)),"") | L18: =IFERROR(LEFT(INDEX('КАТАЛОГ'!$T$2:$T$1093,MATCH($C18,'КАТАЛОГ'!$A$2:$A$1093,0)),70),"") | M18: =IF($C18="",0,IF($J18<>"Да",0,IF(ISNUMBER(SEARCH("Fashionware",$E18)),0,IF(COUNTIF('05 СНАРЯЖЕНИЕ'!$C$34:$C$53,$C18)>0,0,$G18)))) | N18: =IF($C18="",0,IF($J18<>"Да",0,IF(ISNUMBER(SEARCH("Fashionware",$E18)),$G18,0)))
B19: 15 | D19: =IFERROR(INDEX('КАТАЛОГ'!$B$2:$B$1093,MATCH($C19,'КАТАЛОГ'!$A$2:$A$1093,0)),"") | E19: =IFERROR(INDEX('КАТАЛОГ'!$C$2:$C$1093,MATCH($C19,'КАТАЛОГ'!$A$2:$A$1093,0)),"") | G19: =IF($C19="",0,IF(ISNUMBER(SEARCH("Neuroport",$C19)),0,IFERROR(INDEX('КАТАЛОГ'!$R$2:$R$1093,MATCH($C19,'КАТАЛОГ'!$A$2:$A$1093,0)),0))) | H19: =IF($C19="",0,IF(ISNUMBER(SEARCH("Neuroport",$C19)),0,IFERROR(INDEX('КАТАЛОГ'!$M$2:$M$1093,MATCH($C19,'КАТАЛОГ'!$A$2:$A$1093,0)),0))) | I19: =IF($C19="",0,IF(OR(N($H19)=0,ISNUMBER(SEARCH("Fashionware",$E19))),0,IF(ISNUMBER(SEARCH("Borgware",$E19)),4,2))) | J19: Нет | K19: =IFERROR(INDEX('КАТАЛОГ'!$N$2:$N$1093,MATCH($C19,'КАТАЛОГ'!$A$2:$A$1093,0)),"") | L19: =IFERROR(LEFT(INDEX('КАТАЛОГ'!$T$2:$T$1093,MATCH($C19,'КАТАЛОГ'!$A$2:$A$1093,0)),70),"") | M19: =IF($C19="",0,IF($J19<>"Да",0,IF(ISNUMBER(SEARCH("Fashionware",$E19)),0,IF(COUNTIF('05 СНАРЯЖЕНИЕ'!$C$34:$C$53,$C19)>0,0,$G19)))) | N19: =IF($C19="",0,IF($J19<>"Да",0,IF(ISNUMBER(SEARCH("Fashionware",$E19)),$G19,0)))
B20: 16 | D20: =IFERROR(INDEX('КАТАЛОГ'!$B$2:$B$1093,MATCH($C20,'КАТАЛОГ'!$A$2:$A$1093,0)),"") | E20: =IFERROR(INDEX('КАТАЛОГ'!$C$2:$C$1093,MATCH($C20,'КАТАЛОГ'!$A$2:$A$1093,0)),"") | G20: =IF($C20="",0,IF(ISNUMBER(SEARCH("Neuroport",$C20)),0,IFERROR(INDEX('КАТАЛОГ'!$R$2:$R$1093,MATCH($C20,'КАТАЛОГ'!$A$2:$A$1093,0)),0))) | H20: =IF($C20="",0,IF(ISNUMBER(SEARCH("Neuroport",$C20)),0,IFERROR(INDEX('КАТАЛОГ'!$M$2:$M$1093,MATCH($C20,'КАТАЛОГ'!$A$2:$A$1093,0)),0))) | I20: =IF($C20="",0,IF(OR(N($H20)=0,ISNUMBER(SEARCH("Fashionware",$E20))),0,IF(ISNUMBER(SEARCH("Borgware",$E20)),4,2))) | J20: Нет | K20: =IFERROR(INDEX('КАТАЛОГ'!$N$2:$N$1093,MATCH($C20,'КАТАЛОГ'!$A$2:$A$1093,0)),"") | L20: =IFERROR(LEFT(INDEX('КАТАЛОГ'!$T$2:$T$1093,MATCH($C20,'КАТАЛОГ'!$A$2:$A$1093,0)),70),"") | M20: =IF($C20="",0,IF($J20<>"Да",0,IF(ISNUMBER(SEARCH("Fashionware",$E20)),0,IF(COUNTIF('05 СНАРЯЖЕНИЕ'!$C$34:$C$53,$C20)>0,0,$G20)))) | N20: =IF($C20="",0,IF($J20<>"Да",0,IF(ISNUMBER(SEARCH("Fashionware",$E20)),$G20,0)))
B21: 17 | D21: =IFERROR(INDEX('КАТАЛОГ'!$B$2:$B$1093,MATCH($C21,'КАТАЛОГ'!$A$2:$A$1093,0)),"") | E21: =IFERROR(INDEX('КАТАЛОГ'!$C$2:$C$1093,MATCH($C21,'КАТАЛОГ'!$A$2:$A$1093,0)),"") | G21: =IF($C21="",0,IF(ISNUMBER(SEARCH("Neuroport",$C21)),0,IFERROR(INDEX('КАТАЛОГ'!$R$2:$R$1093,MATCH($C21,'КАТАЛОГ'!$A$2:$A$1093,0)),0))) | H21: =IF($C21="",0,IF(ISNUMBER(SEARCH("Neuroport",$C21)),0,IFERROR(INDEX('КАТАЛОГ'!$M$2:$M$1093,MATCH($C21,'КАТАЛОГ'!$A$2:$A$1093,0)),0))) | I21: =IF($C21="",0,IF(OR(N($H21)=0,ISNUMBER(SEARCH("Fashionware",$E21))),0,IF(ISNUMBER(SEARCH("Borgware",$E21)),4,2))) | J21: Нет | K21: =IFERROR(INDEX('КАТАЛОГ'!$N$2:$N$1093,MATCH($C21,'КАТАЛОГ'!$A$2:$A$1093,0)),"") | L21: =IFERROR(LEFT(INDEX('КАТАЛОГ'!$T$2:$T$1093,MATCH($C21,'КАТАЛОГ'!$A$2:$A$1093,0)),70),"") | M21: =IF($C21="",0,IF($J21<>"Да",0,IF(ISNUMBER(SEARCH("Fashionware",$E21)),0,IF(COUNTIF('05 СНАРЯЖЕНИЕ'!$C$34:$C$53,$C21)>0,0,$G21)))) | N21: =IF($C21="",0,IF($J21<>"Да",0,IF(ISNUMBER(SEARCH("Fashionware",$E21)),$G21,0)))
B22: 18 | D22: =IFERROR(INDEX('КАТАЛОГ'!$B$2:$B$1093,MATCH($C22,'КАТАЛОГ'!$A$2:$A$1093,0)),"") | E22: =IFERROR(INDEX('КАТАЛОГ'!$C$2:$C$1093,MATCH($C22,'КАТАЛОГ'!$A$2:$A$1093,0)),"") | G22: =IF($C22="",0,IF(ISNUMBER(SEARCH("Neuroport",$C22)),0,IFERROR(INDEX('КАТАЛОГ'!$R$2:$R$1093,MATCH($C22,'КАТАЛОГ'!$A$2:$A$1093,0)),0))) | H22: =IF($C22="",0,IF(ISNUMBER(SEARCH("Neuroport",$C22)),0,IFERROR(INDEX('КАТАЛОГ'!$M$2:$M$1093,MATCH($C22,'КАТАЛОГ'!$A$2:$A$1093,0)),0))) | I22: =IF($C22="",0,IF(OR(N($H22)=0,ISNUMBER(SEARCH("Fashionware",$E22))),0,IF(ISNUMBER(SEARCH("Borgware",$E22)),4,2))) | J22: Нет | K22: =IFERROR(INDEX('КАТАЛОГ'!$N$2:$N$1093,MATCH($C22,'КАТАЛОГ'!$A$2:$A$1093,0)),"") | L22: =IFERROR(LEFT(INDEX('КАТАЛОГ'!$T$2:$T$1093,MATCH($C22,'КАТАЛОГ'!$A$2:$A$1093,0)),70),"") | M22: =IF($C22="",0,IF($J22<>"Да",0,IF(ISNUMBER(SEARCH("Fashionware",$E22)),0,IF(COUNTIF('05 СНАРЯЖЕНИЕ'!$C$34:$C$53,$C22)>0,0,$G22)))) | N22: =IF($C22="",0,IF($J22<>"Да",0,IF(ISNUMBER(SEARCH("Fashionware",$E22)),$G22,0)))
B23: 19 | D23: =IFERROR(INDEX('КАТАЛОГ'!$B$2:$B$1093,MATCH($C23,'КАТАЛОГ'!$A$2:$A$1093,0)),"") | E23: =IFERROR(INDEX('КАТАЛОГ'!$C$2:$C$1093,MATCH($C23,'КАТАЛОГ'!$A$2:$A$1093,0)),"") | G23: =IF($C23="",0,IF(ISNUMBER(SEARCH("Neuroport",$C23)),0,IFERROR(INDEX('КАТАЛОГ'!$R$2:$R$1093,MATCH($C23,'КАТАЛОГ'!$A$2:$A$1093,0)),0))) | H23: =IF($C23="",0,IF(ISNUMBER(SEARCH("Neuroport",$C23)),0,IFERROR(INDEX('КАТАЛОГ'!$M$2:$M$1093,MATCH($C23,'КАТАЛОГ'!$A$2:$A$1093,0)),0))) | I23: =IF($C23="",0,IF(OR(N($H23)=0,ISNUMBER(SEARCH("Fashionware",$E23))),0,IF(ISNUMBER(SEARCH("Borgware",$E23)),4,2))) | J23: Нет | K23: =IFERROR(INDEX('КАТАЛОГ'!$N$2:$N$1093,MATCH($C23,'КАТАЛОГ'!$A$2:$A$1093,0)),"") | L23: =IFERROR(LEFT(INDEX('КАТАЛОГ'!$T$2:$T$1093,MATCH($C23,'КАТАЛОГ'!$A$2:$A$1093,0)),70),"") | M23: =IF($C23="",0,IF($J23<>"Да",0,IF(ISNUMBER(SEARCH("Fashionware",$E23)),0,IF(COUNTIF('05 СНАРЯЖЕНИЕ'!$C$34:$C$53,$C23)>0,0,$G23)))) | N23: =IF($C23="",0,IF($J23<>"Да",0,IF(ISNUMBER(SEARCH("Fashionware",$E23)),$G23,0)))
B24: 20 | D24: =IFERROR(INDEX('КАТАЛОГ'!$B$2:$B$1093,MATCH($C24,'КАТАЛОГ'!$A$2:$A$1093,0)),"") | E24: =IFERROR(INDEX('КАТАЛОГ'!$C$2:$C$1093,MATCH($C24,'КАТАЛОГ'!$A$2:$A$1093,0)),"") | G24: =IF($C24="",0,IF(ISNUMBER(SEARCH("Neuroport",$C24)),0,IFERROR(INDEX('КАТАЛОГ'!$R$2:$R$1093,MATCH($C24,'КАТАЛОГ'!$A$2:$A$1093,0)),0))) | H24: =IF($C24="",0,IF(ISNUMBER(SEARCH("Neuroport",$C24)),0,IFERROR(INDEX('КАТАЛОГ'!$M$2:$M$1093,MATCH($C24,'КАТАЛОГ'!$A$2:$A$1093,0)),0))) | I24: =IF($C24="",0,IF(OR(N($H24)=0,ISNUMBER(SEARCH("Fashionware",$E24))),0,IF(ISNUMBER(SEARCH("Borgware",$E24)),4,2))) | J24: Нет | K24: =IFERROR(INDEX('КАТАЛОГ'!$N$2:$N$1093,MATCH($C24,'КАТАЛОГ'!$A$2:$A$1093,0)),"") | L24: =IFERROR(LEFT(INDEX('КАТАЛОГ'!$T$2:$T$1093,MATCH($C24,'КАТАЛОГ'!$A$2:$A$1093,0)),70),"") | M24: =IF($C24="",0,IF($J24<>"Да",0,IF(ISNUMBER(SEARCH("Fashionware",$E24)),0,IF(COUNTIF('05 СНАРЯЖЕНИЕ'!$C$34:$C$53,$C24)>0,0,$G24)))) | N24: =IF($C24="",0,IF($J24<>"Да",0,IF(ISNUMBER(SEARCH("Fashionware",$E24)),$G24,0)))
B25: ИТОГО (ТОЛЬКО ОТМЕЧЕННЫЕ «ДА») | G25: =SUM($M$5:$M$24)+SUM($N$5:$N$24) | H25: =SUMIF($J$5:$J$24,"Да",$H$5:$H$24) | I25: =SUMIF($J$5:$J$24,"Да",$I$5:$I$24) | J25: HL / срез | K25: → переносится в HUMANITY на листе 02 | M25: =SUM($M$5:$M$24) | N25: =SUM($N$5:$N$24)
B26: NEUROPORT УСТАНОВЛЕН (2070) | E26: Да | F26: =IF(AND($E$26="Нет",COUNTIF($J$5:$J$24,"Да")>0),"⚠ По правилам 2070-х любой немедицинский хром требует Neuroport (CEMK стр. 26)","✔ ок. Neuroport при создании: 0 €$, 0 HL, максимум Humanity не режется (в игре установка — 1000 €$ и 7 HL в среднем)")
B27: NEUROPORT ДАЁТ: Neural Link (5 слотов Neuralware Options) · Holophone · Biomonitor · Virtu · HUD/Chyron (перевод и субтитры на ходу) · 2 чип-слота под шарды · Personal Link (Interface Plug). Порт под кибердеку — 100 €$ и 3 (1d6) HL; диапазон сети 20 м, до нейропортов — 50 м.
B28: ЖЁСТКИЕ ЛИМИТЫ: одно Speedware на пользователя · один Cyberdeck подключён за раз · цибер-оружие в руке считается имплантом и требует слот(ы) киберруки. Эффекты смотри в КАТАЛОГЕ.
B30: Ⅰ · HUMANITY · ЧЕЛОВЕЧНОСТЬ, ХЛ, ТЕРАПИЯ
B31: БАЗА (EMP × 10) | D31: ='02 ОСНОВА'!$D$31 | E31: От исходной EMP (лист 02, колонка «ЗНАЧ.»).
B32: СРЕЗ МАКСИМУМА ЗА ХРОМ | D32: ='02 ОСНОВА'!$D$32 | E32: Этот же срез стоит в колонке «СРЕЗ» выше. Fashionware и стартовый Neuroport не режут максимум.
B33: HUMANITY МАКСИМУМ | D33: ='02 ОСНОВА'!$D$33 | E33: База минус срез. Вернуть выше максимума нельзя — только снимать хром.
B34: HL ВСЕГО (СРЕДНЕЕ) | D34: ='02 ОСНОВА'!$D$34 | E34: Сумма средних HL установленного хрома. Твоё дом-правило: 7 (2d6) = −7.
B35: ВОССТАНОВЛЕНО (ТЕРАПИЯ/ОПЫТ) | D35: ='02 ОСНОВА'!$D$35 | E35: Правится на листе 02, ячейка D35: терапия + Humanity Gain по CEMK.
B36: HUMANITY ТЕКУЩАЯ | D36: ='02 ОСНОВА'!$D$36 | E36: База − HL + восстановленное, но не выше максимума.
B37: EMP ТЕКУЩАЯ | D37: ='02 ОСНОВА'!$D$37 | E37: Каждый раз, когда десяток Humanity падает — падает и EMP.
B38: СТАТУС | D38: ='02 ОСНОВА'!$D$38 | E38: Humanity < 0 = киберпсихоз: лист забирает GM.
B39: ШКАЛА HUMANITY | D39: ='02 ОСНОВА'!$D$36 | E39: =REPT("█",MAX(0,MIN(40,ROUND($D$39/2,0))))&REPT("░",MAX(0,40-MIN(40,ROUND($D$39/2,0))))
B41: Ⅱ · ТЕРАПИЯ · 1 НЕДЕЛЯ ЗА СЕАНС (CP:R СТР. 229) · MEDTECH НЕ ЛЕЧИТ СЕБЯ САМ
B42: ТИП | D42: ЦЕНА | E42: DV / МАТЕРИАЛЫ | G42: ЭФФЕКТ
B43: Standard Humanity Loss | D43: 500 €$ | E43: Medical Tech DV15 · материалы 100 €$ | G43: Возврат 2d6 Humanity (в среднем 7). Больше максимума не поднять.
B44: Extreme Humanity Loss | D44: 1 000 €$ | E44: Medical Tech DV17 · материалы 500 €$ | G44: Возврат 4d6 Humanity (в среднем 14). Только при серьёзных потерях.
B45: Addiction | D45: 1 000 €$ | E45: Medical Tech DV15 · материалы 500 €$ | G45: Снимает одну зависимость. Год авто-провалов на вторичный эффект источника.
B47: Ⅲ · МЕНТАЛЬНАЯ ТРАВМА ПО 2070-М (CEMK): HUMANITY LOSS / GAIN СОБЫТИЯМИ
B48: БРОСОК | D48: ПРИМЕРЫ СОБЫТИЙ
B49: 1d6 | D49: Свидетель или участник пыток · угроза смерти · несправедливость системы · ограбление дома/на улице
B50: 2d6 | D50: Зверское убийство на глазах · первое убийство · тяжёлая физическая или ментальная травма · близкий умер вдали от тебя
B51: 3d6 | D51: Участие в убийстве невиновного · смерть близкого на твоих глазах · жизнь в зоне хуже Боевой больше недели
B52: GAIN 1d6 | D52: Победа над личным врагом · катарсис от символической победы · примирение с семьёй · настоящий друг
B53: GAIN 2d6 | D53: Ты спас чью-то жизнь · вечеринка с друзьями (≥1 000 €$ общей траты) · месяц жизни по Fresh Food
B54: GAIN 3d6 | D54: Помолвка, свадьба, усыновление, рождение ребёнка, исполнение мечты · большой праздник (≥10 000 €$)
B56: Ⅳ · КИБЕРПСИХОЗ: ЧТО ЭТО ЗНАЧИТ ЗА СТОЛОМ
B57: Humanity — это не «здоровье психики», а способность считать других живыми. На низкой Humanity персонаж начинает видеть в людях наборы деталей: он отстранён, диссоциирован, «люди — запчасти». При Humanity ниже 0 киберпсихоз переходит в крайнюю стадию, и GM играет персонажа по его худшим наклонностям, пока команда (или Medtech) не вытащат его терапией. Держи запас Humanity и не пихай хром «на всякий случай».

Sheet 05 СНАРЯЖЕНИЕ
B1: СНАРЯЖЕНИЕ ▚ БЮДЖЕТ 2550 €$ + 800 €$ НА СТИЛЬ ▚ ОРУЖИЕ · БРОНЯ · ИНВЕНТАРЬ · КАССА
B2: НАЗВАНИЯ БЕРУТСЯ ИЗ КАТАЛОГА — ЦЕНА, УРОН И ШТРАФЫ ПОДТЯНУТСЯ АВТОМАТИЧЕСКИ. ЕСЛИ ВЕЩИ В КАТАЛОГЕ НЕТ — ВПИШИ СВОЮ ЦЕНУ В СТОЛБЕЦ «ЦЕНА СВОЯ».
B3: СТАРТ: ОРУЖИЕ, БРОНЯ, СНАРЯЖЕНИЕ, ХРОМ (€$) | E3: 2550 | F3: ПОТРАЧЕНО | G3: =$H$54+SUM('04 ХРОМ'!$M$5:$M$24)+SUM($O$21:$O$26)-($G$4-SUM('04 ХРОМ'!$N$5:$N$24)) | H3: ОСТАТОК | I3: =$E$3-$G$3 | J3: Копятся из трёх мест: инвентарь (Ⅲ), броня (Ⅱ) и установленный хром (лист 04). Что уже вписано в инвентарь, второй раз не считается.
B4: СТАРТ: СТИЛЬ — FASHION И FASHIONWARE (€$) | E4: 800 | F4: ПОТРАЧЕНО | G4: =SUMPRODUCT(($D$34:$D$53="Мода")*$I$34:$I$53)+SUMPRODUCT(($E$34:$E$53="Fashionware")*$I$34:$I$53)+SUM('04 ХРОМ'!$N$5:$N$24) | H4: ОСТАТОК | I4: =$E$4-$G$4 | J4: Одежда (категория «Мода»), Fashionware из инвентаря и Fashionware-хром с листа 04.
B5: НАЛИЧНЫЕ €$ (АВТО) | D5: =$I$3+SUM($E$58:$E$77) | E5: ПРОВЕРКА БЮДЖЕТА | F5: =IF(OR($I$3<0,$I$4<0),"✖ стартовые бюджеты превышены — согласуй с GM","✔ в рамках стартовых бюджетов: инвентарь + броня + хром") | I5: Остаток бюджета снаряжения (2 550 €$) остаётся при тебе наличными (CP:R стр. 104: «You keep anything you don’t spend»), а остаток 800 €$ на моду и фэшн-хром сгорает. +1500 €$ «от корпорации» — только на импланты, и вместе с обязательным Neural Link.
B7: Ⅰ · ОРУЖИЕ · СТОЛБЕЦ «В РУКАХ 1–4» ВЫНОСИТ ОРУЖИЕ НА ЛИСТ 02
B8: № | C8: НАЗВАНИЕ | D8: ТИП | E8: НАВЫК | F8: УРОН | G8: ROF | H8: МАГ. | I8: ПАТРОНЫ | J8: КАЧЕСТВО | K8: В РУКАХ 1–4 | L8: БАЗА АТАКИ | M8: ЗАМЕТКИ
B9: 1 | C9: Con Arms Unity | D9: =IFERROR(INDEX('КАТАЛОГ'!$C$2:$C$1093,MATCH($C9,'КАТАЛОГ'!$A$2:$A$1093,0)),"") | E9: =IFERROR(INDEX('КАТАЛОГ'!$D$2:$D$1093,MATCH($C9,'КАТАЛОГ'!$A$2:$A$1093,0)),"") | F9: =IFERROR(INDEX('КАТАЛОГ'!$E$2:$E$1093,MATCH($C9,'КАТАЛОГ'!$A$2:$A$1093,0)),"") | G9: =IFERROR(INDEX('КАТАЛОГ'!$F$2:$F$1093,MATCH($C9,'КАТАЛОГ'!$A$2:$A$1093,0)),"") | H9: =IFERROR(INDEX('КАТАЛОГ'!$G$2:$G$1093,MATCH($C9,'КАТАЛОГ'!$A$2:$A$1093,0)),"") | I9: Basic ×40 | J9: Standard | K9: 1 | L9: =IF($C9="","",IFERROR(INDEX('03 НАВЫКИ'!$I$5:$I$76,MATCH($E9,'03 НАВЫКИ'!$C$5:$C$76,0))+IF($J9="Excellent",1,IF($J9="Poor",-1,0)),0)) | M9: Табельный. Power Rebuild: криты +5 урона
B10: 2 | C10: Rostović DB-2 Satara | D10: =IFERROR(INDEX('КАТАЛОГ'!$C$2:$C$1093,MATCH($C10,'КАТАЛОГ'!$A$2:$A$1093,0)),"") | E10: =IFERROR(INDEX('КАТАЛОГ'!$D$2:$D$1093,MATCH($C10,'КАТАЛОГ'!$A$2:$A$1093,0)),"") | F10: =IFERROR(INDEX('КАТАЛОГ'!$E$2:$E$1093,MATCH($C10,'КАТАЛОГ'!$A$2:$A$1093,0)),"") | G10: =IFERROR(INDEX('КАТАЛОГ'!$F$2:$F$1093,MATCH($C10,'КАТАЛОГ'!$A$2:$A$1093,0)),"") | H10: =IFERROR(INDEX('КАТАЛОГ'!$G$2:$G$1093,MATCH($C10,'КАТАЛОГ'!$A$2:$A$1093,0)),"") | I10: Basic ×20 | J10: Standard | K10: 2 | L10: =IF($C10="","",IFERROR(INDEX('03 НАВЫКИ'!$I$5:$I$76,MATCH($E10,'03 НАВЫКИ'!$C$5:$C$76,0))+IF($J10="Excellent",1,IF($J10="Poor",-1,0)),0)) | M10: Tech Rebuild: зарядка → половина SP и стрельба через тонкие укрытия
B11: 3 | D11: =IFERROR(INDEX('КАТАЛОГ'!$C$2:$C$1093,MATCH($C11,'КАТАЛОГ'!$A$2:$A$1093,0)),"") | E11: =IFERROR(INDEX('КАТАЛОГ'!$D$2:$D$1093,MATCH($C11,'КАТАЛОГ'!$A$2:$A$1093,0)),"") | F11: =IFERROR(INDEX('КАТАЛОГ'!$E$2:$E$1093,MATCH($C11,'КАТАЛОГ'!$A$2:$A$1093,0)),"") | G11: =IFERROR(INDEX('КАТАЛОГ'!$F$2:$F$1093,MATCH($C11,'КАТАЛОГ'!$A$2:$A$1093,0)),"") | H11: =IFERROR(INDEX('КАТАЛОГ'!$G$2:$G$1093,MATCH($C11,'КАТАЛОГ'!$A$2:$A$1093,0)),"") | J11: Standard | L11: =IF($C11="","",IFERROR(INDEX('03 НАВЫКИ'!$I$5:$I$76,MATCH($E11,'03 НАВЫКИ'!$C$5:$C$76,0))+IF($J11="Excellent",1,IF($J11="Poor",-1,0)),0))
B12: 4 | D12: =IFERROR(INDEX('КАТАЛОГ'!$C$2:$C$1093,MATCH($C12,'КАТАЛОГ'!$A$2:$A$1093,0)),"") | E12: =IFERROR(INDEX('КАТАЛОГ'!$D$2:$D$1093,MATCH($C12,'КАТАЛОГ'!$A$2:$A$1093,0)),"") | F12: =IFERROR(INDEX('КАТАЛОГ'!$E$2:$E$1093,MATCH($C12,'КАТАЛОГ'!$A$2:$A$1093,0)),"") | G12: =IFERROR(INDEX('КАТАЛОГ'!$F$2:$F$1093,MATCH($C12,'КАТАЛОГ'!$A$2:$A$1093,0)),"") | H12: =IFERROR(INDEX('КАТАЛОГ'!$G$2:$G$1093,MATCH($C12,'КАТАЛОГ'!$A$2:$A$1093,0)),"") | J12: Standard | L12: =IF($C12="","",IFERROR(INDEX('03 НАВЫКИ'!$I$5:$I$76,MATCH($E12,'03 НАВЫКИ'!$C$5:$C$76,0))+IF($J12="Excellent",1,IF($J12="Poor",-1,0)),0))
B13: 5 | D13: =IFERROR(INDEX('КАТАЛОГ'!$C$2:$C$1093,MATCH($C13,'КАТАЛОГ'!$A$2:$A$1093,0)),"") | E13: =IFERROR(INDEX('КАТАЛОГ'!$D$2:$D$1093,MATCH($C13,'КАТАЛОГ'!$A$2:$A$1093,0)),"") | F13: =IFERROR(INDEX('КАТАЛОГ'!$E$2:$E$1093,MATCH($C13,'КАТАЛОГ'!$A$2:$A$1093,0)),"") | G13: =IFERROR(INDEX('КАТАЛОГ'!$F$2:$F$1093,MATCH($C13,'КАТАЛОГ'!$A$2:$A$1093,0)),"") | H13: =IFERROR(INDEX('КАТАЛОГ'!$G$2:$G$1093,MATCH($C13,'КАТАЛОГ'!$A$2:$A$1093,0)),"") | J13: Standard | L13: =IF($C13="","",IFERROR(INDEX('03 НАВЫКИ'!$I$5:$I$76,MATCH($E13,'03 НАВЫКИ'!$C$5:$C$76,0))+IF($J13="Excellent",1,IF($J13="Poor",-1,0)),0))
B14: 6 | D14: =IFERROR(INDEX('КАТАЛОГ'!$C$2:$C$1093,MATCH($C14,'КАТАЛОГ'!$A$2:$A$1093,0)),"") | E14: =IFERROR(INDEX('КАТАЛОГ'!$D$2:$D$1093,MATCH($C14,'КАТАЛОГ'!$A$2:$A$1093,0)),"") | F14: =IFERROR(INDEX('КАТАЛОГ'!$E$2:$E$1093,MATCH($C14,'КАТАЛОГ'!$A$2:$A$1093,0)),"") | G14: =IFERROR(INDEX('КАТАЛОГ'!$F$2:$F$1093,MATCH($C14,'КАТАЛОГ'!$A$2:$A$1093,0)),"") | H14: =IFERROR(INDEX('КАТАЛОГ'!$G$2:$G$1093,MATCH($C14,'КАТАЛОГ'!$A$2:$A$1093,0)),"") | J14: Standard | L14: =IF($C14="","",IFERROR(INDEX('03 НАВЫКИ'!$I$5:$I$76,MATCH($E14,'03 НАВЫКИ'!$C$5:$C$76,0))+IF($J14="Excellent",1,IF($J14="Poor",-1,0)),0))
B15: 7 | D15: =IFERROR(INDEX('КАТАЛОГ'!$C$2:$C$1093,MATCH($C15,'КАТАЛОГ'!$A$2:$A$1093,0)),"") | E15: =IFERROR(INDEX('КАТАЛОГ'!$D$2:$D$1093,MATCH($C15,'КАТАЛОГ'!$A$2:$A$1093,0)),"") | F15: =IFERROR(INDEX('КАТАЛОГ'!$E$2:$E$1093,MATCH($C15,'КАТАЛОГ'!$A$2:$A$1093,0)),"") | G15: =IFERROR(INDEX('КАТАЛОГ'!$F$2:$F$1093,MATCH($C15,'КАТАЛОГ'!$A$2:$A$1093,0)),"") | H15: =IFERROR(INDEX('КАТАЛОГ'!$G$2:$G$1093,MATCH($C15,'КАТАЛОГ'!$A$2:$A$1093,0)),"") | J15: Standard | L15: =IF($C15="","",IFERROR(INDEX('03 НАВЫКИ'!$I$5:$I$76,MATCH($E15,'03 НАВЫКИ'!$C$5:$C$76,0))+IF($J15="Excellent",1,IF($J15="Poor",-1,0)),0))
B16: 8 | D16: =IFERROR(INDEX('КАТАЛОГ'!$C$2:$C$1093,MATCH($C16,'КАТАЛОГ'!$A$2:$A$1093,0)),"") | E16: =IFERROR(INDEX('КАТАЛОГ'!$D$2:$D$1093,MATCH($C16,'КАТАЛОГ'!$A$2:$A$1093,0)),"") | F16: =IFERROR(INDEX('КАТАЛОГ'!$E$2:$E$1093,MATCH($C16,'КАТАЛОГ'!$A$2:$A$1093,0)),"") | G16: =IFERROR(INDEX('КАТАЛОГ'!$F$2:$F$1093,MATCH($C16,'КАТАЛОГ'!$A$2:$A$1093,0)),"") | H16: =IFERROR(INDEX('КАТАЛОГ'!$G$2:$G$1093,MATCH($C16,'КАТАЛОГ'!$A$2:$A$1093,0)),"") | J16: Standard | L16: =IF($C16="","",IFERROR(INDEX('03 НАВЫКИ'!$I$5:$I$76,MATCH($E16,'03 НАВЫКИ'!$C$5:$C$76,0))+IF($J16="Excellent",1,IF($J16="Poor",-1,0)),0))
B17: Атака = 1d10 + «БАЗА АТАКИ» (это уровень навыка + стата с учётом штрафа брони). Патроны пиши прямо тут: «AP ×24», «Basic ×30».
B18: УЧЁТ ДЕНЕГ: траты считаются из блока Ⅲ «ИНВЕНТАРЬ» — оружие, патроны и снаряжение впиши и сюда (для игры), и туда (для бюджета). Броня считается из блока Ⅱ (цена в колонке N, в бюджет — O), хром — с листа 04. Броню и хром в инвентарь дублировать НЕ надо: иначе они посчитаются дважды.
B19: Ⅱ · БРОНЯ И ЩИТ · В ЛОКАЦИИ РАБОТАЕТ ТОЛЬКО ЛУЧШИЙ SP, ШТРАФ БЕРЁТСЯ ОДИН РАЗ · ЦЕНА И УЧЁТ В БЮДЖЕТЕ — КОЛОНКИ N И O
B20: № | C20: НАЗВАНИЕ | D20: ЛОКАЦИЯ | E20: НАДЕТО | F20: SP | G20: HP (ЩИТ) | H20: ШТРАФ REF | I20: ШТРАФ DEX | J20: ШТРАФ MOVE | K20: SP СЕЙЧАС | L20: ЭФФ. SP | M20: ЗАМЕТКИ | N20: ЦЕНА €$ | O20: В БЮДЖЕТ €$
B21: 1 | C21: Light Armorjack | D21: Тело | E21: Да | F21: =IFERROR(INDEX('КАТАЛОГ'!$H$2:$H$1093,MATCH($C21,'КАТАЛОГ'!$A$2:$A$1093,0)),0) | G21: =IFERROR(INDEX('КАТАЛОГ'!$I$2:$I$1093,MATCH($C21,'КАТАЛОГ'!$A$2:$A$1093,0)),0) | H21: =IFERROR(INDEX('КАТАЛОГ'!$J$2:$J$1093,MATCH($C21,'КАТАЛОГ'!$A$2:$A$1093,0)),0) | I21: =IFERROR(INDEX('КАТАЛОГ'!$K$2:$K$1093,MATCH($C21,'КАТАЛОГ'!$A$2:$A$1093,0)),0) | J21: =IFERROR(INDEX('КАТАЛОГ'!$L$2:$L$1093,MATCH($C21,'КАТАЛОГ'!$A$2:$A$1093,0)),0) | L21: =IF($E21<>"Да",0,IF($K21<>"",$K21,$F21)) | M21: SP 11, штрафа нет — уклонение работает | N21: =IF($C21="",0,IFERROR(INDEX('КАТАЛОГ'!$R$2:$R$1093,MATCH($C21,'КАТАЛОГ'!$A$2:$A$1093,0)),0)) | O21: =IF($C21="",0,IF(COUNTIF($C$34:$C$53,$C21)>0,0,$N21))
B22: 2 | C22: Light Armorjack | D22: Голова | E22: Да | F22: =IFERROR(INDEX('КАТАЛОГ'!$H$2:$H$1093,MATCH($C22,'КАТАЛОГ'!$A$2:$A$1093,0)),0) | G22: =IFERROR(INDEX('КАТАЛОГ'!$I$2:$I$1093,MATCH($C22,'КАТАЛОГ'!$A$2:$A$1093,0)),0) | H22: =IFERROR(INDEX('КАТАЛОГ'!$J$2:$J$1093,MATCH($C22,'КАТАЛОГ'!$A$2:$A$1093,0)),0) | I22: =IFERROR(INDEX('КАТАЛОГ'!$K$2:$K$1093,MATCH($C22,'КАТАЛОГ'!$A$2:$A$1093,0)),0) | J22: =IFERROR(INDEX('КАТАЛОГ'!$L$2:$L$1093,MATCH($C22,'КАТАЛОГ'!$A$2:$A$1093,0)),0) | L22: =IF($E22<>"Да",0,IF($K22<>"",$K22,$F22)) | M22: Покупается отдельно на голову | N22: =IF($C22="",0,IFERROR(INDEX('КАТАЛОГ'!$R$2:$R$1093,MATCH($C22,'КАТАЛОГ'!$A$2:$A$1093,0)),0)) | O22: =IF($C22="",0,IF(COUNTIF($C$34:$C$53,$C22)>0,0,$N22))
B23: 3 | C23: Bulletproof Shield | D23: Щит | E23: Да | F23: =IFERROR(INDEX('КАТАЛОГ'!$H$2:$H$1093,MATCH($C23,'КАТАЛОГ'!$A$2:$A$1093,0)),0) | G23: =IFERROR(INDEX('КАТАЛОГ'!$I$2:$I$1093,MATCH($C23,'КАТАЛОГ'!$A$2:$A$1093,0)),0) | H23: =IFERROR(INDEX('КАТАЛОГ'!$J$2:$J$1093,MATCH($C23,'КАТАЛОГ'!$A$2:$A$1093,0)),0) | I23: =IFERROR(INDEX('КАТАЛОГ'!$K$2:$K$1093,MATCH($C23,'КАТАЛОГ'!$A$2:$A$1093,0)),0) | J23: =IFERROR(INDEX('КАТАЛОГ'!$L$2:$L$1093,MATCH($C23,'КАТАЛОГ'!$A$2:$A$1093,0)),0) | L23: =IF($E23<>"Да",0,IF($K23<>"",$K23,$F23)) | M23: Подвижное укрытие: принимает весь урон в свои HP | N23: =IF($C23="",0,IFERROR(INDEX('КАТАЛОГ'!$R$2:$R$1093,MATCH($C23,'КАТАЛОГ'!$A$2:$A$1093,0)),0)) | O23: =IF($C23="",0,IF(COUNTIF($C$34:$C$53,$C23)>0,0,$N23))
B24: 4 | D24: Тело | E24: Нет | F24: =IFERROR(INDEX('КАТАЛОГ'!$H$2:$H$1093,MATCH($C24,'КАТАЛОГ'!$A$2:$A$1093,0)),0) | G24: =IFERROR(INDEX('КАТАЛОГ'!$I$2:$I$1093,MATCH($C24,'КАТАЛОГ'!$A$2:$A$1093,0)),0) | H24: =IFERROR(INDEX('КАТАЛОГ'!$J$2:$J$1093,MATCH($C24,'КАТАЛОГ'!$A$2:$A$1093,0)),0) | I24: =IFERROR(INDEX('КАТАЛОГ'!$K$2:$K$1093,MATCH($C24,'КАТАЛОГ'!$A$2:$A$1093,0)),0) | J24: =IFERROR(INDEX('КАТАЛОГ'!$L$2:$L$1093,MATCH($C24,'КАТАЛОГ'!$A$2:$A$1093,0)),0) | L24: =IF($E24<>"Да",0,IF($K24<>"",$K24,$F24)) | N24: =IF($C24="",0,IFERROR(INDEX('КАТАЛОГ'!$R$2:$R$1093,MATCH($C24,'КАТАЛОГ'!$A$2:$A$1093,0)),0)) | O24: =IF($C24="",0,IF(COUNTIF($C$34:$C$53,$C24)>0,0,$N24))
B25: 5 | D25: Тело | E25: Нет | F25: =IFERROR(INDEX('КАТАЛОГ'!$H$2:$H$1093,MATCH($C25,'КАТАЛОГ'!$A$2:$A$1093,0)),0) | G25: =IFERROR(INDEX('КАТАЛОГ'!$I$2:$I$1093,MATCH($C25,'КАТАЛОГ'!$A$2:$A$1093,0)),0) | H25: =IFERROR(INDEX('КАТАЛОГ'!$J$2:$J$1093,MATCH($C25,'КАТАЛОГ'!$A$2:$A$1093,0)),0) | I25: =IFERROR(INDEX('КАТАЛОГ'!$K$2:$K$1093,MATCH($C25,'КАТАЛОГ'!$A$2:$A$1093,0)),0) | J25: =IFERROR(INDEX('КАТАЛОГ'!$L$2:$L$1093,MATCH($C25,'КАТАЛОГ'!$A$2:$A$1093,0)),0) | L25: =IF($E25<>"Да",0,IF($K25<>"",$K25,$F25)) | N25: =IF($C25="",0,IFERROR(INDEX('КАТАЛОГ'!$R$2:$R$1093,MATCH($C25,'КАТАЛОГ'!$A$2:$A$1093,0)),0)) | O25: =IF($C25="",0,IF(COUNTIF($C$34:$C$53,$C25)>0,0,$N25))
B26: 6 | D26: Тело | E26: Нет | F26: =IFERROR(INDEX('КАТАЛОГ'!$H$2:$H$1093,MATCH($C26,'КАТАЛОГ'!$A$2:$A$1093,0)),0) | G26: =IFERROR(INDEX('КАТАЛОГ'!$I$2:$I$1093,MATCH($C26,'КАТАЛОГ'!$A$2:$A$1093,0)),0) | H26: =IFERROR(INDEX('КАТАЛОГ'!$J$2:$J$1093,MATCH($C26,'КАТАЛОГ'!$A$2:$A$1093,0)),0) | I26: =IFERROR(INDEX('КАТАЛОГ'!$K$2:$K$1093,MATCH($C26,'КАТАЛОГ'!$A$2:$A$1093,0)),0) | J26: =IFERROR(INDEX('КАТАЛОГ'!$L$2:$L$1093,MATCH($C26,'КАТАЛОГ'!$A$2:$A$1093,0)),0) | L26: =IF($E26<>"Да",0,IF($K26<>"",$K26,$F26)) | N26: =IF($C26="",0,IFERROR(INDEX('КАТАЛОГ'!$R$2:$R$1093,MATCH($C26,'КАТАЛОГ'!$A$2:$A$1093,0)),0)) | O26: =IF($C26="",0,IF(COUNTIF($C$34:$C$53,$C26)>0,0,$N26))
B27: SP ГОЛОВЫ (НАДЕТОЕ) | D27: =SUMPRODUCT(MAX(($D$21:$D$26="Голова")*($E$21:$E$26="Да")*$L$21:$L$26)) | E27: Работает лучший SP в локации — второй слой не складывается.
B28: SP ТЕЛА (НАДЕТОЕ) | D28: =SUMPRODUCT(MAX(($D$21:$D$26="Тело")*($E$21:$E$26="Да")*$L$21:$L$26)) | E28: Вся надетая броня локации аблейтится одновременно (−1 за каждое попадание).
B29: ЩИТ: HP | D29: =SUMPRODUCT(MAX(($D$21:$D$26="Щит")*($E$21:$E$26="Да")*$G$21:$G$26)) | E29: Обычный щит 10 HP, усиленный 15 HP. Взять/бросить — Действие.
B30: ШТРАФ БРОНИ REF / DEX / MOVE (ПОЛОЖИТЕЛЬНЫЙ) | D30: =-SUMPRODUCT(MIN(($E$21:$E$26="Да")*$H$21:$H$26)) | E30: =-SUMPRODUCT(MIN(($E$21:$E$26="Да")*$I$21:$I$26)) | F30: =-SUMPRODUCT(MIN(($E$21:$E$26="Да")*$J$21:$J$26)) | G30: Самый строгий штраф из надетого, применяется один раз — он уже вычтен из REF/DEX/MOVE на листе 02. Хочешь ослабить броню — снимай вещи, а не правь эти цифры.
B32: Ⅲ · ИНВЕНТАРЬ · СУММЫ ОТСЮДА ИДУТ В ОБА БЮДЖЕТА ВМЕСТЕ С БРОНЁЙ (Ⅱ) И ХРОМОМ (ЛИСТ 04)
B33: № | C33: НАЗВАНИЕ | D33: КАТЕГОРИЯ | E33: ПОДТИП | F33: КОЛ-ВО | G33: ЦЕНА €$ | H33: ЦЕНА СВОЯ | I33: СУММА | J33: ГДЕ НОСИТ | K33: ЗАМЕТКА | M33: ОПИСАНИЕ ИЗ КАТАЛОГА
B34: 1 | C34: Con Arms Unity | D34: =IFERROR(INDEX('КАТАЛОГ'!$B$2:$B$1093,MATCH($C34,'КАТАЛОГ'!$A$2:$A$1093,0)),"") | E34: =IFERROR(INDEX('КАТАЛОГ'!$C$2:$C$1093,MATCH($C34,'КАТАЛОГ'!$A$2:$A$1093,0)),"") | G34: =IFERROR(INDEX('КАТАЛОГ'!$R$2:$R$1093,MATCH($C34,'КАТАЛОГ'!$A$2:$A$1093,0)),"") | I34: =IF($C34="",0,IF($H34<>"",$H34,IF(ISNUMBER($G34),$G34,0))*IF($F34="",1,$F34)) | J34: в кобуре | M34: =IFERROR(LEFT(INDEX('КАТАЛОГ'!$T$2:$T$1093,MATCH($C34,'КАТАЛОГ'!$A$2:$A$1093,0)),90),"")
B35: 2 | C35: Rostović DB-2 Satara | D35: =IFERROR(INDEX('КАТАЛОГ'!$B$2:$B$1093,MATCH($C35,'КАТАЛОГ'!$A$2:$A$1093,0)),"") | E35: =IFERROR(INDEX('КАТАЛОГ'!$C$2:$C$1093,MATCH($C35,'КАТАЛОГ'!$A$2:$A$1093,0)),"") | G35: =IFERROR(INDEX('КАТАЛОГ'!$R$2:$R$1093,MATCH($C35,'КАТАЛОГ'!$A$2:$A$1093,0)),"") | I35: =IF($C35="",0,IF($H35<>"",$H35,IF(ISNUMBER($G35),$G35,0))*IF($F35="",1,$F35)) | J35: за спиной / в машине | M35: =IFERROR(LEFT(INDEX('КАТАЛОГ'!$T$2:$T$1093,MATCH($C35,'КАТАЛОГ'!$A$2:$A$1093,0)),90),"")
B36: 3 | C36: Handcuffs | D36: =IFERROR(INDEX('КАТАЛОГ'!$B$2:$B$1093,MATCH($C36,'КАТАЛОГ'!$A$2:$A$1093,0)),"") | E36: =IFERROR(INDEX('КАТАЛОГ'!$C$2:$C$1093,MATCH($C36,'КАТАЛОГ'!$A$2:$A$1093,0)),"") | G36: =IFERROR(INDEX('КАТАЛОГ'!$R$2:$R$1093,MATCH($C36,'КАТАЛОГ'!$A$2:$A$1093,0)),"") | I36: =IF($C36="",0,IF($H36<>"",$H36,IF(ISNUMBER($G36),$G36,0))*IF($F36="",1,$F36)) | J36: на поясе | M36: =IFERROR(LEFT(INDEX('КАТАЛОГ'!$T$2:$T$1093,MATCH($C36,'КАТАЛОГ'!$A$2:$A$1093,0)),90),"")
B37: 4 | C37: Basic | D37: =IFERROR(INDEX('КАТАЛОГ'!$B$2:$B$1093,MATCH($C37,'КАТАЛОГ'!$A$2:$A$1093,0)),"") | E37: =IFERROR(INDEX('КАТАЛОГ'!$C$2:$C$1093,MATCH($C37,'КАТАЛОГ'!$A$2:$A$1093,0)),"") | F37: 6 | G37: =IFERROR(INDEX('КАТАЛОГ'!$R$2:$R$1093,MATCH($C37,'КАТАЛОГ'!$A$2:$A$1093,0)),"") | I37: =IF($C37="",0,IF($H37<>"",$H37,IF(ISNUMBER($G37),$G37,0))*IF($F37="",1,$F37)) | J37: подсумок | K37: 40 пистолетных + 20 картечи | M37: =IFERROR(LEFT(INDEX('КАТАЛОГ'!$T$2:$T$1093,MATCH($C37,'КАТАЛОГ'!$A$2:$A$1093,0)),90),"")
B38: 5 | C38: Agent (Standard) | D38: =IFERROR(INDEX('КАТАЛОГ'!$B$2:$B$1093,MATCH($C38,'КАТАЛОГ'!$A$2:$A$1093,0)),"") | E38: =IFERROR(INDEX('КАТАЛОГ'!$C$2:$C$1093,MATCH($C38,'КАТАЛОГ'!$A$2:$A$1093,0)),"") | G38: =IFERROR(INDEX('КАТАЛОГ'!$R$2:$R$1093,MATCH($C38,'КАТАЛОГ'!$A$2:$A$1093,0)),"") | I38: =IF($C38="",0,IF($H38<>"",$H38,IF(ISNUMBER($G38),$G38,0))*IF($F38="",1,$F38)) | J38: карман | M38: =IFERROR(LEFT(INDEX('КАТАЛОГ'!$T$2:$T$1093,MATCH($C38,'КАТАЛОГ'!$A$2:$A$1093,0)),90),"")
B39: 6 | C39: Medtech Bag | D39: =IFERROR(INDEX('КАТАЛОГ'!$B$2:$B$1093,MATCH($C39,'КАТАЛОГ'!$A$2:$A$1093,0)),"") | E39: =IFERROR(INDEX('КАТАЛОГ'!$C$2:$C$1093,MATCH($C39,'КАТАЛОГ'!$A$2:$A$1093,0)),"") | G39: =IFERROR(INDEX('КАТАЛОГ'!$R$2:$R$1093,MATCH($C39,'КАТАЛОГ'!$A$2:$A$1093,0)),"") | I39: =IF($C39="",0,IF($H39<>"",$H39,IF(ISNUMBER($G39),$G39,0))*IF($F39="",1,$F39)) | J39: в багажнике | M39: =IFERROR(LEFT(INDEX('КАТАЛОГ'!$T$2:$T$1093,MATCH($C39,'КАТАЛОГ'!$A$2:$A$1093,0)),90),"")
B40: 7 | C40: Flashlight | D40: =IFERROR(INDEX('КАТАЛОГ'!$B$2:$B$1093,MATCH($C40,'КАТАЛОГ'!$A$2:$A$1093,0)),"") | E40: =IFERROR(INDEX('КАТАЛОГ'!$C$2:$C$1093,MATCH($C40,'КАТАЛОГ'!$A$2:$A$1093,0)),"") | G40: =IFERROR(INDEX('КАТАЛОГ'!$R$2:$R$1093,MATCH($C40,'КАТАЛОГ'!$A$2:$A$1093,0)),"") | I40: =IF($C40="",0,IF($H40<>"",$H40,IF(ISNUMBER($G40),$G40,0))*IF($F40="",1,$F40)) | J40: на поясе | M40: =IFERROR(LEFT(INDEX('КАТАЛОГ'!$T$2:$T$1093,MATCH($C40,'КАТАЛОГ'!$A$2:$A$1093,0)),90),"")
B41: 8 | C41: Duct Tape | D41: =IFERROR(INDEX('КАТАЛОГ'!$B$2:$B$1093,MATCH($C41,'КАТАЛОГ'!$A$2:$A$1093,0)),"") | E41: =IFERROR(INDEX('КАТАЛОГ'!$C$2:$C$1093,MATCH($C41,'КАТАЛОГ'!$A$2:$A$1093,0)),"") | G41: =IFERROR(INDEX('КАТАЛОГ'!$R$2:$R$1093,MATCH($C41,'КАТАЛОГ'!$A$2:$A$1093,0)),"") | I41: =IF($C41="",0,IF($H41<>"",$H41,IF(ISNUMBER($G41),$G41,0))*IF($F41="",1,$F41)) | J41: на поясе | M41: =IFERROR(LEFT(INDEX('КАТАЛОГ'!$T$2:$T$1093,MATCH($C41,'КАТАЛОГ'!$A$2:$A$1093,0)),90),"")
B42: 9 | C42: Bulletproof Shield | D42: =IFERROR(INDEX('КАТАЛОГ'!$B$2:$B$1093,MATCH($C42,'КАТАЛОГ'!$A$2:$A$1093,0)),"") | E42: =IFERROR(INDEX('КАТАЛОГ'!$C$2:$C$1093,MATCH($C42,'КАТАЛОГ'!$A$2:$A$1093,0)),"") | G42: =IFERROR(INDEX('КАТАЛОГ'!$R$2:$R$1093,MATCH($C42,'КАТАЛОГ'!$A$2:$A$1093,0)),"") | I42: =IF($C42="",0,IF($H42<>"",$H42,IF(ISNUMBER($G42),$G42,0))*IF($F42="",1,$F42)) | J42: в руке / за спиной | M42: =IFERROR(LEFT(INDEX('КАТАЛОГ'!$T$2:$T$1093,MATCH($C42,'КАТАЛОГ'!$A$2:$A$1093,0)),90),"")
B43: 10 | C43: Nomad Leathers Jacket | D43: =IFERROR(INDEX('КАТАЛОГ'!$B$2:$B$1093,MATCH($C43,'КАТАЛОГ'!$A$2:$A$1093,0)),"") | E43: =IFERROR(INDEX('КАТАЛОГ'!$C$2:$C$1093,MATCH($C43,'КАТАЛОГ'!$A$2:$A$1093,0)),"") | G43: =IFERROR(INDEX('КАТАЛОГ'!$R$2:$R$1093,MATCH($C43,'КАТАЛОГ'!$A$2:$A$1093,0)),"") | I43: =IF($C43="",0,IF($H43<>"",$H43,IF(ISNUMBER($G43),$G43,0))*IF($F43="",1,$F43)) | J43: комплект «детектив» | M43: =IFERROR(LEFT(INDEX('КАТАЛОГ'!$T$2:$T$1093,MATCH($C43,'КАТАЛОГ'!$A$2:$A$1093,0)),90),"")
B44: 11 | C44: Nomad Leathers Bottoms | D44: =IFERROR(INDEX('КАТАЛОГ'!$B$2:$B$1093,MATCH($C44,'КАТАЛОГ'!$A$2:$A$1093,0)),"") | E44: =IFERROR(INDEX('КАТАЛОГ'!$C$2:$C$1093,MATCH($C44,'КАТАЛОГ'!$A$2:$A$1093,0)),"") | G44: =IFERROR(INDEX('КАТАЛОГ'!$R$2:$R$1093,MATCH($C44,'КАТАЛОГ'!$A$2:$A$1093,0)),"") | I44: =IF($C44="",0,IF($H44<>"",$H44,IF(ISNUMBER($G44),$G44,0))*IF($F44="",1,$F44)) | J44: комплект «детектив» | M44: =IFERROR(LEFT(INDEX('КАТАЛОГ'!$T$2:$T$1093,MATCH($C44,'КАТАЛОГ'!$A$2:$A$1093,0)),90),"")
B45: 12 | C45: Nomad Leathers Footwear | D45: =IFERROR(INDEX('КАТАЛОГ'!$B$2:$B$1093,MATCH($C45,'КАТАЛОГ'!$A$2:$A$1093,0)),"") | E45: =IFERROR(INDEX('КАТАЛОГ'!$C$2:$C$1093,MATCH($C45,'КАТАЛОГ'!$A$2:$A$1093,0)),"") | G45: =IFERROR(INDEX('КАТАЛОГ'!$R$2:$R$1093,MATCH($C45,'КАТАЛОГ'!$A$2:$A$1093,0)),"") | I45: =IF($C45="",0,IF($H45<>"",$H45,IF(ISNUMBER($G45),$G45,0))*IF($F45="",1,$F45)) | J45: комплект «детектив» | M45: =IFERROR(LEFT(INDEX('КАТАЛОГ'!$T$2:$T$1093,MATCH($C45,'КАТАЛОГ'!$A$2:$A$1093,0)),90),"")
B46: 13 | C46: Nomad Leathers Top | D46: =IFERROR(INDEX('КАТАЛОГ'!$B$2:$B$1093,MATCH($C46,'КАТАЛОГ'!$A$2:$A$1093,0)),"") | E46: =IFERROR(INDEX('КАТАЛОГ'!$C$2:$C$1093,MATCH($C46,'КАТАЛОГ'!$A$2:$A$1093,0)),"") | G46: =IFERROR(INDEX('КАТАЛОГ'!$R$2:$R$1093,MATCH($C46,'КАТАЛОГ'!$A$2:$A$1093,0)),"") | I46: =IF($C46="",0,IF($H46<>"",$H46,IF(ISNUMBER($G46),$G46,0))*IF($F46="",1,$F46)) | J46: комплект «детектив» | M46: =IFERROR(LEFT(INDEX('КАТАЛОГ'!$T$2:$T$1093,MATCH($C46,'КАТАЛОГ'!$A$2:$A$1093,0)),90),"")
B47: 14 | C47: Nomad Leathers Mirrorshades | D47: =IFERROR(INDEX('КАТАЛОГ'!$B$2:$B$1093,MATCH($C47,'КАТАЛОГ'!$A$2:$A$1093,0)),"") | E47: =IFERROR(INDEX('КАТАЛОГ'!$C$2:$C$1093,MATCH($C47,'КАТАЛОГ'!$A$2:$A$1093,0)),"") | G47: =IFERROR(INDEX('КАТАЛОГ'!$R$2:$R$1093,MATCH($C47,'КАТАЛОГ'!$A$2:$A$1093,0)),"") | I47: =IF($C47="",0,IF($H47<>"",$H47,IF(ISNUMBER($G47),$G47,0))*IF($F47="",1,$F47)) | J47: комплект «детектив» | K47: комплект «детектив» — зеркальные стёкла в стиле Nomad | M47: =IFERROR(LEFT(INDEX('КАТАЛОГ'!$T$2:$T$1093,MATCH($C47,'КАТАЛОГ'!$A$2:$A$1093,0)),90),"")
B48: 15 | C48: Generic Chic Jacket | D48: =IFERROR(INDEX('КАТАЛОГ'!$B$2:$B$1093,MATCH($C48,'КАТАЛОГ'!$A$2:$A$1093,0)),"") | E48: =IFERROR(INDEX('КАТАЛОГ'!$C$2:$C$1093,MATCH($C48,'КАТАЛОГ'!$A$2:$A$1093,0)),"") | G48: =IFERROR(INDEX('КАТАЛОГ'!$R$2:$R$1093,MATCH($C48,'КАТАЛОГ'!$A$2:$A$1093,0)),"") | I48: =IF($C48="",0,IF($H48<>"",$H48,IF(ISNUMBER($G48),$G48,0))*IF($F48="",1,$F48)) | J48: рабочий комплект — не выделяться | M48: =IFERROR(LEFT(INDEX('КАТАЛОГ'!$T$2:$T$1093,MATCH($C48,'КАТАЛОГ'!$A$2:$A$1093,0)),90),"")
B49: 16 | C49: Generic Chic Bottoms | D49: =IFERROR(INDEX('КАТАЛОГ'!$B$2:$B$1093,MATCH($C49,'КАТАЛОГ'!$A$2:$A$1093,0)),"") | E49: =IFERROR(INDEX('КАТАЛОГ'!$C$2:$C$1093,MATCH($C49,'КАТАЛОГ'!$A$2:$A$1093,0)),"") | G49: =IFERROR(INDEX('КАТАЛОГ'!$R$2:$R$1093,MATCH($C49,'КАТАЛОГ'!$A$2:$A$1093,0)),"") | I49: =IF($C49="",0,IF($H49<>"",$H49,IF(ISNUMBER($G49),$G49,0))*IF($F49="",1,$F49)) | J49: рабочий комплект | M49: =IFERROR(LEFT(INDEX('КАТАЛОГ'!$T$2:$T$1093,MATCH($C49,'КАТАЛОГ'!$A$2:$A$1093,0)),90),"")
B50: 17 | C50: Generic Chic Top | D50: =IFERROR(INDEX('КАТАЛОГ'!$B$2:$B$1093,MATCH($C50,'КАТАЛОГ'!$A$2:$A$1093,0)),"") | E50: =IFERROR(INDEX('КАТАЛОГ'!$C$2:$C$1093,MATCH($C50,'КАТАЛОГ'!$A$2:$A$1093,0)),"") | G50: =IFERROR(INDEX('КАТАЛОГ'!$R$2:$R$1093,MATCH($C50,'КАТАЛОГ'!$A$2:$A$1093,0)),"") | I50: =IF($C50="",0,IF($H50<>"",$H50,IF(ISNUMBER($G50),$G50,0))*IF($F50="",1,$F50)) | J50: рабочий комплект | M50: =IFERROR(LEFT(INDEX('КАТАЛОГ'!$T$2:$T$1093,MATCH($C50,'КАТАЛОГ'!$A$2:$A$1093,0)),90),"")
B51: 18 | C51: Generic Chic Footwear | D51: =IFERROR(INDEX('КАТАЛОГ'!$B$2:$B$1093,MATCH($C51,'КАТАЛОГ'!$A$2:$A$1093,0)),"") | E51: =IFERROR(INDEX('КАТАЛОГ'!$C$2:$C$1093,MATCH($C51,'КАТАЛОГ'!$A$2:$A$1093,0)),"") | G51: =IFERROR(INDEX('КАТАЛОГ'!$R$2:$R$1093,MATCH($C51,'КАТАЛОГ'!$A$2:$A$1093,0)),"") | I51: =IF($C51="",0,IF($H51<>"",$H51,IF(ISNUMBER($G51),$G51,0))*IF($F51="",1,$F51)) | J51: рабочий комплект | M51: =IFERROR(LEFT(INDEX('КАТАЛОГ'!$T$2:$T$1093,MATCH($C51,'КАТАЛОГ'!$A$2:$A$1093,0)),90),"")
B52: 19 | C52: Generic Chic Hats | D52: =IFERROR(INDEX('КАТАЛОГ'!$B$2:$B$1093,MATCH($C52,'КАТАЛОГ'!$A$2:$A$1093,0)),"") | E52: =IFERROR(INDEX('КАТАЛОГ'!$C$2:$C$1093,MATCH($C52,'КАТАЛОГ'!$A$2:$A$1093,0)),"") | G52: =IFERROR(INDEX('КАТАЛОГ'!$R$2:$R$1093,MATCH($C52,'КАТАЛОГ'!$A$2:$A$1093,0)),"") | I52: =IF($C52="",0,IF($H52<>"",$H52,IF(ISNUMBER($G52),$G52,0))*IF($F52="",1,$F52)) | J52: рабочий комплект | M52: =IFERROR(LEFT(INDEX('КАТАЛОГ'!$T$2:$T$1093,MATCH($C52,'КАТАЛОГ'!$A$2:$A$1093,0)),90),"")
B53: 20 | D53: =IFERROR(INDEX('КАТАЛОГ'!$B$2:$B$1093,MATCH($C53,'КАТАЛОГ'!$A$2:$A$1093,0)),"") | E53: =IFERROR(INDEX('КАТАЛОГ'!$C$2:$C$1093,MATCH($C53,'КАТАЛОГ'!$A$2:$A$1093,0)),"") | G53: =IFERROR(INDEX('КАТАЛОГ'!$R$2:$R$1093,MATCH($C53,'КАТАЛОГ'!$A$2:$A$1093,0)),"") | I53: =IF($C53="",0,IF($H53<>"",$H53,IF(ISNUMBER($G53),$G53,0))*IF($F53="",1,$F53)) | M53: =IFERROR(LEFT(INDEX('КАТАЛОГ'!$T$2:$T$1093,MATCH($C53,'КАТАЛОГ'!$A$2:$A$1093,0)),90),"")
B54: ИТОГО ПО ИНВЕНТАРЮ (€$) | E54: =SUM($I$34:$I$53) | F54: СНАРЯЖЕНИЕ + СТИЛЬ, ВСЁ | H54: =SUM($I$34:$I$53) | I54: =IF(($G$3+$G$4)>($E$3+$E$4),"⚠ потрачено больше стартовых 3350 €$ — часть вещей куплена уже в игре","")
B56: Ⅳ · КАССА · ДОХОДЫ И ТРАТЫ В ИГРЕ
B57: ДАТА | C57: ЧТО (ДЕЛО / ПОКУПКА) | E57: ОБОРОТ ± €$ | F57: БАЛАНС | G57: ЗАМЕТКА
F58: =$I$3+SUM($E$58:$E58)
F59: =$I$3+SUM($E$58:$E59)
F60: =$I$3+SUM($E$58:$E60)
F61: =$I$3+SUM($E$58:$E61)
F62: =$I$3+SUM($E$58:$E62)
F63: =$I$3+SUM($E$58:$E63)
F64: =$I$3+SUM($E$58:$E64)
F65: =$I$3+SUM($E$58:$E65)
F66: =$I$3+SUM($E$58:$E66)
F67: =$I$3+SUM($E$58:$E67)
F68: =$I$3+SUM($E$58:$E68)
F69: =$I$3+SUM($E$58:$E69)
... F77: =$I$3+SUM($E$58:$E77)
E78: =SUM($E$58:$E$77) | F78: =$I$3+SUM($E$58:$E$77) | G78: Наличные = стартовый остаток + оборот. Хочешь вести наличные вручную — перебей «БАЛАНС» цифрой.
B80: ПАМЯТКА ПО ДЕНЬГАМ: 2550 €$ — оружие/броня/снаряжение/хром; 800 €$ — только Fashion + Fashionware; жильё (1 000 €$) + Kibble Lifestyle (100 €$/мес) = 1 100 €$ к 1-му числу, первый месяц покрыт; +1500 €$ «от корпорации» — только на импланты и вместе с обязательным Neural Link. Остаток бюджета снаряжения забираешь наличными, остаток модного бюджета сгорает (CP:R стр. 104). В 2070-х можно купить почти всё напрямую у производителя, но по двойной цене (CEMK: расширенная доступность).

Sheet 06 СОСТОЯНИЕ
B1: СОСТОЯНИЕ ▚ РАНЫ · КРИТ-ТРАВМЫ · ЗАВИСИМОСТИ · IP · ЛОГ ДЕЛ
B2: ТЕКУЩЕЕ СОСТОЯНИЕ ОБЪЕКТА | F2: HP | G2: ='02 ОСНОВА'!$D$25&" / "&'02 ОСНОВА'!$D$24 | H2: СОСТОЯНИЕ | I2: ='02 ОСНОВА'!$G$3 | J2: HP правится на листе 02 (ячейка D25) — здесь всё пересчитается.
B3: СПАСБРОСОК СМЕРТИ (BODY) | D3: ='02 ОСНОВА'!$D$27 | E3: ШТРАФ К СПАСБРОСКАМ | F3: ='02 ОСНОВА'!$D$28 | G3: ОТМЕТКИ ПРОВАЛОВ
B4: Смертельное состояние: HP < 1 → −4 ко всем действиям, −6 MOVE, спасбросок смерти в начале каждого хода. Крит-травма даёт +5 урона напрямую в HP (+1 к штрафу спасброска за такие травмы). Стабилизация: DV10 (лёгкое), DV13 (серьёзное), DV15 (смертельное → 1 HP и минута без сознания).
B6: Ⅰ · КРИТ-ТРАВМЫ · ВЫБЕРИ ЛОКАЦИЮ И БРОСОК 2D6 — ОСТАЛЬНОЕ ПОДТЯНЕТСЯ
B7: № | C7: ЛОКАЦИЯ | D7: 2D6 | E7: ТРАВМА (АВТО) | F7: ЭФФЕКТ (АВТО) | G7: БЫСТРЫЙ ФИКС | H7: ЛЕЧЕНИЕ | I7: СТАТУС | J7: ЗАМЕТКИ
B8: 1 | C8: Тело | E8: =IF($D8="","",IF($C8="Тело",IFERROR(INDEX($C$22:$C$33,MATCH($D8,$B$22:$B$33,0)),"—"),IF($C8="Голова",IFERROR(INDEX($C$37:$C$48,MATCH($D8,$B$37:$B$48,0)),"—"),"—"))) | F8: =IF($D8="","",IF($C8="Тело",IFERROR(INDEX($D$22:$D$33,MATCH($D8,$B$22:$B$33,0)),"—"),IF($C8="Голова",IFERROR(INDEX($D$37:$D$48,MATCH($D8,$B$37:$B$48,0)),"—"),"—"))) | G8: =IF($D8="","",IF($C8="Тело",IFERROR(INDEX($E$22:$E$33,MATCH($D8,$B$22:$B$33,0)),"—"),IF($C8="Голова",IFERROR(INDEX($E$37:$E$48,MATCH($D8,$B$37:$B$48,0)),"—"),"—"))) | H8: =IF($D8="","",IF($C8="Тело",IFERROR(INDEX($F$22:$F$33,MATCH($D8,$B$22:$B$33,0)),"—"),IF($C8="Голова",IFERROR(INDEX($F$37:$F$48,MATCH($D8,$B$37:$B$48,0)),"—"),"—"))) | I8: Нет
B9: 2 | C9: Тело | E9: =IF($D9="","",IF($C9="Тело",IFERROR(INDEX($C$22:$C$33,MATCH($D9,$B$22:$B$33,0)),"—"),IF($C9="Голова",IFERROR(INDEX($C$37:$C$48,MATCH($D9,$B$37:$B$48,0)),"—"),"—"))) | F9: =IF($D9="","",IF($C9="Тело",IFERROR(INDEX($D$22:$D$33,MATCH($D9,$B$22:$B$33,0)),"—"),IF($C9="Голова",IFERROR(INDEX($D$37:$D$48,MATCH($D9,$B$37:$B$48,0)),"—"),"—"))) | G9: =IF($D9="","",IF($C9="Тело",IFERROR(INDEX($E$22:$E$33,MATCH($D9,$B$22:$B$33,0)),"—"),IF($C9="Голова",IFERROR(INDEX($E$37:$E$48,MATCH($D9,$B$37:$B$48,0)),"—"),"—"))) | H9: =IF($D9="","",IF($C9="Тело",IFERROR(INDEX($F$22:$F$33,MATCH($D9,$B$22:$B$33,0)),"—"),IF($C9="Голова",IFERROR(INDEX($F$37:$F$48,MATCH($D9,$B$37:$B$48,0)),"—"),"—"))) | I9: Нет
B10: 3 | C10: Тело | E10: =IF($D10="","",IF($C10="Тело",IFERROR(INDEX($C$22:$C$33,MATCH($D10,$B$22:$B$33,0)),"—"),IF($C10="Голова",IFERROR(INDEX($C$37:$C$48,MATCH($D10,$B$37:$B$48,0)),"—"),"—"))) | F10: =IF($D10="","",IF($C10="Тело",IFERROR(INDEX($D$22:$D$33,MATCH($D10,$B$22:$B$33,0)),"—"),IF($C10="Голова",IFERROR(INDEX($D$37:$D$48,MATCH($D10,$B$37:$B$48,0)),"—"),"—"))) | G10: =IF($D10="","",IF($C10="Тело",IFERROR(INDEX($E$22:$E$33,MATCH($D10,$B$22:$B$33,0)),"—"),IF($C10="Голова",IFERROR(INDEX($E$37:$E$48,MATCH($D10,$B$37:$B$48,0)),"—"),"—"))) | H10: =IF($D10="","",IF($C10="Тело",IFERROR(INDEX($F$22:$F$33,MATCH($D10,$B$22:$B$33,0)),"—"),IF($C10="Голова",IFERROR(INDEX($F$37:$F$48,MATCH($D10,$B$37:$B$48,0)),"—"),"—"))) | I10: Нет
B11: 4 | C11: Тело | E11: =IF($D11="","",IF($C11="Тело",IFERROR(INDEX($C$22:$C$33,MATCH($D11,$B$22:$B$33,0)),"—"),IF($C11="Голова",IFERROR(INDEX($C$37:$C$48,MATCH($D11,$B$37:$B$48,0)),"—"),"—"))) | F11: =IF($D11="","",IF($C11="Тело",IFERROR(INDEX($D$22:$D$33,MATCH($D11,$B$22:$B$33,0)),"—"),IF($C11="Голова",IFERROR(INDEX($D$37:$D$48,MATCH($D11,$B$37:$B$48,0)),"—"),"—"))) | G11: =IF($D11="","",IF($C11="Тело",IFERROR(INDEX($E$22:$E$33,MATCH($D11,$B$22:$B$33,0)),"—"),IF($C11="Голова",IFERROR(INDEX($E$37:$E$48,MATCH($D11,$B$37:$B$48,0)),"—"),"—"))) | H11: =IF($D11="","",IF($C11="Тело",IFERROR(INDEX($F$22:$F$33,MATCH($D11,$B$22:$B$33,0)),"—"),IF($C11="Голова",IFERROR(INDEX($F$37:$F$48,MATCH($D11,$B$37:$B$48,0)),"—"),"—"))) | I11: Нет
B12: 5 | C12: Тело | E12: =IF($D12="","",IF($C12="Тело",IFERROR(INDEX($C$22:$C$33,MATCH($D12,$B$22:$B$33,0)),"—"),IF($C12="Голова",IFERROR(INDEX($C$37:$C$48,MATCH($D12,$B$37:$B$48,0)),"—"),"—"))) | F12: =IF($D12="","",IF($C12="Тело",IFERROR(INDEX($D$22:$D$33,MATCH($D12,$B$22:$B$33,0)),"—"),IF($C12="Голова",IFERROR(INDEX($D$37:$D$48,MATCH($D12,$B$37:$B$48,0)),"—"),"—"))) | G12: =IF($D12="","",IF($C12="Тело",IFERROR(INDEX($E$22:$E$33,MATCH($D12,$B$22:$B$33,0)),"—"),IF($C12="Голова",IFERROR(INDEX($E$37:$E$48,MATCH($D12,$B$37:$B$48,0)),"—"),"—"))) | H12: =IF($D12="","",IF($C12="Тело",IFERROR(INDEX($F$22:$F$33,MATCH($D12,$B$22:$B$33,0)),"—"),IF($C12="Голова",IFERROR(INDEX($F$37:$F$48,MATCH($D12,$B$37:$B$48,0)),"—"),"—"))) | I12: Нет
B13: 6 | C13: Тело | E13: =IF($D13="","",IF($C13="Тело",IFERROR(INDEX($C$22:$C$33,MATCH($D13,$B$22:$B$33,0)),"—"),IF($C13="Голова",IFERROR(INDEX($C$37:$C$48,MATCH($D13,$B$37:$B$48,0)),"—"),"—"))) | F13: =IF($D13="","",IF($C13="Тело",IFERROR(INDEX($D$22:$D$33,MATCH($D13,$B$22:$B$33,0)),"—"),IF($C13="Голова",IFERROR(INDEX($D$37:$D$48,MATCH($D13,$B$37:$B$48,0)),"—"),"—"))) | G13: =IF($D13="","",IF($C13="Тело",IFERROR(INDEX($E$22:$E$33,MATCH($D13,$B$22:$B$33,0)),"—"),IF($C13="Голова",IFERROR(INDEX($E$37:$E$48,MATCH($D13,$B$37:$B$48,0)),"—"),"—"))) | H13: =IF($D13="","",IF($C13="Тело",IFERROR(INDEX($F$22:$F$33,MATCH($D13,$B$22:$B$33,0)),"—"),IF($C13="Голова",IFERROR(INDEX($F$37:$F$48,MATCH($D13,$B$37:$B$48,0)),"—"),"—"))) | I13: Нет
B14: 7 | C14: Тело | E14: =IF($D14="","",IF($C14="Тело",IFERROR(INDEX($C$22:$C$33,MATCH($D14,$B$22:$B$33,0)),"—"),IF($C14="Голова",IFERROR(INDEX($C$37:$C$48,MATCH($D14,$B$37:$B$48,0)),"—"),"—"))) | F14: =IF($D14="","",IF($C14="Тело",IFERROR(INDEX($D$22:$D$33,MATCH($D14,$B$22:$B$33,0)),"—"),IF($C14="Голова",IFERROR(INDEX($D$37:$D$48,MATCH($D14,$B$37:$B$48,0)),"—"),"—"))) | G14: =IF($D14="","",IF($C14="Тело",IFERROR(INDEX($E$22:$E$33,MATCH($D14,$B$22:$B$33,0)),"—"),IF($C14="Голова",IFERROR(INDEX($E$37:$E$48,MATCH($D14,$B$37:$B$48,0)),"—"),"—"))) | H14: =IF($D14="","",IF($C14="Тело",IFERROR(INDEX($F$22:$F$33,MATCH($D14,$B$22:$B$33,0)),"—"),IF($C14="Голова",IFERROR(INDEX($F$37:$F$48,MATCH($D14,$B$37:$B$48,0)),"—"),"—"))) | I14: Нет
B15: 8 | C15: Тело | E15: =IF($D15="","",IF($C15="Тело",IFERROR(INDEX($C$22:$C$33,MATCH($D15,$B$22:$B$33,0)),"—"),IF($C15="Голова",IFERROR(INDEX($C$37:$C$48,MATCH($D15,$B$37:$B$48,0)),"—"),"—"))) | F15: =IF($D15="","",IF($C15="Тело",IFERROR(INDEX($D$22:$D$33,MATCH($D15,$B$22:$B$33,0)),"—"),IF($C15="Голова",IFERROR(INDEX($D$37:$D$48,MATCH($D15,$B$37:$B$48,0)),"—"),"—"))) | G15: =IF($D15="","",IF($C15="Тело",IFERROR(INDEX($E$22:$E$33,MATCH($D15,$B$22:$B$33,0)),"—"),IF($C15="Голова",IFERROR(INDEX($E$37:$E$48,MATCH($D15,$B$37:$B$48,0)),"—"),"—"))) | H15: =IF($D15="","",IF($C15="Тело",IFERROR(INDEX($F$22:$F$33,MATCH($D15,$B$22:$B$33,0)),"—"),IF($C15="Голова",IFERROR(INDEX($F$37:$F$48,MATCH($D15,$B$37:$B$48,0)),"—"),"—"))) | I15: Нет
B16: 9 | C16: Тело | E16: =IF($D16="","",IF($C16="Тело",IFERROR(INDEX($C$22:$C$33,MATCH($D16,$B$22:$B$33,0)),"—"),IF($C16="Голова",IFERROR(INDEX($C$37:$C$48,MATCH($D16,$B$37:$B$48,0)),"—"),"—"))) | F16: =IF($D16="","",IF($C16="Тело",IFERROR(INDEX($D$22:$D$33,MATCH($D16,$B$22:$B$33,0)),"—"),IF($C16="Голова",IFERROR(INDEX($D$37:$D$48,MATCH($D16,$B$37:$B$48,0)),"—"),"—"))) | G16: =IF($D16="","",IF($C16="Тело",IFERROR(INDEX($E$22:$E$33,MATCH($D16,$B$22:$B$33,0)),"—"),IF($C16="Голова",IFERROR(INDEX($E$37:$E$48,MATCH($D16,$B$37:$B$48,0)),"—"),"—"))) | H16: =IF($D16="","",IF($C16="Тело",IFERROR(INDEX($F$22:$F$33,MATCH($D16,$B$22:$B$33,0)),"—"),IF($C16="Голова",IFERROR(INDEX($F$37:$F$48,MATCH($D16,$B$37:$B$48,0)),"—"),"—"))) | I16: Нет
B17: 10 | C17: Тело | E17: =IF($D17="","",IF($C17="Тело",IFERROR(INDEX($C$22:$C$33,MATCH($D17,$B$22:$B$33,0)),"—"),IF($C17="Голова",IFERROR(INDEX($C$37:$C$48,MATCH($D17,$B$37:$B$48,0)),"—"),"—"))) | F17: =IF($D17="","",IF($C17="Тело",IFERROR(INDEX($D$22:$D$33,MATCH($D17,$B$22:$B$33,0)),"—"),IF($C17="Голова",IFERROR(INDEX($D$37:$D$48,MATCH($D17,$B$37:$B$48,0)),"—"),"—"))) | G17: =IF($D17="","",IF($C17="Тело",IFERROR(INDEX($E$22:$E$33,MATCH($D17,$B$22:$B$33,0)),"—"),IF($C17="Голова",IFERROR(INDEX($E$37:$E$48,MATCH($D17,$B$37:$B$48,0)),"—"),"—"))) | H17: =IF($D17="","",IF($C17="Тело",IFERROR(INDEX($F$22:$F$33,MATCH($D17,$B$22:$B$33,0)),"—"),IF($C17="Голова",IFERROR(INDEX($F$37:$F$48,MATCH($D17,$B$37:$B$48,0)),"—"),"—"))) | I17: Нет
B18: Крит = два и более «6» на кубах урона ближней/дальней атаки: +5 урона напрямую в HP (SP не гасит). Без прицельного выстрела в голову — таблица тела. Если травма уже есть, перебрасывай, пока не выпадет новая. Quick Fix лечит эффект, но не саму травму.
B20: ТАБЛИЦА 2D6 · КРИТИЧЕСКИЕ ТРАВМЫ ТЕЛА (СПРАВОЧНИК ДЛЯ СТОЛА)
B21: 2D6 | C21: ТРАВМА | D21: ЭФФЕКТ · БЫСТРЫЙ ФИКС · ЛЕЧЕНИЕ | G21: ДЛЯ СТОЛА
B22: 2 | C22: Dismembered Arm (Отрубленная рука) | D22: Руки больше нет. Вы роняете все предметы в её кисти. +1 к Base Death Save Penalty. · Quick Fix: — · Лечение: Surgery DV17 | G22: +5 урона в HP.
B23: 3 | C23: Dismembered Hand (Отрубленная кисть) | D23: Кисти больше нет. Вы роняете все предметы в ней. +1 к Base Death Save Penalty. · Quick Fix: — · Лечение: Surgery DV17 | G23: +5 урона в HP.
B24: 4 | C24: Collapsed Lung (Коллапс лёгкого) | D24: −2 MOVE (мин. 1). +1 к Base Death Save Penalty. · Quick Fix: Paramedic DV15 · Лечение: Surgery DV15 | G24: +5 урона в HP.
B25: 5 | C25: Broken Ribs (Перелом рёбер) | D25: При перемещении более 4 м на ногах — снова бонусный урон крит. травмы в конце хода. · Quick Fix: Paramedic DV13 · Лечение: Paramedic DV15 или Surgery DV13 | G25: +5 урона в HP.
B26: 6 | C26: Broken Arm (Перелом руки) | D26: Сломанная рука не используется. Вы роняете всё из её кисти. · Quick Fix: Paramedic DV13 · Лечение: Paramedic DV15 или Surgery DV13 | G26: +5 урона в HP.
B27: 7 | C27: Foreign Object (Инородное тело) | D27: При перемещении более 4 м на ногах — снова бонусный урон крит. травмы в конце хода. · Quick Fix: First Aid или Paramedic DV13 · Лечение: Quick Fix убирает навсегда | G27: +5 урона в HP.
B28: 8 | C28: Broken Leg (Перелом ноги) | D28: −4 MOVE (мин. 1). · Quick Fix: Paramedic DV13 · Лечение: Paramedic DV15 или Surgery DV13 | G28: +5 урона в HP.
B29: 9 | C29: Torn Muscle (Разрыв мышц) | D29: −2 к атакам ближнего боя. · Quick Fix: First Aid или Paramedic DV13 · Лечение: Quick Fix убирает навсегда | G29: +5 урона в HP.
B30: 10 | C30: Spinal Injury (Травма позвоночника) | D30: В следующем ходу нельзя использовать Действие (можно Перемещаться). +1 к Base Death Save Penalty. · Quick Fix: Paramedic DV15 · Лечение: Surgery DV15 | G30: +5 урона в HP.
B31: 11 | C31: Crushed Fingers (Раздавленные пальцы) | D31: −4 ко всем Действиям этой кистью. · Quick Fix: Paramedic DV13 · Лечение: Surgery DV15 | G31: +5 урона в HP.
B32: 12 | C32: Dismembered Leg (Отрубленная нога) | D32: −6 MOVE (мин. 1). Нельзя уклоняться. +1 к Base Death Save Penalty. · Quick Fix: — · Лечение: Surgery DV17 | G32: +5 урона в HP.
B35: ТАБЛИЦА 2D6 · КРИТИЧЕСКИЕ ТРАВМЫ ГОЛОВЫ (ТОЛЬКО ПРИЦЕЛЬНЫЙ В ГОЛОВУ)
B36: 2D6 | C36: ТРАВМА | D36: ЭФФЕКТ · БЫСТРЫЙ ФИКС · ЛЕЧЕНИЕ | G36: ДЛЯ СТОЛА
B37: 2 | C37: Lost Eye (Потеря глаза) | D37: Глаза больше нет. −4 к атакам дальнего боя и зрительным Perception. +1 к Base Death Save Penalty. · Quick Fix: — · Лечение: Surgery DV17 | G37: +5 урона в HP.
B38: 3 | C38: Brain Injury (Черепно-мозговая травма) | D38: −2 ко всем Действиям. +1 к Base Death Save Penalty. · Quick Fix: — · Лечение: Surgery DV17 | G38: +5 урона в HP.
B39: 4 | C39: Damaged Eye (Повреждение глаза) | D39: −2 к атакам дальнего боя и зрительным Perception. · Quick Fix: Paramedic DV15 · Лечение: Surgery DV13 | G39: +5 урона в HP.
B40: 5 | C40: Concussion (Сотрясение) | D40: −2 ко всем Действиям. · Quick Fix: First Aid или Paramedic DV13 · Лечение: Quick Fix убирает навсегда | G40: +5 урона в HP.
B41: 6 | C41: Broken Jaw (Перелом челюсти) | D41: −4 ко всем Действиям, связанным с речью. · Quick Fix: Paramedic DV13 · Лечение: Paramedic или Surgery DV13 | G41: +5 урона в HP.
B42: 7 | C42: Foreign Object (Инородное тело) | D42: При перемещении более 4 м на ногах — снова бонусный урон крит. травмы в конце хода. · Quick Fix: First Aid или Paramedic DV13 · Лечение: Quick Fix убирает навсегда | G42: +5 урона в HP.
B43: 8 | C43: Whiplash (Хлыстовая травма) | D43: +1 к Base Death Save Penalty. · Quick Fix: Paramedic DV13 · Лечение: Paramedic или Surgery DV13 | G43: +5 урона в HP.
B44: 9 | C44: Cracked Skull (Треснувший череп) | D44: Прицельные атаки в голову дают модификатор ×3, а не ×2. +1 к Base Death Save Penalty. · Quick Fix: Paramedic DV15 · Лечение: Paramedic или Surgery DV15 | G44: +5 урона в HP.
B45: 10 | C45: Damaged Ear (Повреждение уха) | D45: При перемещении более 4 м — нельзя перемещаться в следующем ходу. −2 к слуховым Perception. · Quick Fix: Paramedic DV13 · Лечение: Surgery DV13 | G45: +5 урона в HP.
B46: 11 | C46: Crushed Windpipe (Раздавленная трахея) | D46: Нельзя говорить. +1 к Base Death Save Penalty. · Quick Fix: — · Лечение: Surgery DV15 | G46: +5 урона в HP.
B47: 12 | C47: Lost Ear (Потеря уха) | D47: Уха больше нет. При перемещении более 4 м — нельзя перемещаться в следующем ходу. −4 к слуховым Perception. +1 к Base Death Save Penalty. · Quick Fix: — · Лечение: Surgery DV17 | G47: +5 урона в HP.
B50: Ⅱ · СМЕРТЬ, СТАБИЛИЗАЦИЯ, ЗАВИСИМОСТИ
B51: СТАБИЛИЗАЦИЯ: DV | D51: Лёгкое DV10 · Серьёзное DV13 · Смертельное DV15 (успех → 1 HP и минута без сознания)
B52: СПАСБРОСОК СМЕРТИ | D52: В начале каждого хода при HP < 1: 1d10 ≤ BODY − штраф. Выпало 10 = провал = смерть.
B53: STIM / SPEEDHEAL | D53: Stim снимает штрафы «серьёзно ранен» на час. Speedheal лечит BODY + WILL HP (1 раз в день).
B54: ЗАВИСИМОСТИ (ВВОД) | D54: Нет. Пьёт, но не запойно.
B55: АБСТИНЕНЦИЯ И ТРИГГЕРЫ (ВВОД) | D55: Триггер: сирена и запах горелого пластика — тот переулок, где погиб напарник.
B56: СНЯТИЕ ЗАВИСИМОСТИ | D56: Терапия: 1 неделя, 1 000 €$ + материалы 500 €$, Medical Tech DV15 (лист 04).
B58: Ⅲ · РЕПУТАЦИЯ И УЛУЧШЕНИЯ (IP)
B59: ПОКАЗАТЕЛЬ | D59: ЗНАЧЕНИЕ | E59: ПРАВИЛО
B60: РЕПУТАЦИЯ | D60: 0 | E60: Растёт за громкие дела: реакция улиц, кто берёт твой звонок, кто хочет тебя снять.
B61: IP ЗАРАБОТАНО | D61: 0 | E61: GM выдаёт после сессии: 10–50 за стиль игры, больше — за выполненное дело (лист СПРАВКА).
B62: IP ПОТРАЧЕНО (АВТО) | D62: =SUM($F$67:$F$76) | E62: Сумма по таблице Ⅳ ниже.
B63: IP СВОБОДНО | D63: =$D$61-$D$62 | E63: Заработано минус потрачено.
B65: Ⅳ · ЧТО УЛУЧШИЛИ ЗА IP · СТОИМОСТЬ СЧИТАЕТСЯ АВТОМАТИЧЕСКИ
B66: ДАТА | C66: ЧТО УЛУЧШИЛИ | D66: ТИП | E66: НОВЫЙ УР. | F66: СТОИМОСТЬ IP | G66: ЗАМЕТКА
C67: Evasion → 5 | D67: НАВЫК | F67: =IF(OR($E67="",$D67=""),"",IF($D67="РОЛЬ",60*$E67,IF($D67="НАВЫК ×2",40*$E67,IF($D67="НАВЫК",20*$E67,"")))) | G67: план · 100 IP · первый приоритет: уклонение 15 + d10
C68: Evasion → 6 | D68: НАВЫК | F68: =IF(OR($E68="",$D68=""),"",IF($D68="РОЛЬ",60*$E68,IF($D68="НАВЫК ×2",40*$E68,IF($D68="НАВЫК",20*$E68,"")))) | G68: план · 120 IP · уклонение 16 + d10
C69: Martial Arts (Thamoc) → 6 | D69: НАВЫК | F69: =IF(OR($E69="",$D69=""),"",IF($D69="РОЛЬ",60*$E69,IF($D69="НАВЫК ×2",40*$E69,IF($D69="НАВЫК",20*$E69,"")))) | G69: план · 240 IP (×2) — приёмы формы почти без провалов
C70: Brawling → 6 | D70: НАВЫК | F70: =IF(OR($E70="",$D70=""),"",IF($D70="РОЛЬ",60*$E70,IF($D70="НАВЫК ×2",40*$E70,IF($D70="НАВЫК",20*$E70,"")))) | G70: план · 120 IP
C71: Shoulder Arms → 6 | D71: НАВЫК | F71: =IF(OR($E71="",$D71=""),"",IF($D71="РОЛЬ",60*$E71,IF($D71="НАВЫК ×2",40*$E71,IF($D71="НАВЫК",20*$E71,"")))) | G71: план · 120 IP
C72: Tactics → 2 | D72: НАВЫК | F72: =IF(OR($E72="",$D72=""),"",IF($D72="РОЛЬ",60*$E72,IF($D72="НАВЫК ×2",40*$E72,IF($D72="НАВЫК",20*$E72,"")))) | G72: план · 20 + 40 = 60 IP (два шага)
C73: Human Perception → 3 | D73: НАВЫК | F73: =IF(OR($E73="",$D73=""),"",IF($D73="РОЛЬ",60*$E73,IF($D73="НАВЫК ×2",40*$E73,IF($D73="НАВЫК",20*$E73,"")))) | G73: план · 60 IP
C74: First Aid → 3 | D74: НАВЫК | F74: =IF(OR($E74="",$D74=""),"",IF($D74="РОЛЬ",60*$E74,IF($D74="НАВЫК ×2",40*$E74,IF($D74="НАВЫК",20*$E74,"")))) | G74: план · 60 IP
C75: РАНГ РОЛИ Lawman → 5 | D75: РОЛЬ | F75: =IF(OR($E75="",$D75=""),"",IF($D75="РОЛЬ",60*$E75,IF($D75="НАВЫК ×2",40*$E75,IF($D75="НАВЫК",20*$E75,"")))) | G75: план · 300 IP — тир подкрепления 5–7 (департамент шерифа)
D76: НАВЫК | F76: =IF(OR($E76="",$D76=""),"",IF($D76="РОЛЬ",60*$E76,IF($D76="НАВЫК ×2",40*$E76,IF($D76="НАВЫК",20*$E76,""))))
B77: ИТОГО ПОТРАЧЕНО IP | F77: =SUM($F$67:$F$76) | G77: 20 × уровень — обычный навык · 40 × уровень — навык (×2) · 60 × ранг — ролевая способность. Уровни не перескакивают.
B79: Ⅴ · ЛОГ ДЕЛ (СЕССИИ) · ЧТО БЫЛО И ЗА ЧТО ЗАПЛАТИЛИ
B80: ДАТА | C80: ДЕЛО / СЕССИЯ | E80: РОЛЬ В ДЕЛЕ | F80: НАГРАДА €$ | G80: IP | H80: ИТОГ / ЗАМЕТКА
B101: ИТОГО ЗА КАМПАНИЮ | F101: =SUM($F$81:$F$100) | G101: =SUM($G$81:$G$100) | H101: Сверь IP с полем «IP заработано» выше.
B103: Ⅵ · ДОЛГИ, ЦЕЛИ И КРЮЧКИ
B104: ДОЛГИ И ОБЯЗАТЕЛЬСТВА (КОМУ, ЧТО, КОГДА) | D104: Наличных на старте нет — вышел из управления с нулём, всё до последнего евродоллара ушло в снаряжение. Жильё — контейнер в боевых зонах: жильё 1 000 €$ + Kibble 100 €$/мес = 1 100 €$ к 1-му числу каждого месяца (первый месяц покрыт). Подписок нет: Trauma Team Silver (500 €$/мес) не по карману — копит на разовый вызов с первых дел. Долгов нет, кредитная история убита вместе с карьерой.
B106: ЖИЗНЕННЫЕ ЦЕЛИ / КРЮЧКИ ДЛЯ GM | D106: Закрыть дело о корпоративном складе и вернуть себе имя. Найти, кому в управлении это было выгодно.
B108: ТАБУ И ТРИГГЕРЫ (ОТ ИГРОКА) | D108: Не трогает детей. Не работает против копов — даже против тех, кто его выкинул.
B111: Источники: Cyberpunk RED Corebook (стр. 79, 129, 186–190, 223, 229, 408), CEMK Rule Book (2070-е: стр. 26–30), гайд «Spes Desperata». Лист — домашний инструмент кампании.

Sheet КАТАЛОГ
A1: КАТАЛОГ ▚ 1092 ПОЗИЦИЙ ИЗ DATA POOL (CYBERPUNK RED / CEMK / BLACK CHROME / INTERFACE RED) ▚ НЕ ПРАВЬ ЭТОТ ЛИСТ — НА НЕГО ССЫЛАЮТСЯ ФОРМУЛЫ ОСТАЛЬНЫХ
A2: Power Rebuild | B2: Апгрейды оружия | F2: ROF | G2: МАГ. | H2: SP | I2: HP | J2: 0 | K2: 0 | L2: 0 | M2: 0 | R2: 1000 | S2: CEMK 30 | T2: The weapon is reinforced to handle extreme strain, enabling increased precision. Rebuild. Requires 2 attachment slots. Transforms the weapon into a Power Weapon. Whenever a Power Weapon causes a Critical Injury (see CEMK
A3: Smart Rebuild | B3: Апгрейды оружия | J3: 0 | K3: 0 | L3: 0 | M3: 0 | R3: 1000 | S3: CEMK 31 | T3: The weapon’s internals are stripped down and rebuilt, incorporating advances in smart targeting technology needed to make use of improved gyrojet bullets. Rebuild. Requires 2 attachment slots. Transforms the weapon into
A4: Tech Rebuild | B4: Апгрейды оружия | J4: 0 | K4: 0 | L4: 0 | M4: 0 | R4: 1000 | S4: CEMK 31 | T4: The weapon is reworked from the ground up to be fitted with electromagnetic launch modules. Rebuild. Requires 2 attachment slots. Transforms the weapon into a Tech Weapon. Weapon is equipped with a scope that can see sim
A5: Bayonet | B5: Апгрейды оружия | J5: 0 | K5: 0 | L5: 0 | M5: 0 | R5: 100 | S5: CP:R 343 | T5: When wielded, this weapon can also be used as a Light Melee Weapon. While this is attached to a weapon, it cannot be concealed under clothing.
A6: Drum Magazine | B6: Апгрейды оружия | J6: 0 | K6: 0 | L6: 0 | M6: 0 | R6: 500 | S6: CP:R 343 | T6: The weapon holds a maximum number of shots equal to its Drum entry on the Clip Chart below. Only one clip can be attached to a weapon at a time. While this is attached to a weapon, it cannot be concealed under clothing.
A7: Extended Magazine | B7: Апгрейды оружия | J7: 0 | K7: 0 | L7: 0 | M7: 0 | R7: 100 | S7: CP:R 343 | T7: The weapon holds a maximum number of shots equal to its Extended entry on the Clip Chart chart below. Only one clip can be attached to a weapon at a time. While this is attached to a weapon, it cannot be concealed under
A8: Grenade Launcher Underbarrel | B8: Апгрейды оружия | J8: 0 | K8: 0 | L8: 0 | M8: 0 | R8: 500 | S8: CP:R 343 | T8: When wielded in two hands, the weapon can also be used as a Grenade Launcher, with only 1 grenade in its magazine. While this is attached to a weapon, it cannot be concealed under clothing. Requires 2 Attachment Slots.
A9: Infrared Nightvision Scope | B9: Апгрейды оружия | J9: 0 | K9: 0 | L9: 0 | M9: 0 | R9: 500 | S9: CP:R 343 | T9: Reduces penalties imposed on your firing at a target obscured to you by darkness, smoke, fog, etc. to 0. Looking through the scope, you can distinguish hot meat from cold metal, but not more specifically than that. You c
A10: Shotgun Underbarrel | B10: Апгрейды оружия | J10: 0 | K10: 0 | L10: 0 | M10: 0 | R10: 500 | S10: CP:R 343 | T10: When wielded in two hands, the weapon can also be used as a Shotgun, with only 2 shots in its magazine. While this is attached to a weapon, it cannot be concealed under clothing. Requires 2 Attachment Slots.
A11: Smartgun Link | B11: Апгрейды оружия | J11: 0 | K11: 0 | L11: 0 | M11: 0 | R11: 500 | S11: CP:R 343 | T11: Installing or uninstalling a Smartgun Link takes an hour. A weapon is a Smartgun only when it has a Smartgun Link attached to it. Special Cyberware is required to take advantage of a Smartgun. A Smartgun Link must be con
A12: Sniping Scope | B12: Апгрейды оружия | J12: 0 | K12: 0 | L12: 0 | M12: 0 | R12: 100 | S12: CP:R 343 | T12: Looking through the scope, user can see detail up to 800m/yds away. When attacking a target 51m/yards or further away with either a weapon's single shot firing mode or an Aimed Shot, you can add a +1 to your Check. Does
A13: Airhypo Bayonet | B13: Апгрейды оружия | J13: 0 | K13: 0 | L13: 0 | M13: 0 | R13: 100 | S13: DL:TT 14 · IR5 48 | T13: A drug-based twist on the standard bayonet. You won’t break flesh with this attachment, but you can pump someone full of whatever chemical you load into the reservoir. An easy-to-use drug distribution platform mounted on
A14: Grapple Gun Underbarrel | B14: Апгрейды оружия | J14: 0 | K14: 0 | L14: 0 | M14: 0 | R14: 100 | S14: DL:TT 14 · IR5 48 | T14: When someone shoves you off a building, you don’t always have time to drop your rifle and grab your grapple gun. Save your life by combining the two! The weapon can be used as a Grapple Gun (see CP:R, page 353). However,
... A65: Trailer (Bicycle) | B65: Апгрейды транспорта | J65: 0 | K65: 0 | L65: 0 | M65: 0 | R65: 50 | S65: DLC:Wheels 5 · IR3 79 | T65: A small trailer you can hook onto your bicycle with a cargo area measuring 5 feet (1.5 meters) long and 1.5 feet (.46 meters) wide. It can be attached or detached from the bicycle with an Action. If the bicycle has the F
A66: Bulletproof Shield | B66: Броня | H66: 0 | I66: 10 | J66: 0 | K66: 0 | L66: 0 | M66: 0 | R66: 100 | S66: CP:R 350 | T66: A transparent polycarbonate shield that can protect you in a firefight.
A67: Leathers | B67: Броня | H67: 4 | J67: 0 | K67: 0 | L67: 0 | M67: 0 | R67: 20 | S67: CP:R 350 | T67: Thin leather with reinforced pads at shoulders, hips, and gut. Favored by Nomads and other 'punks who ride bikes. This also includes all those road-warrior wannabes wearing open-butt chaps and random sports equipment.
A68: Kevlar® | B68: Броня | H68: 7 | J68: 0 | K68: 0 | L68: 0 | M68: 0 | R68: 50 | S68: CP:R 350 | T68: The favored protection for the past 90 years. To quote DuPont: Kevlar® is a heat-resistant, synthetic, lightweight fiber that delivers high tensile strength that brings improved protection and performance across a range
A69: Light Armorjack | B69: Броня | H69: 11 | J69: 0 | K69: 0 | L69: 0 | M69: 0 | R69: 100 | S69: CP:R 350 | T69: A combination of Kevlar® and plastic meshes inserted into the weave of the fabric. Armorjack provides superior protection, especially against high-velocity bullets.
A70: Bodyweight Suit | B70: Броня | H70: 11 | J70: 0 | K70: 0 | L70: 0 | M70: 0 | R70: 1000 | S70: CP:R 350 | T70: Skinsuit with impact absorbing, sintered armorgel layered in key body areas. Surprisingly, they are also breathable and quite comfortable. Besides giving you a measure of protection, a Bodyweight Suit also has a place to
A71: Medium Armorjack | B71: Броня | H71: 12 | J71: -2 | K71: -2 | L71: -2 | M71: 0 | R71: 100 | S71: CP:R 350 | T71: Heavier Armorjack, with solid plastic plating, reinforced with thicker Kevlar® mesh. Typical Street wear, this combines decent protection with a decent сost.
A72: Heavy Armorjack | B72: Броня | H72: 13 | J72: -2 | K72: -2 | L72: -2 | M72: 0 | R72: 500 | S72: CP:R 350 | T72: The thickest Armorjack, combining denser Kevlar® and a layered mix of plastic and mesh weaves. It stops all but the heaviest attacks, but costs a pretty eb.
A73: Flak | B73: Броня | H73: 15 | J73: -4 | K73: -4 | L73: -4 | M73: 0 | R73: 500 | S73: CP:R 350 | T73: This is the 21st century version of the time-honored flak vest and pants with metal plates designed to provide protection from high explosive weaponry, artillery, grenades, shotguns, and anti-personnel mines. Modern flak
A74: Metalgear® | B74: Броня | H74: 18 | J74: -4 | K74: -4 | L74: -4 | M74: 0 | R74: 5000 | S74: CP:R 350 | T74: You know how Evil Empire Storm Troopers just seem to stand there and take the hit? Metalgear® is the Dark Future equivalent of that type of armor: solid metal and plastic plates on a mesh body cover. Metalgear® will stop
A75: The Dirk Combat Jacket | B75: Броня | H75: 11 | J75: 0 | K75: 0 | L75: 0 | M75: 0 | R75: 500 | S75: BC 28 | T75: The Dirk is Light Armorjack Body Armor with the appearance of Leisurewear Fashion. Two standard-size clips of ammunition can be concealed in the jacket
A76: Shock Armor | B76: Броня | H76: 7 | J76: 0 | K76: 0 | L76: 0 | M76: 0 | R76: 500 | S76: BC 29 | T76: Gibson Battlegear Shock Armor is Kevlar® Body Armor. When you are the defender in a grapple, you can use an Action to send a pulse of electricity into the armor, forcing the attacker in the grapple to make a DV15 Resist
A77: Fire Brand Bunker Gear | B77: Броня | H77: 15 | J77: -4 | K77: -4 | L77: -4 | M77: 0 | R77: 1000 | S77: BC 29 | T77: Fire Brand Bunker Gear is Flak Armor. Unlike other armor, it isn’t bought in two pieces and must always be worn on both your body and head locations. When repaired, both pieces are repaired at the same time. When the arm
A78: Tactical Smart Armor | B78: Броня | H78: 12 | J78: -2 | K78: -2 | L78: -2 | M78: 0 | R78: 1000 | S78: BC 30 | T78: The Gibson Battlegear Tactical Smart Armor is Medium Armorjack Armor with built-in Smart Glasses. Unlike other armor, it isn’t bought in two pieces and must always be worn on both your body and head location. When repair
... A88: MechaMan Motorcycle Helmet | B88: Броня | H88: 15 | J88: -4 | K88: -4 | L88: -4 | M88: 0 | R88: 5000 | S88: BC 37 | T88: The MechaMan Motorcycle Helmet is Flak Head Armor with built-in Tech upgraded Smart Glasses, which come installed with Chyron and Low Light / Infrared / UV Cybereye options.
A89: SkidRow PackShield | B89: Броня | H89: 0 | I89: 10 | J89: 0 | K89: 0 | L89: 0 | M89: 0 | R89: 100 | S89: DL:12Gear 4 · IR4 68 | T89: The PackShield is a Bulletproof Shield (HP10) with the appearance of Businesswear. It will not provide protection while worn as a backpack and must still be equipped in a hand to be effective. When worn as a backpack it
A90: High-Density Bulletproof Shield | B90: Броня | H90: 0 | I90: 15 | J90: 0 | K90: 0 | L90: 0 | M90: 0 | R90: 200 | S90: DL:12RED 3 · IR5 99 | T90: A shield with 15 HP. It cannot be installed in a Popup Shield.
A91: Light Metalgear® | B91: Броня | H91: 16 | J91: -3 | K91: -3 | L91: -3 | M91: 0 | R91: 1000 | S91: DL:12RED 3 · IR5 99 · IR5 123 | T91: The ultimate in full combat protection has just evolved. Today’s battlefields are faster than those of yesterday. Our new lighter model provides the same all-over clamshell protection you expect from us in a more mobile
A92: Scavenged Armor | B92: Броня | H92: 11 | J92: 0 | K92: 0 | L92: 0 | M92: 0 | R92: 50 | S92: DL:BC+ 4 | T92: Scavenged Armor is body armor with SP11. Once ablated, its SP cannot be restored. At 0 SP, it falls off the wearer.
A93: Roller Derby Padding | B93: Броня | H93: 7 | J93: 0 | K93: 0 | L93: 0 | M93: 0 | R93: 50 | S93: DL:CtR 9 | T93: Uniform padding for roller derby as determined by regulations established by the Night City Wonderland League. Head and Body are purchased separately. Head or Body Armor with SP7. Always in a team’s specific colors.
A94: Hybrid Metalgear® | B94: Броня | H94: 17 | J94: -3 | K94: -4 | L94: -4 | M94: 0 | R94: 2552 | S94: IR5 123 | T94: The needs of the battlefield are unceasing, and demand the perfect blend of offense and defense. Our half-segmented model provides the same all-over clamshell protection you expect from Metalgear® with the knee and elbow
A95: Heavy Metalgear® | B95: Броня | H95: 19 | J95: -4 | K95: -5 | L95: -5 | M95: 0 | R95: 5000 | S95: IR5 123 | T95: The heat of some battlefields rival the fires of hell. Our maximum hardplate model provides maximum clamshell protection to survive the most intense firefights. Heavy Metalgear® is Metalgear® with an SP of 19 and an Armo
A96: Armor Piercing Grenade | B96: Гранаты и взрывчатка | E96: 1d10 | J96: 0 | K96: 0 | L96: 0 | M96: 0 | R96: 100 | S96: CP:R 345 | T96: DEX + Athletics + 1d10 vs Grenade Launcher DV When using this ammunition, you ablate armor by 2 instead of 1 whenever you would ablate armor.
A97: Biotoxin Grenade | B97: Гранаты и взрывчатка | E97: 1d10 | J97: 0 | K97: 0 | L97: 0 | M97: 0 | R97: 500 | S97: CP:R 345 | T97: DEX + Athletics + 1d10 vs Grenade Launcher DV When using this ammunition, you deal no damage with your attack. Anyone meat hit by your attack must instead attempt to beat a DV15 Resist Torture/Drugs Check. Anyone who fai
A98: EMP Grenade | B98: Гранаты и взрывчатка | E98: 1d10 | J98: 0 | K98: 0 | L98: 0 | M98: 0 | R98: 500 | S98: CP:R 345 | T98: DEX + Athletics + 1d10 vs Grenade Launcher DV When using this ammunition, you deal no damage with your attack. Anyone hit by your attack must instead attempt to beat a DV15 Cybertech Check. If they fail, the GM chooses 2
A99: Flashbang Grenade | B99: Гранаты и взрывчатка | E99: 1d10 | J99: 0 | K99: 0 | L99: 0 | M99: 0 | R99: 100 | S99: CP:R 346 | T99: DEX + Athletics + 1d10 vs Grenade Launcher DV When using this ammunition, you deal no damage with your attack. Anyone hit by your attack must instead attempt to beat a DV15 Resist Torture/Drugs Check. Anyone who fails su
A100: Incendiary Grenade | B100: Гранаты и взрывчатка | E100: 1d10 | J100: 0 | K100: 0 | L100: 0 | M100: 0 | R100: 100 | S100: CP:R 346 | T100: DEX + Athletics + 1d10 vs Grenade Launcher DV When using this ammunition, whenever you deal damage to a target through their armor, you ignite the target. Until your target spends an Action to put themselves out, they ta
A101: Poison Grenade | B101: Гранаты и взрывчатка | E101: 1d10 | J101: 0 | K101: 0 | L101: 0 | M101: 0 | R101: 100 | S101: CP:R 346 | T101: DEX + Athletics + 1d10 vs Grenade Launcher DV When using this ammunition, you deal no damage with your attack. Anyone meat hit by your attack must instead attempt to beat a DV13 Resist Torture/Drugs Check. Anyone who fai
A102: Sleep Grenade | B102: Гранаты и взрывчатка | E102: 1d10 | J102: 0 | K102: 0 | L102: 0 | M102: 0 | R102: 500 | S102: CP:R 346 | T102: DEX + Athletics + 1d10 vs Grenade Launcher DV When using this ammunition, you deal no damage with your attack. Anyone meat hit by your attack must instead attempt to beat a DV13 Resist Torture/Drugs Check. Anyone who fai
A103: Smoke Grenade | B103: Гранаты и взрывчатка | E103: 1d10 | J103: 0 | K103: 0 | L103: 0 | M103: 0 | R103: 50 | S103: CP:R 347 | T103: DEX + Athletics + 1d10 vs Grenade Launcher DV When using this ammunition, you deal no damage with your attack. Obscures a 10m/yd by 10m/yd area with smoke for a minute on impact. The typical penalty for trying to perform
A104: Teargas Grenade | B104: Гранаты и взрывчатка | E104: 1d10 | J104: 0 | K104: 0 | L104: 0 | M104: 0 | R104: 50 | S104: CP:R 347 | T104: DEX + Athletics + 1d10 vs Grenade Launcher DV When using this ammunition, you deal no damage with your attack. Anyone with meat eyes hit by your attack must instead attempt to beat a DV13 Resist Torture/Drugs Check. Anyo
A105: Arachnid Grenade | B105: Гранаты и взрывчатка | E105: 1d10 | J105: 0 | K105: 0 | L105: 0 | M105: 0 | R105: 100 | S105: BC 86 | T105: DEX + Athletics + 1d10 vs Grenade Launcher DV The Arachnid is a non-lethal net grenade designed by the big brains at Centurion Essentials. This spherical explosive is filled with a highly flexible and sticky solution. Th
A106: Shuriken Tornado Grenade | B106: Гранаты и взрывчатка | E106: 1d10 | J106: 0 | K106: 0 | L106: 0 | M106: 0 | R106: 100 | S106: BC 87 | T106: DEX + Athletics + 1d10 vs Grenade Launcher DV When Great Lakes Cutlery decided to get into the arms business, they did it with the Shuriken Tornado. This pineapple-style grenade is packed tightly with stacked shuriken an
A107: KTech Security Grenade | B107: Гранаты и взрывчатка | E107: 1d10 | J107: 0 | K107: 0 | L107: 0 | M107: 0 | R107: 100 | S107: BC 89 | T107: DEX + Athletics + 1d10 vs Grenade Launcher DV KTech Security Grenades are carried primarily by SovOil naval security units aboard ships where fire and explosions can be a significant concern. These pineapple-style grenad
... A113: KillChip 100 Micro-Bomb | B113: Гранаты и взрывчатка | E113: 6d6 | J113: 0 | K113: 0 | L113: 0 | M113: 0 | R113: 100 | S113: BC 88 | T113: The origin of the KillChip 100 has been a mystery since the first one exploded a head during the 4th Corporate War. The KillChip looks just like a standard memory chip, and reads like it too when plugged into an Agent. W
A114: Micro Hydrogen Combuster | B114: Гранаты и взрывчатка | J114: 0 | K114: 0 | L114: 0 | M114: 0 | R114: 500 | S114: BC 88 | T114: The Hydrosubsidium Micro Hydrogen Combustor is a small explosive device designed for deployment in full bottles. All units are rigged with a thirty-second timer that begins the countdown once the device is submerged enti
A115: OUTLet Explosive | B115: Гранаты и взрывчатка | J115: 0 | K115: 0 | L115: 0 | M115: 0 | R115: 100 | S115: BC 89 | T115: An OUTLet Explosive looks just like a standard outlet adapter, but it’s actually a small yet powerful micro-explosive. When plugged into a wall socket the OUTLet can be set to detonate via a remote trigger. The explosive
A116: TR-4 Detonator Fluid | B116: Гранаты и взрывчатка | J116: 0 | K116: 0 | L116: 0 | M116: 0 | R116: 500 | S116: BC 90 | T116: TR-4 Detonator Fluid is a reactionary liquid capable of transforming ordinary CHOOH2 into a super explosive devastating to vehicles. To use TR-4, all one must do is pour the fluid into a fuel tank, where it mixes with th
A117: C9 Charge | B117: Гранаты и взрывчатка | E117: 8d6 | J117: 0 | K117: 0 | L117: 0 | M117: 0 | R117: 250 | S117: IR5 121 | T117: Plastic explosive, handmade, and guaranteed to explode. This is an Explosive. A C9 Charge can be planted as an Action on any surface. Upon planting C9, the user attempts a DV17 Demolitions Skill Check. If they succeed, t
A118: C9 Kill Switch | B118: Гранаты и взрывчатка | J118: 0 | K118: 0 | L118: 0 | M118: 0 | R118: 100 | S118: IR5 122 | T118: When preventing equipment from falling into enemy hands, C9 is the only way to be sure. A C9 Kill Switch can be installed as part of a C9 Charge being planted by a user with authorized access on a Vehicle with a Security
A119: Mini C9 Charge | B119: Гранаты и взрывчатка | E119: 6d6 | J119: 0 | K119: 0 | L119: 0 | M119: 0 | R119: 60 | S119: IR5 122 | T119: A tightly packed plastic explosive charge, smaller, for jobs that require less explosive. This is an Explosive. A Mini C9 Charge can be planted as an Action on any surface. Upon planting C9, the user attempts a DV17 Demo
A120: Asia Pop Bottoms | B120: Мода | J120: 0 | K120: 0 | L120: 0 | M120: 0 | R120: 100 | S120: CP:R 356 | T120: Bright. Costume-like. Youthful.
A121: Asia Pop Top | B121: Мода | J121: 0 | K121: 0 | L121: 0 | M121: 0 | R121: 20 | S121: CP:R 356 | T121: Bright. Costume-like. Youthful.
A122: Asia Pop Jacket | B122: Мода | J122: 0 | K122: 0 | L122: 0 | M122: 0 | R122: 100 | S122: CP:R 356 | T122: Bright. Costume-like. Youthful.
A123: Asia Pop Footwear | B123: Мода | J123: 0 | K123: 0 | L123: 0 | M123: 0 | R123: 100 | S123: CP:R 356 | T123: Bright. Costume-like. Youthful.
A124: Asia Pop Jewelry | B124: Мода | J124: 0 | K124: 0 | L124: 0 | M124: 0 | R124: 100 | S124: CP:R 356 | T124: Bright. Costume-like. Youthful.
A125: Asia Pop Mirrorshades | B125: Мода | J125: 0 | K125: 0 | L125: 0 | M125: 0 | R125: 100 | S125: CP:R 356 | T125: Bright. Costume-like. Youthful.
A126: Asia Pop Glasses | B126: Мода | J126: 0 | K126: 0 | L126: 0 | M126: 0 | R126: 100 | S126: CP:R 356 | T126: Bright. Costume-like. Youthful.
A127: Asia Pop Contact Lenses | B127: Мода | J127: 0 | K127: 0 | L127: 0 | M127: 0 | R127: 100 | S127: CP:R 356 | T127: Bright. Costume-like. Youthful.
A128: Asia Pop Hats | B128: Мода | J128: 0 | K128: 0 | L128: 0 | M128: 0 | R128: 100 | S128: CP:R 356 | T128: Bright. Costume-like. Youthful.
A129: Bag Lady Chic Bottoms | B129: Мода | J129: 0 | K129: 0 | L129: 0 | M129: 0 | R129: 20 | S129: CP:R 356 | T129: Homeless. Ragged. Vagrant.
A130: Bag Lady Chic Top | B130: Мода | J130: 0 | K130: 0 | L130: 0 | M130: 0 | R130: 10 | S130: CP:R 356 | T130: Homeless. Ragged. Vagrant.
A131: Bag Lady Chic Jacket | B131: Мода | J131: 0 | K131: 0 | L131: 0 | M131: 0 | R131: 20 | S131: CP:R 356 | T131: Homeless. Ragged. Vagrant.
... A302: Aerozep | B302: Транспорт | J302: 0 | K302: 0 | L302: 0 | M302: 0 | R302: 30000 | S302: CP:R 191 | T302: Modern cargo blimps that range wildly in size depending on their function. Aerozeps have customized rooms. 50,000eb per room below deck (minimum two rooms).
A303: SH-45 Patroller | B303: Транспорт | I303: 15 | J303: 0 | K303: 0 | L303: 0 | M303: 0 | R303: 16000 | S303: BC 58 | T303: The Dayton SH-45 Patroller is a serious upgrade to the old Dayton SH-35. The most striking change was replacing the open cockpit of the SH-35 with an enclosed one just large enough for the pilot. All the essential inform
A304: SH-45 Patroller Law | B304: Транспорт | I304: 30 | J304: 0 | K304: 0 | L304: 0 | M304: 0 | R304: 21000 | S304: BC 58 | T304: The Patroller Law is a Gyrocopter with only one seat, two Bulletproof Glass Upgrades, and an Onboard Machine Gun. It is incompatible with the Seating Upgrade.
A305: Dayton TDT 004 | B305: Транспорт | J305: 0 | K305: 0 | L305: 0 | M305: 0 | R305: 43000 | S305: BC 59 | T305: The TDT’s design is a grand step forward in the world of troop transport at a price that notably undercuts Militech and other military vendors. At its size, it is unrivaled in speed and durability. Its sleek frame is aer
A306: Tanson Bellhop | B306: Транспорт | J306: 0 | K306: 0 | L306: 0 | M306: 0 | R306: 16000 | S306: BC 60 | T306: Laugh all you want but K-pop performers have made the Tanson Bellhop the trendiest transport copter of 2045. Folded down, the Bellhop can be wheeled around like a large piece of luggage. When activated, the case opens in
A307: Zetatech AeroVox | B307: Транспорт | J307: 0 | K307: 0 | L307: 0 | M307: 0 | R307: 51000 | S307: BC 61 | T307: The Zetatech AeroVox is an economy-class aerodyne popular with up-and-coming corporate types with just enough cash to afford a full-size aerodyne and a bland taste for something standard and dependable. Since entering th
A308: Zetatech AeroCop | B308: Транспорт | H308: 13 | I308: 30 | J308: 0 | K308: 0 | L308: 0 | M308: 0 | R308: 58000 | S308: BC 61 | T308: The AeroCop is an AV4 Multipurpose Aerodyne with a Heavy Chassis, Armored Chassis, two Bulletproof Glass Upgrades, and an Onboard Machine Gun.
A309: Zetatech Destination | B309: Транспорт | J309: 0 | K309: 0 | L309: 0 | M309: 0 | R309: 40000 | S309: BC 62 | T309: The Zetatech Destination is a standard compact aerodyne for the modern age. Widely considered affordable and reliable for an a vehicle in its class, Zetatech brags they’ve sold more than 2 million units globally. While n
A310: Zetatech Herakles | B310: Транспорт | H310: 13 | I310: 15 | J310: 0 | K310: 0 | L310: 0 | M310: 0 | R310: 63000 | S310: BC 63 · DGD 112 | T310: The Zetatech Herakles is a workhose of an aerodyne designed specifically for the defense market. Perfect for both troop transport and crowd control, the Herakles has proven popular with private security providers and C-S
A311: AmeriCar EconoCompact | B311: Транспорт | J311: 0 | K311: 0 | L311: 0 | M311: 0 | R311: 20000 | S311: BC 64 | T311: Rising from the Corporate ashes of New American Motors, the EconoCompact, AmeriCar’s flagship product, is a highly affordable, no-frills, reliable automobile. It appeals to those who can’t afford a typical compact but st
A312: AmeriCar Family Star Van | B312: Транспорт | J312: 0 | K312: 0 | L312: 0 | M312: 0 | R312: 31000 | S312: BC 65 | T312: When it comes to family comfort and transportation, look no further than the AmeriCar Family Star. Following AmeriCar’s plan for affordable, modern transport, the Family Star makes waves with its throwback design and com
A313: Diego Motors Chupacabra | B313: Транспорт | J313: 0 | K313: 0 | L313: 0 | M313: 0 | R313: 37000 | S313: BC 66 · DGD 139 | T313: Diego Motors knows how to make no-nonsense transportation, and the Chupacabra is the perfect example. The bastard child of an off-roader and a military vehicle that dreamed of being a muscle car when it grew up, the Chup
A314: Diego Motors Range Trike | B314: Транспорт | H314: 13 | J314: 0 | K314: 0 | L314: 0 | M314: 0 | R314: 31000 | S314: BC 67 | T314: The Range Trike is the product of Diego Motors, a company run by a distant offshoot of the Jode Family operating primarily in South America. These Nomads have a natural talent for making custom trikes. Each piece is hand
A315: The Grundy | B315: Транспорт | H315: 13 | J315: 0 | K315: 0 | L315: 0 | M315: 0 | R315: 41000 | S315: BC 68 | T315: After running out of space in their junkyards, Grundy Salvage International decided to diversify their business. They started by pulling all the armor plating they had and stacking it in one part of their yard. They then
A316: The Harvey 100 | B316: Транспорт | J316: 0 | K316: 0 | L316: 0 | M316: 0 | R316: 20000 | S316: BC 69 | T316: The Harvey 100 was marketed as the “motorcycle for everyone” but became better known for its number of cross-used parts from older motorcycles, with one reviewer dubbing it the “Frankenbike”. But it was this feature of i
A317: The Harriet 100 | B317: Транспорт | J317: 0 | K317: 0 | L317: 0 | M317: 0 | R317: 21000 | S317: BC 69 | T317: The Harriet 100 is a Roadbike with a Smuggling Upgrade.
A318: The Harvey Merc | B318: Транспорт | J318: 0 | K318: 0 | L318: 0 | M318: 0 | R318: 30000 | S318: BC 69 | T318: The Harvey Merc is a Roadbike with an Onboard Machine Gun and Onboard Rocket Pod.
A319: Highway Master Artemis | B319: Транспорт | H319: 13 | I319: 30 | J319: 0 | K319: 0 | L319: 0 | M319: 0 | R319: 60000 | S319: BC 70 | T319: The Highway Master Artemis from Brennan is a luxurious street chariot for the new age. The bike drives like a low-rider, with a sleek canopy sliding over the driver to create a self-contained environment — bulletproof, o
A320: Kaukaz Volkhov | B320: Транспорт | H320: 13 | J320: 0 | K320: 0 | L320: 0 | M320: 0 | R320: 41000 | S320: BC 71 | T320: The Kaukaz Volkhov is a multipurpose armored pickup truck offering plenty of cargo space, a hauling capacity of 8 tons, and a reinforced frame and chassis. The Volkhov is most often associated with SovOil security forces
A321: Makigai Ebi | B321: Транспорт | J321: 0 | K321: 0 | L321: 0 | M321: 0 | R321: 23000 | S321: BC 72 | T321: The Makigai Ebi is a reliable mini-hatchback built for the city. It has great fuel efficiency, decent cargo space, comfortable seating, and better-than-average environmental controls. What more could you want? Most Ebi a
A322: Militech Gorgon Security Van | B322: Транспорт | H322: 13 | I322: 15 | J322: 0 | K322: 0 | L322: 0 | M322: 0 | R322: 37000 | S322: BC 73 | T322: While Militech focuses most of its manufacturing might on weapons technologies, it still produces ground vehicles such as the Gorgon. A van designed for security teams and mercs, the Gorgon is tough, with a chassis capab
A323: Zacatzontli Pickup Truck | B323: Транспорт | J323: 0 | K323: 0 | L323: 0 | M323: 0 | R323: 27000 | S323: BC 74 | T323: Ortiz Auto’s standout offering is the Zacatzontli. During the last few years the truck made its way into the North American market, though it has long been a best seller in Central America. The Zac’s chunky tires, reinfo
A324: The Paladin 500 | B324: Транспорт | H324: 13 | J324: 0 | K324: 0 | L324: 0 | M324: 0 | R324: 59000 | S324: BC 75 | T324: The Paladin 500 is Turbo Neon Motors’ premiere offering. Starting with old Max Interceptor frames bought wholesale, the garage’s engineers reworked the transmission and engine, polishing its performance to a mirrored she
A325: Quadra Thunder-X | B325: Транспорт | H325: 13 | I325: 15 | J325: 0 | K325: 0 | L325: 0 | M325: 0 | R325: 57000 | S325: BC 76 | T325: During a short-lived classic car renaissance at the start of the 4th Corporate War, Quadra released the Thunder-X, their modern homage to the vintage muscle cars of the mid-20th century. Wherever possible to do so invisi
A326: Street King Combat Vehicle | B326: Транспорт | H326: 13 | I326: 30 | J326: 0 | K326: 0 | L326: 0 | M326: 0 | R326: 63000 | S326: BC 77 | T326: Although less popular than the Paladin 500, the Street King is still an impressive beast of a vehicle. At its heart, the Street King is a reimagines the classic military transport that saw heavy use during the 4th Corpor
A327: Tanson JetBoy Hoverboard | B327: Транспорт | J327: 0 | K327: 0 | L327: 0 | M327: 0 | R327: 1000 | S327: BC 78 | T327: Nothing says speed and style like the JetBoy. First released a decade ago, the JetBoy quickly became popular among young gangers. Who needs an expensive motorcycle when a hoverboard is far cheaper and — frankly — cooler?
A328: TetraCorp America MegaHauler | B328: Транспорт | H328: 13 | I328: 30 | J328: 0 | K328: 0 | L328: 0 | M328: 0 | R328: 143000 | S328: BC 79 | T328: This monster cargo transport can be found on almost every major land route as the crown jewel in a well-protected caravan. The MegaHauler can manage up to three cargo containers at once using a detachable secondary engin
A329: TetraCorp America Corporate Bus | B329: Транспорт | H329: 13 | I329: 15 | J329: 0 | K329: 0 | L329: 0 | M329: 0 | R329: 50000 | S329: BC 80 | T329: The TetraCorp America Badger Corporate Bus is a high-end shuttle designed with the corporate world in mind. Constructed from durable polymers, the Badger is a secure vehicle perfect for protecting Corporate assets. The b
A330: Yang’s Wheels Rickshaw | B330: Транспорт | J330: 0 | K330: 0 | L330: 0 | M330: 0 | R330: 21000 | S330: BC 81 | T330: The Yang’s Wheels Rickshaw is the brainchild of Gabriel Yang, the reigning bicycle monarch out of Night City. After seeing a need in the market for cheap, fast, and agile hired transport, he purchased hundreds of wrecked
A331: Zonda Molly 1K | B331: Транспорт | J331: 0 | K331: 0 | L331: 0 | M331: 0 | R331: 15000 | S331: BC 82 | T331: Despite the recent release of the Zonda Molly 2K in Japan, the original 1K model remains the workhorse of the off-road market. Biotechnica uses Mollys to haul researchers through their Reference Forests. Petrochem uses M
A332: Zonda Parallax CybercycleTM | B332: Транспорт | H332: 13 | J332: 0 | K332: 0 | L332: 0 | M332: 0 | R332: 110000 | S332: BC 83 | T332: The Zonda Parallax Cybercycle™ is the high-end evolution of motorcycle mania. Considered the bike for elite riders, the Parallax boasts fantastic speed and control, with durability surpassing standard models. Thanks to i
A333: Zonda Sliver | B333: Транспорт | I333: 15 | J333: 0 | K333: 0 | L333: 0 | M333: 0 | R333: 27000 | S333: BC 84 | T333: The Sliver by Zonda comes loaded with gadgets and these extra bells and whistles make it worth every Eurobuck. The most beloved feature of the bike is the holographic display on the windshield, a touchscreen collecting e
A334: Sawtooth | B334: Транспорт | H334: 13 | I334: 15 | J334: 0 | K334: 0 | L334: 0 | M334: 0 | R334: 113000 | S334: CPCW 1 | T334: The Sawtooth is fast, brutal, and crewed by absolute maniacs. Built on the frame of a small luxury coupe, it’s exceptionally nimble. An unpredictable close-quarters nightmare, the Sawtooth rams into other cars and jaws w
...

Sheet СПРАВКА
B1: СПРАВКА ▚ DV · ДИСТАНЦИИ · УКРЫТИЯ · РАНЫ · IP · ЖИЗНЬ · 2070
B3: Ⅰ · СЛОЖНОСТЬ ПРОВЕРОК (DV) · CP:R СТР. 129
B4: СЛОЖНОСТЬ | C4: DV | D4: КОГДА БРОСАТЬ
B5: Simple | C5: 9 | D5: Плюнуть в урну, вспомнить вчерашний разговор, обычная бытовая задача.
B6: Everyday | C6: 13 | D6: Рутинная работа: дешёвый замок, слух на улице, починить провод.
B7: Difficult | C7: 15 | D7: Профессиональная задача: слежка, серьёзный ремонт, взлом двери.
B8: Professional | C8: 17 | D8: Работа специалиста: сложный ремонт, полевая хирургия, взлом системы.
B9: Heroic | C9: 21 | D9: На грани человеческого: выжить в падении, обыграть профи в его деле.
B10: Incredible | C10: 24 | D10: Легендарно: то, о чём будут рассказывать в барах.
B11: Legendary | C11: 29 | D11: Почти невозможно ни для кого.
B13: Ⅱ · ДИСТАНЦИЯ: DV ПО ТИПУ ОРУЖИЯ · CP:R СТР. 172–173
B14: Weapon Type | C14: 0-6 | D14: 7-12 | E14: 13-25 | F14: 26-50 | G14: 51-100 | H14: 101-200 | I14: 201-400 | J14: 401-800
B15: Snubnose Pistol | C15: 12 | D15: 14 | E15: 20 | F15: 26 | G15: 35 | H15: — | I15: — | J15: —
B16: Pistol | C16: 13 | D16: 15 | E16: 20 | F16: 25 | G16: 30 | H16: 35 | I16: — | J16: —
B17: Long Barrel Pistol | C17: 15 | D17: 13 | E17: 14 | F17: 19 | G17: 20 | H17: 22 | I17: 30 | J17: —
B18: Subcompact SMG | C18: 13 | D18: 13 | E18: 14 | F18: 21 | G18: 27 | H18: 30 | I18: — | J18: —
B19: SMG | C19: 15 | D19: 13 | E19: 15 | F19: 20 | G19: 25 | H19: 25 | I19: 30 | J19: —
B20: Short Barrel Shotgun | C20: 12 | D20: 14 | E20: 23 | F20: 27 | G20: 32 | H20: — | I20: — | J20: —
B21: Shotgun | C21: 13 | D21: 15 | E21: 20 | F21: 25 | G21: 30 | H21: 35 | I21: — | J21: —
B22: Long Barrel Shotgun | C22: 14 | D22: 16 | E22: 15 | F22: 18 | G22: 25 | H22: 28 | I22: — | J22: —
B23: Carbine | C23: 16 | D23: 15 | E23: 13 | F23: 15 | G23: 20 | H23: 25 | I23: 30 | J23: —
B24: Assault Rifle | C24: 17 | D24: 16 | E24: 15 | F24: 13 | G24: 15 | H24: 20 | I24: 25 | J24: 30
B25: Battle Rifle | C25: 18 | D25: 16 | E25: 16 | F25: 14 | G25: 14 | H25: 19 | I25: 24 | J25: 29
... B35: Missile Launcher | C35: 30 | D35: 25 | E35: 25 | F35: 20 | G35: 17 | H35: 20 | I35: 20 | J35: 20
B37: Ⅲ · АВТООГОНЬ · ДЕЙСТВИЕ + 10 ПАТРОНОВ + НАВЫК AUTOFIRE
B38: Weapon Type | C38: 0-6 | D38: 7-12 | E38: 13-25 | F38: 26-50 | G38: 51-100 | H38: МАКС. МНОЖИТЕЛЬ
B39: Machine Pistol | C39: 17 | D39: 20 | E39: 22 | F39: 27 | G39: 30 | H39: ×3
B40: SMGs | C40: 20 | D40: 17 | E40: 20 | F40: 25 | G40: 30 | H40: ×3
B41: Assault Rifle | C41: 22 | D41: 20 | E41: 17 | F41: 20 | G41: 25 | H41: ×4
B42: Machine Gun | C42: 21 | D42: 18 | E42: 18 | F42: 19 | G42: 25 | H42: ×4
B43: Урон = 2d6 × (насколько ты превысил DV), но не больше множителя оружия. Две «6» — ещё и крит-травма. Броня гасит урон как обычно. Цели с REF 8+ могут уклоняться. Прицельный выстрел не совместим с автоогнём.
B45: Ⅳ · ПРИЦЕЛЬНЫЕ ВЫСТРЕЛЫ, УКРЫТИЯ, ПОДАВЛЕНИЕ
B46: СИТУАЦИЯ | C46: МОДИФ. | D46: ЧТО ПРОИСХОДИТ
B47: Прицельный выстрел (ROF 1, всё действие) | C47: −8 | D47: Только одна атака. Попадание — эффект по выбранной локации.
B48: …в голову | C48: ×2 урона | D48: Прошедший через броню урон умножается на 2 (при «треснувшем черепе» — на 3).
B49: …в предмет в руках | C49: роняет | D49: Если прошёл хотя бы 1 урон — цель роняет выбранный предмет.
B50: …в ногу | C50: Broken Leg | D50: Если прошёл хотя бы 1 урон — крит-травма «Broken Leg» (если есть целые ноги).
B51: Огонь на подавление | C51: WILL+Concentration | D51: Действие + 10 пуль. Провал — цель обязана уйти за укрытие (иначе Run).
B52: Картечь (Shells) | C52: DV13 | D52: Все видимые цели в квадрате 6×6 м получают 3d6 (один бросок урона на всех).
B53: Взрывчатка | C53: 10×10 м | D53: Один бросок урона на всех в квадрате. Волна не бьёт за укрытием, если оно выдержало.
B54: МАТЕРИАЛ УКРЫТИЯ | C54: ТОНКОЕ | D54: ТОЛСТОЕ | E54: ПРИМЕРЫ / КАК ЧИТАТЬ
B55: Сталь | C55: 25 HP | D55: 50 HP | E55: Дверь машины, грузовой контейнер (тонкий).
B56: Камень | C56: 20 HP | D56: 40 HP | E56: Кирпичная кладка, бетонная тумба.
B57: Пуленепробиваемое стекло | C57: 15 HP | D57: 30 HP | E57: Витрина банка, бронированное окно.
B58: Бетон | C58: 10 HP | D58: 25 HP | E58: Уличный парапет, стена подъезда.
B59: Дерево | C59: 5 HP | D59: 20 HP | E59: Перевёрнутый стол (тонкое), барная стойка (толстое).
B60: Гипс / пена / пластик | C60: 0 HP (не укрытие) | D60: 15 HP | E60: Офисная перегородка.
B61: УКРЫТИЕ НЕ ДАЁТ ШТРАФА К АТАКЕ (ни в Corebook, ни в CEMK): правило бинарное — «ты в укрытии, только если полностью за тем, что может остановить пулю; если враг тебя видит, ты не в укрытии». Попадание уходит в укрытие: участок 2×2 м, у него есть HP (см. таблицу выше). Разрушенное укрытие обрушивается, избыточный урон за ним не идёт (кроме взрывчатки). ЩИТ — подвижное укрытие: пока у него есть HP, ты в укрытии, и весь урон атаки идёт в HP щита; но уклоняться с ним нельзя. Живой щит не защищает от выстрелов в голову и ближнего боя.
B63: Ⅴ · ДЕЙСТВИЯ В ХОДЕ · 1 MOVE ACTION + 1 ДЕЙСТВИЕ
B64: ДЕЙСТВИЕ | C64: ЧТО ДЕЛАЕТ
B65: Move Action | C65: Переместиться на MOVE × 2 м (или на MOVE клеток).
B66: Attack | C66: Ближняя или дальняя атака.
B67: Choke | C67: Только против схваченного врага.
B68: Equip/Drop Shield | C68: Взять или бросить щит — Действие.
B69: Get into a Vehicle | C69: Сесть в транспорт.
B70: Get Up | C70: Подняться из Prone. Пока не встанешь — не двигаешься.
B71: Grab | C71: Схватить врага или предмет в его руках.
B72: Hold Action | C72: Отложить действие: условие, номер инициативы, цель.
B73: Human Shield | C73: Живой щит из схваченного врага (щит с HP = BODY).
B74: Reload | C74: Перезарядить магазин одним типом патронов.
B75: Run | C75: Дополнительное Move Action, если уже двигался в этом ходу.
... B82: Vehicle Maneuver | C82: Полная концентрация на сложном манёвре.
B84: Ⅵ · РАНЫ, СМЕРТЬ, СТАБИЛИЗАЦИЯ
B85: СОСТОЯНИЕ | C85: ПОРОГ | D85: ЭФФЕКТ И СТАБИЛИЗАЦИЯ
B86: Смертельное (Mortally Wounded) | C86: HP < 1 | D86: −4 ко всем действиям, −6 MOVE (мин. 1). В начале хода — спасбросок смерти. Урон атакой: +крит. травма и +1 к штрафу спасброска. · DV15 → 1 HP, без сознания (1 минута)
B87: Серьёзное (Seriously Wounded) | C87: HP ≤ ½ максимума (вверх) | D87: −2 ко всем действиям. · DV13
B88: Лёгкое (Lightly Wounded) | C88: HP < максимума | D88: Эффектов нет. · DV10
B89: Мёртв | C89: Проваленный спасбросок смерти | D89: Ты мёртв. Соболезнуем. · —
B90: Смертельный спасбросок: 1d10 ≤ BODY − штраф. Выпало «10» — провал. Провал = смерть. Крит-травма: два и более «6» на кубах урона → +5 урона напрямую в HP и эффект травмы (таблицы на листе 06).
B92: Ⅶ · IP: СКОЛЬКО СТОИТ РАЗВИТИЕ · CP:R СТР. 408
B93: ЧТО УЛУЧШАЕМ | C93: 1 | D93: 2 | E93: 3 | F93: 4 | G93: 5 | H93: 6 | I93: 7 | J93: 8 | K93: 9 | L93: 10
B94: НАВЫК (20 × уровень) | C94: 20 | D94: 40 | E94: 60 | F94: 80 | G94: 100 | H94: 120 | I94: 140 | J94: 160 | K94: 180 | L94: 200
B95: НАВЫК ×2 (40 × уровень) | C95: 40 | D95: 80 | E95: 120 | F95: 160 | G95: 200 | H95: 240 | I95: 280 | J95: 320 | K95: 360 | L95: 400
B96: РОЛЕВАЯ СПОСОБНОСТЬ (60 × ранг) | C96: 60 | D96: 120 | E96: 180 | F96: 240 | G96: 300 | H96: 360 | I96: 420 | J96: 480 | K96: 540 | L96: 600
B97: Столбцы — НОВЫЙ уровень/ранг. Перескакивать уровни нельзя, даже если IP хватает: сначала надо отыграть на текущем. Улучшения записывай на листе 06 — стоимость посчитается сама.
B98: ОПЫТ: 10 IP — «старались, но не вышло» / боевые навыки/поддержка/исследование/отыгрыш; 20 IP — дело выполнено еле-еле; 30–50 IP — уверенный успех, важные цели, выдающийся отыгрыш. GM выдаёт по стилю игры каждого.
B100: Ⅷ · ЖИЗНЬ, ЖИЛЬЁ, МЕДИЦИНА: ПОЧЁМ В 2070-Х
B101: СТАТЬЯ | C101: ЦЕНА €$ | D101: ПОЯСНЕНИЕ
B102: Lifestyle: Kibble | C102: 100 / мес | D102: Еда-пайка. Стартовый Lifestyle у всех покрыт.
B103: Lifestyle: Generic Prepak | C103: 300 / мес | D103: Нормальная еда, вечер в хорошем баре.
B104: Lifestyle: Good Prepak | C104: 600 / мес | D104: Еда как в ресторане, концерты раз в месяц.
B105: Lifestyle: Fresh Food | C105: 1 500 / мес | D105: Настоящая еда, отель без счёта, executive-бар.
B106: Жильё: Cube Hotel | C106: 500 / мес | D106: Капсула. Ежемесячный срез Humanity по CEMK.
B107: Жильё: Cargo Container | C107: 1 000 / мес | D107: Стартовое жильё (первый месяц бесплатно).
B108: Жильё: Studio Apartment | C108: 1 500 / мес | D108: Обычная квартира — как у команды в мегабашне VEX (Rent).
B109: Trauma Team Silver | C109: 500 / год | D109: Подписка: привозят в больницу и стабилизируют.
B110: Trauma Team Executive | C110: 1 000 / год | D110: Плюс лечение и VIP-палата.
B111: Hospital Treatment DV10/13/15/17+ | C111: 50 / 100 / 500 / 1 000 | D111: Больничная помощь по сложности ранения.
B112: Терапия: Standard HL | C112: 500 + 100 материалов | D112: Неделя, Medical Tech DV15, возврат 2d6 Humanity.
... B117: Продать лут (Streetwise) | C117: ×½ цены | D117: Скупка за половину; редкое — через Fixer.
B119: Ⅸ · 2070-Е: ЧТО РАБОТАЕТ ИНАЧЕ (CEMK «THE 2070s IN CYBERPUNK RED»)
B121: 1. NEUROPORT: при создании можно поставить бесплатно — 0 €$, 0 HL, максимум Humanity не режется. Любой немедицинский хром требует Neuroport.
B122: 2. РОЛИ В 2070-Х: Fixer достаёт дорогие вещи поштучно с ранга 1 (на ранге 4 — Very Expensive, 7 — Luxury, 9 — Super Luxury). Exec/Media/Rockerboy/Lawman — с ранга 4. Nomad — любые транспорт и апгрейды с ранга 1 (Moto).
B123: 3. НЕТРАННЕРЫ: Quickhack по хрому — Simple (DV6) с ранга 1, Standard (DV8) — 2, Difficult (DV10) — 3, Advanced (DV12) — 4. Scanner стал NET-действием, а на ранге 3 Interface нейропорты вскрываются без проверки.
B124: 4. ДОСТУПНОСТЬ: почти всё можно купить напрямую у производителя, но по двойной цене (кроме уникального/кастомного).
B125: 5. МЕНТАЛЬНАЯ ТРАВМА: Humanity меняется не только от хрома — события и месяцы жизни режут или возвращают её (см. лист 04).
B127: Ⅹ · LAWMAN · BACKUP: ВЫЗОВ ПОДКРЕПЛЕНИЯ · CP:R СТР. 158–159
B128: РАНГ BACKUP | C128: БОЕВОЙ № | D128: SP | E128: HP | F128: MOVE / BODY | G128: КТО ПРИЕДЕТ
B129: 1–2 | C129: 8 | D129: 7 | E129: 20 | F129: 4 / 4 | G129: Корпоративная охрана: 4 прокат-копа, пешком. Heavy Pistols, Kevlar.
B130: 3–4 | C130: 10 | D130: 7 | E130: 25 | F130: 5 / 5 | G130: Патрульные: 4 копа на двух Compact Groundcar. Heavy Pistols, Kevlar.
...

Sheet ПРАВИЛА
B1: КАК ПОЛЬЗОВАТЬСЯ ЭТИМ ЛИСТОМ ▚ NC//NET · НАЙТ-СИТИ 2070
B4: Ⅰ · ГЛАВНОЕ ПРО ЦВЕТА И ЛОГИКУ
B5: Жёлтые поля | C5: Сюда пишешь ты. Свободный ввод: имена, отыгрыш, отряды оружия, патроны, даты.
B6: Серо-синие поля | C6: Считается само. Можно перебить своим значением — формула заменится цифрой.
B7: Красные и «⚠» | C7: Проверки: перерасход бюджета, лишние очки, киберпсихоз, превышение ранга роли.
B8: Лист 01 ДОСЬЕ | C8: Первый лист — история персонажа: имя, роль, психопрофиль, связи, работа соло. Служебная сводка внизу тянет цифры с остальных листов. Это то, что читает GM.
B9: Лист 02 ОСНОВА | C9: Характеристики (62 очка), производные (HP, Humanity, инициатива), ролевая способность — Combat Awareness (Solo) и таблица Backup (Lawman), оружие в руках, броня и памятка бойца.
B10: Лист 03 НАВЫКИ | C10: 66 навыков из гайда + 6 свободных строк. Пишешь только уровень — база (уровень + стата с учётом штрафа брони) считается сама. Внизу проверка обязательных 13 и максимума 6.
B11: Лист 04 ХРОМ | C11: Импланты: HL по среднему, срез максимума Humanity, клиника, слоты. Здесь же Humanity, терапия и ментальная травма 2070-х.
B12: Лист 05 СНАРЯЖЕНИЕ | C12: Стартовый бюджет 2550 + 800 на стиль. Траты копятся из трёх мест: инвентарь (Ⅲ), броня (Ⅱ) и установленный хром с листа 04 — дубли не считаются. Ниже касса кампании: доходы, траты, баланс.
B13: Лист 06 СОСТОЯНИЕ | C13: Раны, крит-травмы (выбери локацию и бросок 2d6 — травма подтянется), зависимости, IP и лог дел. Здесь же таблицы крит-травм для стола.
B14: КАТАЛОГ / СПРАВКА / ПРАВИЛА | C14: Каталог 1092 позиций из Data Pool и справочник DV/укрытий/IP. Эти листы не правь — на них ссылаются формулы.
B16: Ⅱ · ШАГИ СОЗДАНИЯ ПЕРСОНАЖА (ГАЙД SPES DESPERATA)
B17: 1. Роль | C17: Lawman (коп в отставке) — ролевая способность Backup; Solo — Combat Awareness. На старте ранг роли 4. Обязательный пакет роли — 7 навыков минимум по 2 (лист 03, блок Ⅱ).
B18: 2. Lifepath | C18: Общий (CP:R стр. 45) + ролевой: Lawman — стр. 36 (должность, юрисдикция, коррумпированность, враг, цель), Solo — стр. 53. Результаты — на лист 01 ДОСЬЕ.
B19: 3. Характеристики | C19: 62 очка на 10 стат, каждая от 2 до 8. Рабочий приём: по 6 везде, потом 2 лишних по вкусу.
B20: 4. Производные | C20: HP = 10 + 5 × ⌈(BODY+WILL)/2⌉, порог серьёзного ранения — половина HP вверх, спасбросок = BODY, Humanity = EMP × 10. Всё считается на листе 02.
B21: 5. Навыки | C21: 86 очков: 26 в 13 обязательных (по 2) + 60 свободных, максимум 6. Родной язык — 4 уровня бесплатно. Навыки с ×2 стоят 2 очка за уровень.
B22: 6. Закупка | C22: 2550 €$ на оружие, броню, снаряжение и хром + 800 €$ на Fashion и Fashionware. Бюджет считается сам: инвентарь + броня + установленный хром; Neuroport при создании бесплатен (0 €$, 0 HL). Неиспользованное сгорает.
B23: 7. Lifestyle | C23: Kibble (100 €$/мес) и жильё покрыты. Дальше платишь сам — см. СПРАВКУ.
B25: Ⅲ · LAWMAN В 2070-Х: КОП ВНЕ СИСТЕМЫ
B26: Backup — твой козырь | C26: Ранг роли = шанс дозвониться. Действие, 1d10 ≤ ранга, приезд через 1d6 раундов; «6» на d6 — тир выше. Таблица тиров — на листах 02 и СПРАВКА.
B27: Цена отставки | C27: Отставной коп зовёт только тех, с кем сохранил отношения, и только когда действительно надо: частые вызовы = штраф или разжалование. Взамен — свобода работать вне приказов и доступ к старым базам данных.
B28: Навыки копа | C28: Criminology, Deduction, Interrogation, Tracking — расследование; Autofire (×2), Handgun, Shoulder Arms — стволы; плюс социальные (Conversation, Human Perception, Persuasion, Bribery), чтобы говорить с улицей и с управлением.
B29: Роль в команде | C29: Ты — тот, кто читает место преступления, держит допрос и приводит подкрепление, когда всё пошло не так. Броня и ствол у тебя как у «стены», но решать дело ты можешь и языком.
B31: Ⅳ · SOLO В 2070-Х: ЧТО ДЕРЖАТЬ В ГОЛОВЕ
B32: Combat Awareness | C32: Свободно распределяешь очки ранга между шестью способностями: до боя, вне боя и — за Действие — в бою. Расклад на листе 02, там же счётчик вложенного.
B33: Загрузка под задачу | C33: Перед штурмом — Precision Attack, в обороне — Damage Deflection, на разведке — Threat Detection. Не забывай менять расклад под сцену.
B34: Что чаще всего нужно | C34: Autofire и Shoulder Arms для тяжёлых целей, Handgun всегда с собой, Interrogation и Resist Torture/Drugs — рабочие навыки наёмника, Tactics — чтобы читать поле боя.
B35: Роль в команде | C35: Ты — тот, кто держит линию огня, читает засады и вытаскивает раненых. Твоя броня и SP — аргумент в переговорах; твоя Humanity — цена за хром.
B37: Ⅳ · ЕСЛИ ЧТО-ТО СЛОМАЛОСЬ
B38: Появилась вещь не из каталога | C38: Впиши название вручную, а цену — в столбец «ЦЕНА СВОЯ»: сумма и бюджет посчитаются по ней.
B39: Добавляешь строки | C39: Вставляй строки ВНУТРИ таблиц (не вместо заголовков) — тогда формулы и суммы подтянутся. Если что-то поехало — сверься с адресами в шапке блоков.
B40: Не переименовывай листы | C40: Формулы ссылаются на «02 ОСНОВА», «04 ХРОМ» и остальные листы по именам.
B41: Хочешь больше автоподстановки | C41: Расширь КАТАЛОГ: добавь строку с тем же порядком столбцов, и подстановка заработает.
B43: Ⅴ · ИСТОЧНИКИ
B44: Cyberpunk RED Corebook | C44: Создание персонажа (стр. 73–89), навыки (стр. 86–90), броня и оружие (стр. 340–351), бой (стр. 170–190), терапия (стр. 229), IP (стр. 408), Lifestyle (стр. 377).
B45: Cyberpunk: Edgerunners Mission Kit | C45: Правила 2070-х: Neuroport (стр. 26, 35), твики ролей, расширенная доступность, ментальная травма (стр. 28–30).
B46: Гайд «Spes Desperata» | C46: Порядок создания, 62/86, must-have навыки по ролям, закупка, Lifestyle — используется в кампании.
B47: Дисклеймер | C47: Это домашний лист для вашей кампании. Если у стола свои дом-правила — правь смело: формулы простые, все правила лежат рядом.
